Workbook

Sheet 2 months
B1: Member's Name: | C1: Sheila Mae Peñarubia | I1: Loan Amount: | J1: 50000 | L1: Member's Name: | M1: Sheila Mae Peñarubia | S1: Loan Amount: | T1: 50000
B2: Membership Number: | I2: Date | J2: 3/2/23 | L2: Membership Number: | S2: Date | T2: 3/2/23
B3: No. of Loan's Made: | I3: Interest Rate: | J3: 0.015 | L3: No. of Loan's Made: | P3: Interest Rate: | S3: Interest Rate: | T3: 0.015
B4: Mode of Payment: | I4: No. of months to Pay | J4: 2 | L4: Mode of Payment: | O4: No. of Months to Pay: | S4: No. of months to Pay | T4: 2
B5: Payment's Made | C5: Present Capital Loan | D5: Constant Payment Deducted to Capital Loan | E5: Interest Amount per Payment | F5: Amount to be Paid | G5: Paid Amount | H5: Date of Payment | I5: Receipt Number | J5: REMARKS | L5: Payment's Made | M5: Present Capital Loan | N5: Constant Payment Deducted to Capital Loan | O5: Interest Amount per Payment | P5: Amount to be Paid | Q5: Paid Amount | R5: Date of Payment | S5: Receipt Number | T5: REMARKS
B6: 1st Payment: | C6: =J1 -> 50000 | D6: =J1/J4 -> 25000 | E6: =(C6*0.015) -> 750 | F6: ='24 mos'!$C$255+E6 -> 100750 | L6: 1st Payment: | M6: =T1 -> 50000 | N6: =T1/T4 -> 25000 | O6: =(M6*0.015) -> 750 | P6: ='24 mos'!$C$255+O6 -> 100750
B7: 2nd Payment: | C7: 25000 | D7: 25000 | E7: =(C7*0.015) -> 375 | F7: ='24 mos'!$C$255+E7 -> 100375 | J7: Fully Paid | L7: 2nd Payment: | M7: 25000 | N7: 25000 | O7: =(M7*0.015) -> 375 | P7: ='24 mos'!$C$255+O7 -> 100375 | T7: Fully Paid
B10: Member's Name: | C10: Velasco, Virgilia | F10: (EMERGENCY LOAN) | I10: Loan Amount: | J10: 20000 | L10: Member's Name: | M10: Velasco, Virgilia | P10: (EMERGENCY LOAN) | S10: Loan Amount: | T10: 20000
B11: Membership Number: | I11: Date: | J11: 2/5/2025 | L11: Membership Number: | S11: Date: | T11: 2/5/2025
B12: No. of Loan's Made: | I12: Interest Rate: | J12: 0.015 | L12: No. of Loan's Made: | S12: Interest Rate: | T12: 0.015
B13: Mode of Payment: | I13: No. of Months to Pay: | J13: 2 | L13: Mode of Payment: | S13: No. of Months to Pay: | T13: 2
B14: Payment's Made | C14: Present Capital Loan | D14: Constant Payment Deducted to Capital Loan | E14: Interest Amount per Payment | F14: Amount to be Paid | G14: Paid Amount | H14: Date of Payment | I14: Receipt Number | J14: REMARKS | L14: Payment's Made | M14: Present Capital Loan | N14: Constant Payment Deducted to Capital Loan | O14: Interest Amount per Payment | P14: Amount to be Paid | Q14: Paid Amount | R14: Date of Payment | S14: Receipt Number | T14: REMARKS
B15: 1st Payment: | C15: =J10 -> 20000 | D15: =J10/J13 -> 10000 | E15: =(C15*0.015) -> 300 | F15: =SUM(D15:E15) -> 10300 | L15: 1st Payment: | M15: =T10 -> 20000 | N15: =T10/T13 -> 10000 | O15: =(M15*0.015) -> 300 | P15: =SUM(N15:O15) -> 10300
B16: 2nd Payment: | C16: 10000 | D16: 10000 | E16: =(C16*0.015) -> 150 | F16: =SUM(D16:E16) -> 10150 | J16: Fully Paid | L16: 2nd Payment: | M16: 10000 | N16: 10000 | O16: =(M16*0.015) -> 150 | P16: =SUM(N16:O16) -> 10150 | T16: Fully Paid
B19: Member's Name: | C19: Macabare, Ronnie | F19: Emergency Loan | H19: Loan Amount: | J19: 5000 | L19: Member's Name: | M19: Macabare, Ronnie | P19: Emergency Loan | R19: Loan Amount: | T19: 5000
B20: Membership Number: | I20: Date: | J20: 4/22/2024 | L20: Membership Number: | S20: Date: | T20: 4/22/2024
B21: No. of Loan's Made: | F21: Interest Rate: | J21: 0.015 | L21: No. of Loan's Made: | P21: Interest Rate: | T21: 0.015
B22: Mode of Payment: | E22: No. of Months to Pay: | J22: 2 | L22: Mode of Payment: | O22: No. of Months to Pay: | T22: 2
B23: Payment's Made | C23: Present Capital Loan | D23: Constant Payment Deducted to Capital Loan | E23: Interest Amount per Payment | F23: Amount to be Paid | G23: Paid Amount | H23: Date of Payment | I23: Receipt Number | J23: REMARKS | L23: Payment's Made | M23: Present Capital Loan | N23: Constant Payment Deducted to Capital Loan | O23: Interest Amount per Payment | P23: Amount to be Paid | Q23: Paid Amount | R23: Date of Payment | S23: Receipt Number | T23: REMARKS
B24: 1st Payment: | C24: =J19 -> 5000 | D24: =J19/J22 -> 2500 | E24: =(C24*0.015) -> 75 | F24: =SUM(D24:E24) -> 2575 | L24: 1st Payment: | M24: =T19 -> 5000 | N24: =T19/T22 -> 2500 | O24: =(M24*0.015) -> 75 | P24: =SUM(N24:O24) -> 2575
B25: 2nd Payment: | C25: 2500 | D25: 2500 | E25: =(C25*0.015) -> 37.5 | F25: =SUM(D25:E25) -> 2537.5 | J25: Fully Paid | L25: 2nd Payment: | M25: 2500 | N25: 2500 | O25: =(M25*0.015) -> 37.5 | P25: =SUM(N25:O25) -> 2537.5 | T25: Fully Paid

Sheet 1 month
B1: Member's Name: | C1: Virgilia Velasco | H1: Loan Amount: | J1: 20000 | L1: Member's Name: | M1: Virgilia Velasco | R1: Loan Amount: | T1: 20000
B2: Membership Number: | I2: Date: | J2: 5/3/23 | L2: Membership Number: | S2: Date: | T2: 5/3/23
B3: No. of Loan's Made: | F3: Interest Rate: | J3: 0.015 | L3: No. of Loan's Made: | P3: Interest Rate: | T3: 0.015
B4: Mode of Payment: | E4: No. of Months to Pay: | J4: 1 | L4: Mode of Payment: | O4: No. of Months to Pay: | T4: 1
B5: Payment's Made | C5: Present Capital Loan | D5: Constant Payment Deducted to Capital Loan | E5: Interest Amount per Payment | F5: Amount to be Paid | G5: Paid Amount | H5: Date of Payment | I5: Receipt Number | J5: REMARKS | L5: Payment's Made | M5: Present Capital Loan | N5: Constant Payment Deducted to Capital Loan | O5: Interest Amount per Payment | P5: Amount to be Paid | Q5: Paid Amount | R5: Date of Payment | S5: Receipt Number | T5: REMARKS
B6: 1st Payment: | C6: =J1 -> 20000 | D6: =J1/J4 -> 20000 | E6: =(C6*0.015) -> 300 | F6: ='24 mos'!$C$255+E6 -> 100300 | J6: Fully Paid | L6: 1st Payment: | M6: =T1 -> 20000 | N6: =T1/T4 -> 20000 | O6: =(M6*0.015) -> 300 | P6: ='24 mos'!$C$255+O6 -> 100300 | T6: Fully Paid
B9: Member's Name: | C9: Acala, Aimee | I9: Loan Amount: | J9: 10000 | L9: Member's Name: | M9: Acala, Aimee | S9: Loan Amount: | T9: 10000
B10: Membership Number: | I10: Date: | J10: 11/30/23 | L10: Membership Number: | S10: Date: | T10: 11/30/23
B11: No. of Loan's Made: | I11: Interest Rate: | J11: 0.015 | L11: No. of Loan's Made: | S11: Interest Rate: | T11: 0.015
B12: Mode of Payment: | I12: No. of Months to Pay: | J12: 1 | L12: Mode of Payment: | S12: No. of Months to Pay: | T12: 1
B13: Payment's Made | C13: Present Capital Loan | D13: Constant Payment Deducted to Capital Loan | E13: Interest Amount per Payment | F13: Amount to be Paid | G13: Paid Amount | H13: Date of Payment | I13: Receipt Number | J13: REMARKS | L13: Payment's Made | M13: Present Capital Loan | N13: Constant Payment Deducted to Capital Loan | O13: Interest Amount per Payment | P13: Amount to be Paid | Q13: Paid Amount | R13: Date of Payment | S13: Receipt Number | T13: REMARKS
B14: 1st Payment: | C14: =J9 -> 10000 | D14: =J9/J12 -> 10000 | E14: =(C14*0.015) -> 150 | F14: ='24 mos'!$C$255+E14 -> 100150 | J14: Fully Paid | L14: 1st Payment: | M14: =T9 -> 10000 | N14: =T9/T12 -> 10000 | O14: =(M14*0.015) -> 150 | P14: ='24 mos'!$C$255+O14 -> 100150 | T14: Fully Paid
B17: Member's Name: | I17: Loan Amount: | J17: 30000 | L17: Member's Name: | S17: Loan Amount: | T17: 30000
B18: Membership Number: | I18: Date: | L18: Membership Number: | S18: Date:
B19: No. of Loan's Made: | I19: Interest Rate: | J19: 0.015 | L19: No. of Loan's Made: | S19: Interest Rate: | T19: 0.015
B20: Mode of Payment: | I20: No. of Months to Pay: | J20: 1 | L20: Mode of Payment: | S20: No. of Months to Pay: | T20: 1
B21: Payment's Made | C21: Present Capital Loan | D21: Constant Payment Deducted to Capital Loan | E21: Interest Amount per Payment | F21: Amount to be Paid | G21: Paid Amount | H21: Date of Payment | I21: Receipt Number | J21: REMARKS | L21: Payment's Made | M21: Present Capital Loan | N21: Constant Payment Deducted to Capital Loan | O21: Interest Amount per Payment | P21: Amount to be Paid | Q21: Paid Amount | R21: Date of Payment | S21: Receipt Number | T21: REMARKS
B22: 1st Payment: | C22: =J17 -> 30000 | D22: =J17/J20 -> 30000 | E22: =(C22*0.015) -> 450 | F22: ='24 mos'!$C$255+E22 -> 100450 | J22: Fully Paid | L22: 1st Payment: | M22: =T17 -> 30000 | N22: =T17/T20 -> 30000 | O22: =(M22*0.015) -> 450 | P22: ='24 mos'!$C$255+O22 -> 100450 | T22: Fully Paid
B24: Member's Name: | C24: Tangtang, Neddie | F24: Emergency Loan | I24: Loan Amount: | J24: 5000 | L24: Member's Name: | M24: Tangtang, Neddie | P24: Emergency Loan | S24: Loan Amount: | T24: 5000
B25: Membership Number: | I25: Date: | J25: 6/21/2025 | L25: Membership Number: | S25: Date: | T25: 6/21/2025
B26: No. of Loan's Made: | I26: Interest Rate: | J26: 0.015 | L26: No. of Loan's Made: | S26: Interest Rate: | T26: 0.015
B27: Mode of Payment: | I27: No. of Months to Pay: | J27: 1 | L27: Mode of Payment: | S27: No. of Months to Pay: | T27: 1
B28: Payment's Made | C28: Present Capital Loan | D28: Constant Payment Deducted to Capital Loan | E28: Interest Amount per Payment | F28: Amount to be Paid | G28: Paid Amount | H28: Date of Payment | I28: Receipt Number | J28: REMARKS | L28: Payment's Made | M28: Present Capital Loan | N28: Constant Payment Deducted to Capital Loan | O28: Interest Amount per Payment | P28: Amount to be Paid | Q28: Paid Amount | R28: Date of Payment | S28: Receipt Number | T28: REMARKS
B29: 1st Payment: | C29: =J24 -> 5000 | D29: =J24/J27 -> 5000 | E29: =(C29*0.015) -> 75 | F29: =SUM(D29:E29) -> 5075 | J29: Fully Paid | L29: 1st Payment: | M29: =T24 -> 5000 | N29: =T24/T27 -> 5000 | O29: =(M29*0.015) -> 75 | P29: =SUM(N29:O29) -> 5075 | T29: Fully Paid

Sheet 18
B1: Member's Name: | C1: De Gracia, April | I1: Loan Amount: | J1: 50000 | L1: Member's Name: | M1: De Gracia, April | S1: Loan Amount: | T1: 50000
B2: Membership Number: | I2: Date: | J2: 6/13/2025 | L2: Membership Number: | S2: Date: | T2: 6/13/2025
B3: No. of Loan's Made: | I3: Interest Rate: | J3: 0.015 | L3: No. of Loan's Made: | S3: Interest Rate: | T3: 0.015
B4: Mode of Payment: | I4: No. of Months to Pay: | J4: 18 | L4: Mode of Payment: | S4: No. of Months to Pay: | T4: 18
B5: Payment's Made | C5: Present Capital Loan | D5: Constant Payment Deducted to Capital Loan | E5: Interest Amount per Payment | F5: Amount to be Paid | G5: Paid Amount | H5: Date of Payment | I5: Receipt Number | J5: REMARKS | L5: Payment's Made | M5: Present Capital Loan | N5: Constant Payment Deducted to Capital Loan | O5: Interest Amount per Payment | P5: Amount to be Paid | Q5: Paid Amount | R5: Date of Payment | S5: Receipt Number | T5: REMARKS
B6: 1st Payment: | C6: =J1 -> 50000 | D6: 2778 | E6: =(C6*0.015) -> 750 | F6: =SUM(D6:E6) -> 3528 | L6: 1st Payment: | M6: =T1 -> 50000 | N6: 2778 | O6: =(M6*0.015) -> 750 | P6: =SUM(N6:O6) -> 3528
B7: 2nd Payment: | C7: 47226 | D7: 2778 | E7: =(C7*0.015) -> 708.39 | F7: =SUM(D7:E7) -> 3486.39 | L7: 2nd Payment: | M7: 47226 | N7: 2778 | O7: =(M7*0.015) -> 708.39 | P7: =SUM(N7:O7) -> 3486.39
B8: 3rd Payment: | C8: 44448 | D8: 2778 | E8: =(C8*0.015) -> 666.72 | F8: =SUM(D8:E8) -> 3444.72 | L8: 3rd Payment: | M8: 44448 | N8: 2778 | O8: =(M8*0.015) -> 666.72 | P8: =SUM(N8:O8) -> 3444.72
B9: 4th Payment: | C9: 41670 | D9: 2778 | E9: =(C9*0.015) -> 625.05 | F9: =SUM(D9:E9) -> 3403.05 | L9: 4th Payment: | M9: 41670 | N9: 2778 | O9: =(M9*0.015) -> 625.05 | P9: =SUM(N9:O9) -> 3403.05
B10: 5th Payment: | C10: 38892 | D10: 2778 | E10: =(C10*0.015) -> 583.38 | F10: =SUM(D10:E10) -> 3361.38 | L10: 5th Payment: | M10: 38892 | N10: 2778 | O10: =(M10*0.015) -> 583.38 | P10: =SUM(N10:O10) -> 3361.38
B11: 6th Payment: | C11: 36114 | D11: 2778 | E11: =(C11*0.015) -> 541.71 | F11: =SUM(D11:E11) -> 3319.71 | L11: 6th Payment: | M11: 36114 | N11: 2778 | O11: =(M11*0.015) -> 541.71 | P11: =SUM(N11:O11) -> 3319.71
B12: 7th Payment: | C12: 33336 | D12: 2778 | E12: =(C12*0.015) -> 500.04 | F12: =SUM(D12:E12) -> 3278.04 | L12: 7th Payment: | M12: 33336 | N12: 2778 | O12: =(M12*0.015) -> 500.04 | P12: =SUM(N12:O12) -> 3278.04
B13: 8th Payment: | C13: 30558 | D13: 2778 | E13: =(C13*0.015) -> 458.37 | F13: =SUM(D13:E13) -> 3236.37 | L13: 8th Payment: | M13: 30558 | N13: 2778 | O13: =(M13*0.015) -> 458.37 | P13: =SUM(N13:O13) -> 3236.37
B14: 9th Payment: | C14: 27780 | D14: 2778 | E14: =(C14*0.015) -> 416.7 | F14: =SUM(D14:E14) -> 3194.7 | L14: 9th Payment: | M14: 27780 | N14: 2778 | O14: =(M14*0.015) -> 416.7 | P14: =SUM(N14:O14) -> 3194.7
B15: 10th Payment: | C15: 25002 | D15: 2778 | E15: =(C15*0.015) -> 375.03 | F15: =SUM(D15:E15) -> 3153.03 | L15: 10th Payment: | M15: 25002 | N15: 2778 | O15: =(M15*0.015) -> 375.03 | P15: =SUM(N15:O15) -> 3153.03
B16: 11th Payment: | C16: 22224 | D16: 2778 | E16: =(C16*0.015) -> 333.36 | F16: =SUM(D16:E16) -> 3111.36 | L16: 11th Payment: | M16: 22224 | N16: 2778 | O16: =(M16*0.015) -> 333.36 | P16: =SUM(N16:O16) -> 3111.36
B17: 12th Payment: | C17: 19446 | D17: 2778 | E17: =(C17*0.015) -> 291.69 | F17: =SUM(D17:E17) -> 3069.69 | L17: 12th Payment: | M17: 19446 | N17: 2778 | O17: =(M17*0.015) -> 291.69 | P17: =SUM(N17:O17) -> 3069.69
B18: 13th Payment: | C18: 16668 | D18: 2778 | E18: =(C18*0.015) -> 250.02 | F18: =SUM(D18:E18) -> 3028.02 | L18: 13th Payment: | M18: 16668 | N18: 2778 | O18: =(M18*0.015) -> 250.02 | P18: =SUM(N18:O18) -> 3028.02
... B22: 17th Payment: | C22: 5556 | D22: 2778 | E22: =(C22*0.015) -> 83.34 | F22: =SUM(D22:E22) -> 2861.34 | L22: 17th Payment: | M22: 5556 | N22: 2778 | O22: =(M22*0.015) -> 83.34 | P22: =SUM(N22:O22) -> 2861.34
B23: 18th Payment: | C23: 2778 | D23: 2778 | E23: =(C23*0.015) -> 41.67 | F23: =SUM(D23:E23) -> 2819.67 | J23: Fully paid | L23: 18th Payment: | M23: 2778 | N23: 2778 | O23: =(M23*0.015) -> 41.67 | P23: =SUM(N23:O23) -> 2819.67 | T23: Fully paid

Sheet 3 mos
B1: Member's Name: | C1: Macayan, Nenita | I1: Loan Amount: | J1: 50000 | L1: Member's Name: | M1: Macayan, Nenita | S1: Loan Amount: | T1: 50000
B2: Membership Number: | I2: Date: | J2: 7/14/2025 | L2: Membership Number: | S2: Date: | T2: 7/14/2025
B3: No. of Loan's Made: | I3: Interest Rate: | J3: 0.015 | L3: No. of Loan's Made: | S3: Interest Rate: | T3: 0.015
B4: Mode of Payment: | I4: No. of Months to Pay: | J4: 3 | L4: Mode of Payment: | S4: No. of Months to Pay: | T4: 3
B5: Payment's Made | C5: Present Capital Loan | D5: Constant Payment Deducted to Capital Loan | E5: Interest Amount per Payment | F5: Amount to be Paid | G5: Paid Amount | H5: Date of Payment | I5: Receipt Number | J5: REMARKS | L5: Payment's Made | M5: Present Capital Loan | N5: Constant Payment Deducted to Capital Loan | O5: Interest Amount per Payment | P5: Amount to be Paid | Q5: Paid Amount | R5: Date of Payment | S5: Receipt Number | T5: REMARKS
B6: 1st Payment: | C6: =J1 -> 50000 | D6: =J1/J4 -> 16666.667 | E6: =(C6*0.015) -> 750 | F6: =SUM(D6:E6) -> 17416.667 | L6: 1st Payment: | M6: =T1 -> 50000 | N6: =T1/T4 -> 16666.667 | O6: =(M6*0.015) -> 750 | P6: =SUM(N6:O6) -> 17416.667
B7: 2nd Payment: | C7: 33334 | D7: 16667 | E7: =(C7*0.015) -> 500.01 | F7: =SUM(D7:E7) -> 17167.01 | L7: 2nd Payment: | M7: 33334 | N7: 16667 | O7: =(M7*0.015) -> 500.01 | P7: =SUM(N7:O7) -> 17167.01
B8: 3rd Payment: | C8: 16667 | D8: 16667 | E8: =(C8*0.015) -> 250.005 | F8: =SUM(D8:E8) -> 16917.005 | J8: Fully Paid | L8: 3rd Payment: | M8: 16667 | N8: 16667 | O8: =(M8*0.015) -> 250.005 | P8: =SUM(N8:O8) -> 16917.005 | T8: Fully Paid
B11: Member's Name: | C11: Dela Peña, Benita | F11: (EMERGENCY LOAN) | I11: Loan Amount: | J11: 20000 | L11: Member's Name: | M11: Dela Peña, Benita | P11: (EMERGENCY LOAN) | S11: Loan Amount: | T11: 20000
B12: Membership Number: | I12: Date: | J12: 2/18/2025 | L12: Membership Number: | S12: Date: | T12: 2/18/2025
B13: No. of Loan's Made: | I13: Interest Rate: | J13: 0.015 | L13: No. of Loan's Made: | S13: Interest Rate: | T13: 0.015
B14: Mode of Payment: | I14: No. of Months to Pay: | J14: 3 | L14: Mode of Payment: | S14: No. of Months to Pay: | T14: 3
B15: Payment's Made | C15: Present Capital Loan | D15: Constant Payment Deducted to Capital Loan | E15: Interest Amount per Payment | F15: Amount to be Paid | G15: Paid Amount | H15: Date of Payment | I15: Receipt Number | J15: REMARKS | L15: Payment's Made | M15: Present Capital Loan | N15: Constant Payment Deducted to Capital Loan | O15: Interest Amount per Payment | P15: Amount to be Paid | Q15: Paid Amount | R15: Date of Payment | S15: Receipt Number | T15: REMARKS
B16: 1st Payment: | C16: =J11 -> 20000 | D16: =J11/J14 -> 6666.6667 | E16: =(C16*0.015) -> 300 | F16: =SUM(D16:E16) -> 6966.6667 | L16: 1st Payment: | M16: =T11 -> 20000 | N16: =T11/T14 -> 6666.6667 | O16: =(M16*0.015) -> 300 | P16: =SUM(N16:O16) -> 6966.6667
B17: 2nd Payment: | C17: 13334 | D17: 6667 | E17: =(C17*0.015) -> 200.01 | F17: =SUM(D17:E17) -> 6867.01 | L17: 2nd Payment: | M17: 13334 | N17: 6667 | O17: =(M17*0.015) -> 200.01 | P17: =SUM(N17:O17) -> 6867.01
B18: 3rd Payment: | C18: 6667 | D18: 6667 | E18: =(C18*0.015) -> 100.005 | F18: =SUM(D18:E18) -> 6767.005 | J18: Fully Paid | L18: 3rd Payment: | M18: 6667 | N18: 6667 | O18: =(M18*0.015) -> 100.005 | P18: =SUM(N18:O18) -> 6767.005 | T18: Fully Paid
B21: Member's Name: | C21: Mayores, Jenelyn | F21: Emergency Loan | H21: Loan Amount: | J21: 10000 | L21: Member's Name: | M21: Mayores, Jenelyn | P21: Emergency Loan | R21: Loan Amount: | T21: 10000
B22: Membership Number: | I22: Date: | J22: 7/29/2024 | L22: Membership Number: | S22: Date: | T22: 7/29/2024
B23: No. of Loan's Made: | F23: Interest Rate: | J23: 0.015 | L23: No. of Loan's Made: | P23: Interest Rate: | T23: 0.015
B24: Mode of Payment: | E24: No. of Months to Pay: | J24: 3 | L24: Mode of Payment: | O24: No. of Months to Pay: | T24: 3
B25: Payment's Made | C25: Present Capital Loan | D25: Constant Payment Deducted to Capital Loan | E25: Interest Amount per Payment | F25: Amount to be Paid | G25: Paid Amount | H25: Date of Payment | I25: Receipt Number | J25: REMARKS | L25: Payment's Made | M25: Present Capital Loan | N25: Constant Payment Deducted to Capital Loan | O25: Interest Amount per Payment | P25: Amount to be Paid | Q25: Paid Amount | R25: Date of Payment | S25: Receipt Number | T25: REMARKS
B26: 1st Payment: | C26: =J21 -> 10000 | D26: =J21/J24 -> 3333.3333 | E26: =(C26*0.015) -> 150 | F26: =SUM(D26:E26) -> 3483.3333 | L26: 1st Payment: | M26: =T21 -> 10000 | N26: =T21/T24 -> 3333.3333 | O26: =(M26*0.015) -> 150 | P26: =SUM(N26:O26) -> 3483.3333
B27: 2nd Payment: | C27: 6667 | D27: 3333 | E27: =(C27*0.015) -> 100.005 | F27: =SUM(D27:E27) -> 3433.005 | L27: 2nd Payment: | M27: 6667 | N27: 3333 | O27: =(M27*0.015) -> 100.005 | P27: =SUM(N27:O27) -> 3433.005
B28: 3rd Payment: | C28: 3333 | D28: 3333 | E28: =(C28*0.015) -> 49.995 | F28: =SUM(D28:E28) -> 3382.995 | J28: Fully Paid | L28: 3rd Payment: | M28: 3333 | N28: 3333 | O28: =(M28*0.015) -> 49.995 | P28: =SUM(N28:O28) -> 3382.995 | T28: Fully Paid
B31: Member's Name: | C31: Velasco, Virgilia | F31: Emergency Loan | H31: Loan Amount: | J31: 10000 | L31: Member's Name: | M31: Velasco, Virgilia | P31: Emergency Loan | R31: Loan Amount: | T31: 10000
B32: Membership Number: | I32: Date: | J32: 8/10/2024 | L32: Membership Number: | S32: Date: | T32: 8/10/2024
B33: No. of Loan's Made: | F33: Interest Rate: | J33: 0.015 | L33: No. of Loan's Made: | P33: Interest Rate: | T33: 0.015
B34: Mode of Payment: | E34: No. of Months to Pay: | J34: 3 | L34: Mode of Payment: | O34: No. of Months to Pay: | T34: 3
B35: Payment's Made | C35: Present Capital Loan | D35: Constant Payment Deducted to Capital Loan | E35: Interest Amount per Payment | F35: Amount to be Paid | G35: Paid Amount | H35: Date of Payment | I35: Receipt Number | J35: REMARKS | L35: Payment's Made | M35: Present Capital Loan | N35: Constant Payment Deducted to Capital Loan | O35: Interest Amount per Payment | P35: Amount to be Paid | Q35: Paid Amount | R35: Date of Payment | S35: Receipt Number | T35: REMARKS
B36: 1st Payment: | C36: =J31 -> 10000 | D36: =J31/J34 -> 3333.3333 | E36: =(C36*0.015) -> 150 | F36: =SUM(D36:E36) -> 3483.3333 | L36: 1st Payment: | M36: =T31 -> 10000 | N36: =T31/T34 -> 3333.3333 | O36: =(M36*0.015) -> 150 | P36: =SUM(N36:O36) -> 3483.3333
B37: 2nd Payment: | C37: 6666 | D37: 3333 | E37: =(C37*0.015) -> 99.99 | F37: =SUM(D37:E37) -> 3432.99 | L37: 2nd Payment: | M37: 6666 | N37: 3333 | O37: =(M37*0.015) -> 99.99 | P37: =SUM(N37:O37) -> 3432.99
B38: 3rd Payment: | C38: 3333 | D38: 3333 | E38: =(C38*0.015) -> 49.995 | F38: =SUM(D38:E38) -> 3382.995 | J38: Fully Paid | L38: 3rd Payment: | M38: 3333 | N38: 3333 | O38: =(M38*0.015) -> 49.995 | P38: =SUM(N38:O38) -> 3382.995 | T38: Fully Paid
B42: Member's Name: | C42: Crisostomo, Sophia | I42: Loan Amount: | J42: 100000
B43: Membership Number: | I43: Date:
B44: No. of Loan's Made: | I44: Interest Rate: | J44: 0.015
B45: Mode of Payment: | I45: No. of Months to Pay: | J45: 3
B46: Payment's Made | C46: Present Capital Loan | D46: Constant Payment Deducted to Capital Loan | E46: Interest Amount per Payment | F46: Amount to be Paid | G46: Paid Amount | H46: Date of Payment | I46: Receipt Number | J46: REMARKS
B47: 1st Payment: | C47: =J42 -> 100000 | D47: =J42/J45 -> 33333.333 | E47: =(C47*0.015) -> 1500 | F47: =SUM(D47:E47) -> 34833.333 | G47: 20000 | H47: 6/16/2025
B48: 2nd Payment: | C48: 66666 | D48: 33333 | E48: =(C48*0.015) -> 999.99 | F48: =SUM(D48:E48) -> 34332.99 | G48: 30000 | H48: 7/28/2025
B49: 3rd Payment: | C49: 33333 | D49: 33333 | E49: =(C49*0.015) -> 499.995 | F49: =SUM(D49:E49) -> 33832.995 | G49: 10000 | H49: 8/18/2025 | J49: Fully Paid
F50: =SUM(F47:F49) -> 102999.32 | G50: =SUM(G47:G49) -> 60000 | H50: 42999

Sheet 9 mos
B1: Member's Name: | C1: Tuzon, Arlenita | I1: Loan Amount: | J1: 70000 | L1: Member's Name: | M1: Tuzon, Arlenita | S1: Loan Amount: | T1: 70000
B2: Membership Number: | I2: Date: | L2: Membership Number: | S2: Date:
B3: No. of Loan's Made: | I3: Interest Rate: | J3: 0.015 | L3: No. of Loan's Made: | S3: Interest Rate: | T3: 0.015
B4: Mode of Payment: | I4: No. of Months to Pay: | J4: 9 | L4: Mode of Payment: | S4: No. of Months to Pay: | T4: 9
B5: Payment's Made | C5: Present Capital Loan | D5: Constant Payment Deducted to Capital Loan | E5: Interest Amount per Payment | F5: Amount to be Paid | G5: Paid Amount | H5: Date of Payment | I5: Receipt Number | J5: REMARKS | L5: Payment's Made | M5: Present Capital Loan | N5: Constant Payment Deducted to Capital Loan | O5: Interest Amount per Payment | P5: Amount to be Paid | Q5: Paid Amount | R5: Date of Payment | S5: Receipt Number | T5: REMARKS
B6: 1st Payment: | C6: 70000 | D6: =J1/J4 -> 7777.7778 | E6: =(C6*0.015) -> 1050 | F6: =SUM(D6:E6) -> 8827.7778 | L6: 1st Payment: | M6: 70000 | N6: =T1/T4 -> 7777.7778 | O6: =(M6*0.015) -> 1050 | P6: =SUM(N6:O6) -> 8827.7778
B7: 2nd Payment: | C7: 62224 | D7: 7778 | E7: =(C7*0.015) -> 933.36 | F7: =SUM(D7:E7) -> 8711.36 | L7: 2nd Payment: | M7: 62224 | N7: 7778 | O7: =(M7*0.015) -> 933.36 | P7: =SUM(N7:O7) -> 8711.36
B8: 3rd Payment: | C8: 54446 | D8: 7778 | E8: =(C8*0.015) -> 816.69 | F8: =SUM(D8:E8) -> 8594.69 | L8: 3rd Payment: | M8: 54446 | N8: 7778 | O8: =(M8*0.015) -> 816.69 | P8: =SUM(N8:O8) -> 8594.69
B9: 4th Payment: | C9: 46668 | D9: 7778 | E9: =(C9*0.015) -> 700.02 | F9: =SUM(D9:E9) -> 8478.02 | L9: 4th Payment: | M9: 46668 | N9: 7778 | O9: =(M9*0.015) -> 700.02 | P9: =SUM(N9:O9) -> 8478.02
B10: 5th Payment: | C10: 38890 | D10: 7778 | E10: =(C10*0.015) -> 583.35 | F10: =SUM(D10:E10) -> 8361.35 | L10: 5th Payment: | M10: 38890 | N10: 7778 | O10: =(M10*0.015) -> 583.35 | P10: =SUM(N10:O10) -> 8361.35
B11: 6th Payment: | C11: 31112 | D11: 7778 | E11: =(C11*0.015) -> 466.68 | F11: =SUM(D11:E11) -> 8244.68 | L11: 6th Payment: | M11: 31112 | N11: 7778 | O11: =(M11*0.015) -> 466.68 | P11: =SUM(N11:O11) -> 8244.68
B12: 7th Payment: | C12: 23334 | D12: 7778 | E12: =(C12*0.015) -> 350.01 | F12: =SUM(D12:E12) -> 8128.01 | L12: 7th Payment: | M12: 23334 | N12: 7778 | O12: =(M12*0.015) -> 350.01 | P12: =SUM(N12:O12) -> 8128.01
B13: 8th Payment: | C13: 15556 | D13: 7778 | E13: =(C13*0.015) -> 233.34 | F13: =SUM(D13:E13) -> 8011.34 | L13: 8th Payment: | M13: 15556 | N13: 7778 | O13: =(M13*0.015) -> 233.34 | P13: =SUM(N13:O13) -> 8011.34
B14: 9th Payment: | C14: 7778 | D14: 7778 | E14: =(C14*0.015) -> 116.67 | F14: =SUM(D14:E14) -> 7894.67 | L14: 9th Payment: | M14: 7778 | N14: 7778 | O14: =(M14*0.015) -> 116.67 | P14: =SUM(N14:O14) -> 7894.67
B17: Member's Name: | C17: Vega, Divina | I17: Loan Amount: | J17: 100000 | L17: Member's Name: | M17: Vega, Divina | S17: Loan Amount: | T17: 100000
B18: Membership Number: | I18: Date: | J18: 7/29/2025 | L18: Membership Number: | S18: Date: | T18: 7/29/2025
B19: No. of Loan's Made: | I19: Interest Rate: | J19: 0.015 | L19: No. of Loan's Made: | S19: Interest Rate: | T19: 0.015
B20: Mode of Payment: | I20: No. of Months to Pay: | J20: 9 | L20: Mode of Payment: | S20: No. of Months to Pay: | T20: 9
B21: Payment's Made | C21: Present Capital Loan | D21: Constant Payment Deducted to Capital Loan | E21: Interest Amount per Payment | F21: Amount to be Paid | G21: Paid Amount | H21: Date of Payment | I21: Receipt Number | J21: REMARKS | L21: Payment's Made | M21: Present Capital Loan | N21: Constant Payment Deducted to Capital Loan | O21: Interest Amount per Payment | P21: Amount to be Paid | Q21: Paid Amount | R21: Date of Payment | S21: Receipt Number | T21: REMARKS
B22: 1st Payment: | C22: 100000 | D22: =J17/J20 -> 11111.111 | E22: =(C22*0.015) -> 1500 | F22: =SUM(D22:E22) -> 12611.111 | L22: 1st Payment: | M22: 100000 | N22: =T17/T20 -> 11111.111 | O22: =(M22*0.015) -> 1500 | P22: =SUM(N22:O22) -> 12611.111
B23: 2nd Payment: | C23: 88888 | D23: 11111 | E23: =(C23*0.015) -> 1333.32 | F23: =SUM(D23:E23) -> 12444.32 | L23: 2nd Payment: | M23: 88888 | N23: 11111 | O23: =(M23*0.015) -> 1333.32 | P23: =SUM(N23:O23) -> 12444.32
B24: 3rd Payment: | C24: 77777 | D24: 11111 | E24: =(C24*0.015) -> 1166.655 | F24: =SUM(D24:E24) -> 12277.655 | L24: 3rd Payment: | M24: 77777 | N24: 11111 | O24: =(M24*0.015) -> 1166.655 | P24: =SUM(N24:O24) -> 12277.655
B25: 4th Payment: | C25: 66666 | D25: 11111 | E25: =(C25*0.015) -> 999.99 | F25: =SUM(D25:E25) -> 12110.99 | L25: 4th Payment: | M25: 66666 | N25: 11111 | O25: =(M25*0.015) -> 999.99 | P25: =SUM(N25:O25) -> 12110.99
B26: 5th Payment: | C26: 55555 | D26: 11111 | E26: =(C26*0.015) -> 833.325 | F26: =SUM(D26:E26) -> 11944.325 | L26: 5th Payment: | M26: 55555 | N26: 11111 | O26: =(M26*0.015) -> 833.325 | P26: =SUM(N26:O26) -> 11944.325
B27: 6th Payment: | C27: 44444 | D27: 11111 | E27: =(C27*0.015) -> 666.66 | F27: =SUM(D27:E27) -> 11777.66 | L27: 6th Payment: | M27: 44444 | N27: 11111 | O27: =(M27*0.015) -> 666.66 | P27: =SUM(N27:O27) -> 11777.66
B28: 7th Payment: | C28: 33333 | D28: 11111 | E28: =(C28*0.015) -> 499.995 | F28: =SUM(D28:E28) -> 11610.995 | L28: 7th Payment: | M28: 33333 | N28: 11111 | O28: =(M28*0.015) -> 499.995 | P28: =SUM(N28:O28) -> 11610.995
B29: 8th Payment: | C29: 22222 | D29: 11111 | E29: =(C29*0.015) -> 333.33 | F29: =SUM(D29:E29) -> 11444.33 | L29: 8th Payment: | M29: 22222 | N29: 11111 | O29: =(M29*0.015) -> 333.33 | P29: =SUM(N29:O29) -> 11444.33
B30: 9th Payment: | C30: 11111 | D30: 11111 | E30: =(C30*0.015) -> 166.665 | F30: =SUM(D30:E30) -> 11277.665 | L30: 9th Payment: | M30: 11111 | N30: 11111 | O30: =(M30*0.015) -> 166.665 | P30: =SUM(N30:O30) -> 11277.665
F31: =SUM(F22:F30) -> 107499.05

Sheet 6 mos
B1: Member's Name: | C1: Yusingco, Marites | F1: Emergency Loan | H1: Loan Amount: | J1: 15000 | L1: Member's Name: | M1: Yusingco, Marites | P1: Emergency Loan | R1: Loan Amount: | T1: 15000
B2: Membership Number: | I2: Date: | J2: 3/24/2025 | L2: Membership Number: | S2: Date: | T2: 3/24/2025
B3: No. of Loan's Made: | F3: Interest Rate: | J3: 0.015 | L3: No. of Loan's Made: | P3: Interest Rate: | T3: 0.015
B4: Mode of Payment: | E4: No. of Months to Pay: | J4: 6 | L4: Mode of Payment: | O4: No. of Months to Pay: | T4: 6
B5: Payment's Made | C5: Present Capital Loan | D5: Constant Payment Deducted to Capital Loan | E5: Interest Amount per Payment | F5: Amount to be Paid | G5: Paid Amount | H5: Date of Payment | I5: Receipt Number | J5: REMARKS | L5: Payment's Made | M5: Present Capital Loan | N5: Constant Payment Deducted to Capital Loan | O5: Interest Amount per Payment | P5: Amount to be Paid | Q5: Paid Amount | R5: Date of Payment | S5: Receipt Number | T5: REMARKS
B6: 1st Payment: | C6: =J1 -> 15000 | D6: =J1/J4 -> 2500 | E6: =(C6*0.015) -> 225 | F6: =SUM(D6:E6) -> 2725 | L6: 1st Payment: | M6: =T1 -> 15000 | N6: =T1/T4 -> 2500 | O6: =(M6*0.015) -> 225 | P6: =SUM(N6:O6) -> 2725
B7: 2nd Payment: | C7: 12500 | D7: 2500 | E7: =(C7*0.015) -> 187.5 | F7: =SUM(D7:E7) -> 2687.5 | L7: 2nd Payment: | M7: 12500 | N7: 2500 | O7: =(M7*0.015) -> 187.5 | P7: =SUM(N7:O7) -> 2687.5
B8: 3rd Payment: | C8: 10000 | D8: 2500 | E8: =(C8*0.015) -> 150 | F8: =SUM(D8:E8) -> 2650 | L8: 3rd Payment: | M8: 10000 | N8: 2500 | O8: =(M8*0.015) -> 150 | P8: =SUM(N8:O8) -> 2650
B9: 4th Payment: | C9: 7500 | D9: 2500 | E9: =(C9*0.015) -> 112.5 | F9: =SUM(D9:E9) -> 2612.5 | L9: 4th Payment: | M9: 7500 | N9: 2500 | O9: =(M9*0.015) -> 112.5 | P9: =SUM(N9:O9) -> 2612.5
B10: 5th Payment: | C10: 5000 | D10: 2500 | E10: =(C10*0.015) -> 75 | F10: =SUM(D10:E10) -> 2575 | L10: 5th Payment: | M10: 5000 | N10: 2500 | O10: =(M10*0.015) -> 75 | P10: =SUM(N10:O10) -> 2575
B11: 6th Payment: | C11: 2500 | D11: 2500 | E11: =(C11*0.015) -> 37.5 | F11: =SUM(D11:E11) -> 2537.5 | J11: Fully Paid | L11: 6th Payment: | M11: 2500 | N11: 2500 | O11: =(M11*0.015) -> 37.5 | P11: =SUM(N11:O11) -> 2537.5 | T11: Fully Paid
B14: Member's Name: | C14: Batan, Hermelita | H14: Loan Amount: | J14: 200000 | L14: Member's Name: | M14: Batan, Hermelita | R14: Loan Amount: | T14: 200000
B15: Membership Number: | I15: Date: | J15: 4/18/2024 | L15: Membership Number: | S15: Date: | T15: 4/18/2024
B16: No. of Loan's Made: | F16: Interest Rate: | J16: 0.015 | L16: No. of Loan's Made: | P16: Interest Rate: | T16: 0.015
B17: Mode of Payment: | E17: No. of Months to Pay: | J17: 6 | L17: Mode of Payment: | O17: No. of Months to Pay: | T17: 6
B18: Payment's Made | C18: Present Capital Loan | D18: Constant Payment Deducted to Capital Loan | E18: Interest Amount per Payment | F18: Amount to be Paid | G18: Paid Amount | H18: Date of Payment | I18: Receipt Number | J18: REMARKS | L18: Payment's Made | M18: Present Capital Loan | N18: Constant Payment Deducted to Capital Loan | O18: Interest Amount per Payment | P18: Amount to be Paid | Q18: Paid Amount | R18: Date of Payment | S18: Receipt Number | T18: REMARKS
B19: 1st Payment: | C19: =J14 -> 200000 | D19: =J14/J17 -> 33333.333 | E19: =(C19*0.015) -> 3000 | F19: =SUM(D19:E19) -> 36333.333 | L19: 1st Payment: | M19: =T14 -> 200000 | N19: =T14/T17 -> 33333.333 | O19: =(M19*0.015) -> 3000 | P19: =SUM(N19:O19) -> 36333.333
B20: 2nd Payment: | C20: 166665 | D20: 33333 | E20: =(C20*0.015) -> 2499.975 | F20: =SUM(D20:E20) -> 35832.975 | L20: 2nd Payment: | M20: 166665 | N20: 33333 | O20: =(M20*0.015) -> 2499.975 | P20: =SUM(N20:O20) -> 35832.975
B21: 3rd Payment: | C21: 133332 | D21: 33333 | E21: =(C21*0.015) -> 1999.98 | F21: =SUM(D21:E21) -> 35332.98 | L21: 3rd Payment: | M21: 133332 | N21: 33333 | O21: =(M21*0.015) -> 1999.98 | P21: =SUM(N21:O21) -> 35332.98
B22: 4th Payment: | C22: 99999 | D22: 33333 | E22: =(C22*0.015) -> 1499.985 | F22: =SUM(D22:E22) -> 34832.985 | L22: 4th Payment: | M22: 99999 | N22: 33333 | O22: =(M22*0.015) -> 1499.985 | P22: =SUM(N22:O22) -> 34832.985
B23: 5th Payment: | C23: 66666 | D23: 33333 | E23: =(C23*0.015) -> 999.99 | F23: =SUM(D23:E23) -> 34332.99 | L23: 5th Payment: | M23: 66666 | N23: 33333 | O23: =(M23*0.015) -> 999.99 | P23: =SUM(N23:O23) -> 34332.99
B24: 6th Payment: | C24: 33333 | D24: 33333 | E24: =(C24*0.015) -> 499.995 | F24: =SUM(D24:E24) -> 33832.995 | J24: Fully Paid | L24: 6th Payment: | M24: 33333 | N24: 33333 | O24: =(M24*0.015) -> 499.995 | P24: =SUM(N24:O24) -> 33832.995 | T24: Fully Paid
B28: Member's Name: | C28: Malicdem, Elena | H28: Loan Amount: | J28: 20000 | L28: Member's Name: | M28: Malicdem, Elena | R28: Loan Amount: | T28: 20000
B29: Membership Number: | I29: Date: | J29: 4/4/2024 | L29: Membership Number: | S29: Date: | T29: 4/4/2024
B30: No. of Loan's Made: | F30: Interest Rate: | J30: 0.015 | L30: No. of Loan's Made: | P30: Interest Rate: | T30: 0.015
B31: Mode of Payment: | E31: No. of Months to Pay: | J31: 6 | L31: Mode of Payment: | O31: No. of Months to Pay: | T31: 6
B32: Payment's Made | C32: Present Capital Loan | D32: Constant Payment Deducted to Capital Loan | E32: Interest Amount per Payment | F32: Amount to be Paid | G32: Paid Amount | H32: Date of Payment | I32: Receipt Number | J32: REMARKS | L32: Payment's Made | M32: Present Capital Loan | N32: Constant Payment Deducted to Capital Loan | O32: Interest Amount per Payment | P32: Amount to be Paid | Q32: Paid Amount | R32: Date of Payment | S32: Receipt Number | T32: REMARKS
B33: 1st Payment: | C33: =J28 -> 20000 | D33: =J28/J31 -> 3333.3333 | E33: =(C33*0.015) -> 300 | F33: =SUM(D33:E33) -> 3633.3333 | L33: 1st Payment: | M33: =T28 -> 20000 | N33: =T28/T31 -> 3333.3333 | O33: =(M33*0.015) -> 300 | P33: =SUM(N33:O33) -> 3633.3333
B34: 2nd Payment: | C34: 16665 | D34: 3333 | E34: =(C34*0.015) -> 249.975 | F34: =SUM(D34:E34) -> 3582.975 | L34: 2nd Payment: | M34: 16665 | N34: 3333 | O34: =(M34*0.015) -> 249.975 | P34: =SUM(N34:O34) -> 3582.975
B35: 3rd Payment: | C35: 13332 | D35: 3333 | E35: =(C35*0.015) -> 199.98 | F35: =SUM(D35:E35) -> 3532.98 | L35: 3rd Payment: | M35: 13332 | N35: 3333 | O35: =(M35*0.015) -> 199.98 | P35: =SUM(N35:O35) -> 3532.98
B36: 4th Payment: | C36: 9999 | D36: 3333 | E36: =(C36*0.015) -> 149.985 | F36: =SUM(D36:E36) -> 3482.985 | L36: 4th Payment: | M36: 9999 | N36: 3333 | O36: =(M36*0.015) -> 149.985 | P36: =SUM(N36:O36) -> 3482.985
B37: 5th Payment: | C37: 6666 | D37: 3333 | E37: =(C37*0.015) -> 99.99 | F37: =SUM(D37:E37) -> 3432.99 | L37: 5th Payment: | M37: 6666 | N37: 3333 | O37: =(M37*0.015) -> 99.99 | P37: =SUM(N37:O37) -> 3432.99
B38: 6th Payment: | C38: 3333 | D38: 3333 | E38: =(C38*0.015) -> 49.995 | F38: =SUM(D38:E38) -> 3382.995 | J38: Fully Paid | L38: 6th Payment: | M38: 3333 | N38: 3333 | O38: =(M38*0.015) -> 49.995 | P38: =SUM(N38:O38) -> 3382.995 | T38: Fully Paid
B42: Member's Name: | C42: Buenaobra, Nordie | H42: Loan Amount: | J42: 10000 | L42: Member's Name: | M42: Buenaobra, Nordie | R42: Loan Amount: | T42: 10000
B43: Membership Number: | I43: Date: | J43: 5/21/2025 | L43: Membership Number: | S43: Date: | T43: 5/21/2025
B44: No. of Loan's Made: | F44: Interest Rate: | J44: 0.015 | L44: No. of Loan's Made: | P44: Interest Rate: | T44: 0.015
B45: Mode of Payment: | E45: No. of Months to Pay: | J45: 6 | L45: Mode of Payment: | O45: No. of Months to Pay: | T45: 6
B46: Payment's Made | C46: Present Capital Loan | D46: Constant Payment Deducted to Capital Loan | E46: Interest Amount per Payment | F46: Amount to be Paid | G46: Paid Amount | H46: Date of Payment | I46: Receipt Number | J46: REMARKS | L46: Payment's Made | M46: Present Capital Loan | N46: Constant Payment Deducted to Capital Loan | O46: Interest Amount per Payment | P46: Amount to be Paid | Q46: Paid Amount | R46: Date of Payment | S46: Receipt Number | T46: REMARKS
B47: 1st Payment: | C47: =J42 -> 10000 | D47: =J42/J45 -> 1666.6667 | E47: =(C47*0.015) -> 150 | F47: =SUM(D47:E47) -> 1816.6667 | L47: 1st Payment: | M47: =T42 -> 10000 | N47: =T42/T45 -> 1666.6667 | O47: =(M47*0.015) -> 150 | P47: =SUM(N47:O47) -> 1816.6667
B48: 2nd Payment: | C48: 8335 | D48: 1667 | E48: =(C48*0.015) -> 125.025 | F48: =SUM(D48:E48) -> 1792.025 | L48: 2nd Payment: | M48: 8335 | N48: 1667 | O48: =(M48*0.015) -> 125.025 | P48: =SUM(N48:O48) -> 1792.025
B49: 3rd Payment: | C49: 6668 | D49: 1667 | E49: =(C49*0.015) -> 100.02 | F49: =SUM(D49:E49) -> 1767.02 | L49: 3rd Payment: | M49: 6668 | N49: 1667 | O49: =(M49*0.015) -> 100.02 | P49: =SUM(N49:O49) -> 1767.02
B50: 4th Payment: | C50: 5001 | D50: 1667 | E50: =(C50*0.015) -> 75.015 | F50: =SUM(D50:E50) -> 1742.015 | L50: 4th Payment: | M50: 5001 | N50: 1667 | O50: =(M50*0.015) -> 75.015 | P50: =SUM(N50:O50) -> 1742.015
B51: 5th Payment: | C51: 3334 | D51: 1667 | E51: =(C51*0.015) -> 50.01 | F51: =SUM(D51:E51) -> 1717.01 | L51: 5th Payment: | M51: 3334 | N51: 1667 | O51: =(M51*0.015) -> 50.01 | P51: =SUM(N51:O51) -> 1717.01
B52: 6th Payment: | C52: 1667 | D52: 1667 | E52: =(C52*0.015) -> 25.005 | F52: =SUM(D52:E52) -> 1692.005 | J52: Fully Paid | L52: 6th Payment: | M52: 1667 | N52: 1667 | O52: =(M52*0.015) -> 25.005 | P52: =SUM(N52:O52) -> 1692.005 | T52: Fully Paid
B55: Member's Name: | C55: Gunda, Jomelyn | F55: Emergency Loan | H55: Loan Amount: | J55: 10000 | L55: Member's Name: | M55: Gunda, Jomelyn | P55: Emergency Loan | R55: Loan Amount: | T55: 10000
B56: Membership Number: | I56: Date: | J56: 5/16/2025 | L56: Membership Number: | S56: Date: | T56: 5/16/2025
B57: No. of Loan's Made: | F57: Interest Rate: | J57: 0.015 | L57: No. of Loan's Made: | P57: Interest Rate: | T57: 0.015
B58: Mode of Payment: | E58: No. of Months to Pay: | J58: 6 | L58: Mode of Payment: | O58: No. of Months to Pay: | T58: 6
B59: Payment's Made | C59: Present Capital Loan | D59: Constant Payment Deducted to Capital Loan | E59: Interest Amount per Payment | F59: Amount to be Paid | G59: Paid Amount | H59: Date of Payment | I59: Receipt Number | J59: REMARKS | L59: Payment's Made | M59: Present Capital Loan | N59: Constant Payment Deducted to Capital Loan | O59: Interest Amount per Payment | P59: Amount to be Paid | Q59: Paid Amount | R59: Date of Payment | S59: Receipt Number | T59: REMARKS
B60: 1st Payment: | C60: =J55 -> 10000 | D60: =J55/J58 -> 1666.6667 | E60: =(C60*0.015) -> 150 | F60: =SUM(D60:E60) -> 1816.6667 | L60: 1st Payment: | M60: =T55 -> 10000 | N60: =T55/T58 -> 1666.6667 | O60: =(M60*0.015) -> 150 | P60: =SUM(N60:O60) -> 1816.6667
B61: 2nd Payment: | C61: 8335 | D61: 1667 | E61: =(C61*0.015) -> 125.025 | F61: =SUM(D61:E61) -> 1792.025 | L61: 2nd Payment: | M61: 8335 | N61: 1667 | O61: =(M61*0.015) -> 125.025 | P61: =SUM(N61:O61) -> 1792.025
B62: 3rd Payment: | C62: 6668 | D62: 1667 | E62: =(C62*0.015) -> 100.02 | F62: =SUM(D62:E62) -> 1767.02 | L62: 3rd Payment: | M62: 6668 | N62: 1667 | O62: =(M62*0.015) -> 100.02 | P62: =SUM(N62:O62) -> 1767.02
B63: 4th Payment: | C63: 5001 | D63: 1667 | E63: =(C63*0.015) -> 75.015 | F63: =SUM(D63:E63) -> 1742.015 | L63: 4th Payment: | M63: 5001 | N63: 1667 | O63: =(M63*0.015) -> 75.015 | P63: =SUM(N63:O63) -> 1742.015
B64: 5th Payment: | C64: 3334 | D64: 1667 | E64: =(C64*0.015) -> 50.01 | F64: =SUM(D64:E64) -> 1717.01 | L64: 5th Payment: | M64: 3334 | N64: 1667 | O64: =(M64*0.015) -> 50.01 | P64: =SUM(N64:O64) -> 1717.01
B65: 6th Payment: | C65: 1667 | D65: 1667 | E65: =(C65*0.015) -> 25.005 | F65: =SUM(D65:E65) -> 1692.005 | J65: Fully Paid | L65: 6th Payment: | M65: 1667 | N65: 1667 | O65: =(M65*0.015) -> 25.005 | P65: =SUM(N65:O65) -> 1692.005 | T65: Fully Paid
B68: Member's Name: | C68: Macayan, Nenita | H68: Loan Amount: | J68: 170000 | L68: Member's Name: | M68: Macayan, Nenita | R68: Loan Amount: | T68: 170000
B69: Membership Number: | I69: Date: | J69: 10/22/2025 | L69: Membership Number: | S69: Date: | T69: 10/22/2025
B70: No. of Loan's Made: | F70: Interest Rate: | J70: 0.015 | L70: No. of Loan's Made: | P70: Interest Rate: | T70: 0.015
B71: Mode of Payment: | E71: No. of Months to Pay: | J71: 6 | L71: Mode of Payment: | O71: No. of Months to Pay: | T71: 6
B72: Payment's Made | C72: Present Capital Loan | D72: Constant Payment Deducted to Capital Loan | E72: Interest Amount per Payment | F72: Amount to be Paid | G72: Paid Amount | H72: Date of Payment | I72: Receipt Number | J72: REMARKS | L72: Payment's Made | M72: Present Capital Loan | N72: Constant Payment Deducted to Capital Loan | O72: Interest Amount per Payment | P72: Amount to be Paid | Q72: Paid Amount | R72: Date of Payment | S72: Receipt Number | T72: REMARKS
B73: 1st Payment: | C73: =J68 -> 170000 | D73: =J68/J71 -> 28333.333 | E73: =(C73*0.015) -> 2550 | F73: =SUM(D73:E73) -> 30883.333 | L73: 1st Payment: | M73: =T68 -> 170000 | N73: =T68/T71 -> 28333.333 | O73: =(M73*0.015) -> 2550 | P73: =SUM(N73:O73) -> 30883.333
B74: 2nd Payment: | C74: 131665 | D74: 28333 | E74: =(C74*0.015) -> 1974.975 | F74: =SUM(D74:E74) -> 30307.975 | L74: 2nd Payment: | M74: 131665 | N74: 28333 | O74: =(M74*0.015) -> 1974.975 | P74: =SUM(N74:O74) -> 30307.975
B75: 3rd Payment: | C75: 108332 | D75: 28333 | E75: =(C75*0.015) -> 1624.98 | F75: =SUM(D75:E75) -> 29957.98 | L75: 3rd Payment: | M75: 108332 | N75: 28333 | O75: =(M75*0.015) -> 1624.98 | P75: =SUM(N75:O75) -> 29957.98
B76: 4th Payment: | C76: 79999 | D76: 28333 | E76: =(C76*0.015) -> 1199.985 | F76: =SUM(D76:E76) -> 29532.985 | L76: 4th Payment: | M76: 79999 | N76: 28333 | O76: =(M76*0.015) -> 1199.985 | P76: =SUM(N76:O76) -> 29532.985
B77: 5th Payment: | C77: 56666 | D77: 28333 | E77: =(C77*0.015) -> 849.99 | F77: =SUM(D77:E77) -> 29182.99 | L77: 5th Payment: | M77: 56666 | N77: 28333 | O77: =(M77*0.015) -> 849.99 | P77: =SUM(N77:O77) -> 29182.99
B78: 6th Payment: | C78: 28333 | D78: 28333 | E78: =(C78*0.015) -> 424.995 | F78: =SUM(D78:E78) -> 28757.995 | J78: Fully Paid | L78: 6th Payment: | M78: 28333 | N78: 28333 | O78: =(M78*0.015) -> 424.995 | P78: =SUM(N78:O78) -> 28757.995 | T78: Fully Paid

Sheet 8 mos
B1: Member's Name: | C1: Crisostomo, Sophia | I1: Loan Amount: | J1: 200000 | L1: Member's Name: | M1: Crisostomo, Sophia | S1: Loan Amount: | T1: 200000
B2: Membership Number: | I2: Date: | J2: 8/29/2025 | L2: Membership Number: | S2: Date: | T2: 8/29/2025
B3: No. of Loan's Made: | I3: Interest Rate: | J3: 0.015 | L3: No. of Loan's Made: | S3: Interest Rate: | T3: 0.015
B4: Mode of Payment: | I4: No. of Months to Pay: | J4: 8 | L4: Mode of Payment: | S4: No. of Months to Pay: | T4: 8
B5: Payment's Made | C5: Present Capital Loan | D5: Constant Payment Deducted to Capital Loan | E5: Interest Amount per Payment | F5: Amount to be Paid | G5: Paid Amount | H5: Date of Payment | I5: Receipt Number | J5: REMARKS | L5: Payment's Made | M5: Present Capital Loan | N5: Constant Payment Deducted to Capital Loan | O5: Interest Amount per Payment | P5: Amount to be Paid | Q5: Paid Amount | R5: Date of Payment | S5: Receipt Number | T5: REMARKS
B6: 1st Payment: | C6: 100000 | D6: =J1/J4 -> 25000 | E6: 3000 | F6: =SUM(D6:E6) -> 28000 | L6: 1st Payment: | M6: 100000 | N6: =T1/T4 -> 25000 | O6: 3000 | P6: =SUM(N6:O6) -> 28000
B7: 2nd Payment: | C7: 175000 | D7: 25000 | E7: =(C7*0.015) -> 2625 | F7: =SUM(D7:E7) -> 27625 | L7: 2nd Payment: | M7: 175000 | N7: 25000 | O7: =(M7*0.015) -> 2625 | P7: =SUM(N7:O7) -> 27625
B8: 3rd Payment: | C8: 150000 | D8: 25000 | E8: =(C8*0.015) -> 2250 | F8: =SUM(D8:E8) -> 27250 | L8: 3rd Payment: | M8: 150000 | N8: 25000 | O8: =(M8*0.015) -> 2250 | P8: =SUM(N8:O8) -> 27250
B9: 4th Payment: | C9: 125000 | D9: 25000 | E9: =(C9*0.015) -> 1875 | F9: =SUM(D9:E9) -> 26875 | L9: 4th Payment: | M9: 125000 | N9: 25000 | O9: =(M9*0.015) -> 1875 | P9: =SUM(N9:O9) -> 26875
B10: 5th Payment: | C10: 10000 | D10: 25000 | E10: 1500 | F10: =SUM(D10:E10) -> 26500 | L10: 5th Payment: | M10: 10000 | N10: 25000 | O10: 1500 | P10: =SUM(N10:O10) -> 26500
B11: 6th Payment: | C11: 75000 | D11: 25000 | E11: =(C11*0.015) -> 1125 | F11: =SUM(D11:E11) -> 26125 | L11: 6th Payment: | M11: 75000 | N11: 25000 | O11: =(M11*0.015) -> 1125 | P11: =SUM(N11:O11) -> 26125
B12: 7th Payment: | C12: 50000 | D12: 25000 | E12: =(C12*0.015) -> 750 | F12: =SUM(D12:E12) -> 25750 | L12: 7th Payment: | M12: 50000 | N12: 25000 | O12: =(M12*0.015) -> 750 | P12: =SUM(N12:O12) -> 25750
B13: 8th Payment: | C13: 25000 | D13: 25000 | E13: =(C13*0.015) -> 375 | F13: =SUM(D13:E13) -> 25375 | J13: Fully Paid | L13: 8th Payment: | M13: 25000 | N13: 25000 | O13: =(M13*0.015) -> 375 | P13: =SUM(N13:O13) -> 25375 | T13: Fully Paid

Sheet 15 mos
B1: Member's Name: | C1: Fontejon, Sandra | I1: Loan Amount: | J1: 40125 | L1: Member's Name: | M1: Fontejon, Sandra | S1: Loan Amount: | T1: 40125
B2: Membership Number: | I2: Date: | J2: 3/7/2025 | L2: Membership Number: | S2: Date: | T2: 3/7/2025
B3: No. of Loan's Made: | I3: Interest Rate: | J3: 0.015 | L3: No. of Loan's Made: | S3: Interest Rate: | T3: 0.015
B4: Mode of Payment: | I4: No. of Months to Pay: | J4: 15 | L4: Mode of Payment: | S4: No. of Months to Pay: | T4: 15
B5: Payment's Made | C5: Present Capital Loan | D5: Constant Payment Deducted to Capital Loan | E5: Interest Amount per Payment | F5: Amount to be Paid | G5: Paid Amount | H5: Date of Payment | I5: Receipt Number | J5: REMARKS | L5: Payment's Made | M5: Present Capital Loan | N5: Constant Payment Deducted to Capital Loan | O5: Interest Amount per Payment | P5: Amount to be Paid | Q5: Paid Amount | R5: Date of Payment | S5: Receipt Number | T5: REMARKS
B6: 1st Payment: | C6: =J1 -> 40125 | D6: =J1/J4 -> 2675 | E6: =(C6*0.015) -> 601.875 | F6: =SUM(D6:E6) -> 3276.875 | L6: 1st Payment: | M6: =T1 -> 40125 | N6: =T1/T4 -> 2675 | O6: =(M6*0.015) -> 601.875 | P6: =SUM(N6:O6) -> 3276.875
B7: 2nd Payment: | C7: 37450 | D7: 2675 | E7: =(C7*0.015) -> 561.75 | F7: =SUM(D7:E7) -> 3236.75 | L7: 2nd Payment: | M7: 37450 | N7: 2675 | O7: =(M7*0.015) -> 561.75 | P7: =SUM(N7:O7) -> 3236.75
B8: 3rd Payment: | C8: 34775 | D8: 2675 | E8: =(C8*0.015) -> 521.625 | F8: =SUM(D8:E8) -> 3196.625 | L8: 3rd Payment: | M8: 34775 | N8: 2675 | O8: =(M8*0.015) -> 521.625 | P8: =SUM(N8:O8) -> 3196.625
B9: 4th Payment: | C9: 32100 | D9: 2675 | E9: =(C9*0.015) -> 481.5 | F9: =SUM(D9:E9) -> 3156.5 | L9: 4th Payment: | M9: 32100 | N9: 2675 | O9: =(M9*0.015) -> 481.5 | P9: =SUM(N9:O9) -> 3156.5
B10: 5th Payment: | C10: 29425 | D10: 2675 | E10: =(C10*0.015) -> 441.375 | F10: =SUM(D10:E10) -> 3116.375 | L10: 5th Payment: | M10: 29425 | N10: 2675 | O10: =(M10*0.015) -> 441.375 | P10: =SUM(N10:O10) -> 3116.375
B11: 6th Payment: | C11: 26750 | D11: 2675 | E11: =(C11*0.015) -> 401.25 | F11: =SUM(D11:E11) -> 3076.25 | L11: 6th Payment: | M11: 26750 | N11: 2675 | O11: =(M11*0.015) -> 401.25 | P11: =SUM(N11:O11) -> 3076.25
B12: 7th Payment: | C12: 24075 | D12: 2675 | E12: =(C12*0.015) -> 361.125 | F12: =SUM(D12:E12) -> 3036.125 | L12: 7th Payment: | M12: 24075 | N12: 2675 | O12: =(M12*0.015) -> 361.125 | P12: =SUM(N12:O12) -> 3036.125
B13: 8th Payment: | C13: 21400 | D13: 2675 | E13: =(C13*0.015) -> 321 | F13: =SUM(D13:E13) -> 2996 | L13: 8th Payment: | M13: 21400 | N13: 2675 | O13: =(M13*0.015) -> 321 | P13: =SUM(N13:O13) -> 2996
B14: 9th Payment: | C14: 18725 | D14: 2675 | E14: =(C14*0.015) -> 280.875 | F14: =SUM(D14:E14) -> 2955.875 | L14: 9th Payment: | M14: 18725 | N14: 2675 | O14: =(M14*0.015) -> 280.875 | P14: =SUM(N14:O14) -> 2955.875
B15: 10th Payment: | C15: 16050 | D15: 2675 | E15: =(C15*0.015) -> 240.75 | F15: =SUM(D15:E15) -> 2915.75 | L15: 10th Payment: | M15: 16050 | N15: 2675 | O15: =(M15*0.015) -> 240.75 | P15: =SUM(N15:O15) -> 2915.75
B16: 11th Payment: | C16: 13375 | D16: 2675 | E16: =(C16*0.015) -> 200.625 | F16: =SUM(D16:E16) -> 2875.625 | L16: 11th Payment: | M16: 13375 | N16: 2675 | O16: =(M16*0.015) -> 200.625 | P16: =SUM(N16:O16) -> 2875.625
B17: 12th Payment: | C17: 10700 | D17: 2675 | E17: =(C17*0.015) -> 160.5 | F17: =SUM(D17:E17) -> 2835.5 | L17: 12th Payment: | M17: 10700 | N17: 2675 | O17: =(M17*0.015) -> 160.5 | P17: =SUM(N17:O17) -> 2835.5
B18: 13th Payment: | C18: 8025 | D18: 2675 | E18: =(C18*0.015) -> 120.375 | F18: =SUM(D18:E18) -> 2795.375 | L18: 13th Payment: | M18: 8025 | N18: 2675 | O18: =(M18*0.015) -> 120.375 | P18: =SUM(N18:O18) -> 2795.375
B19: 14th Payment: | C19: 5350 | D19: 2675 | E19: =(C19*0.015) -> 80.25 | F19: =SUM(D19:E19) -> 2755.25 | L19: 14th Payment: | M19: 5350 | N19: 2675 | O19: =(M19*0.015) -> 80.25 | P19: =SUM(N19:O19) -> 2755.25
B20: 15th Payment: | C20: 2675 | D20: 2675 | E20: =(C20*0.015) -> 40.125 | F20: =SUM(D20:E20) -> 2715.125 | J20: Fully Paid | L20: 15th Payment: | M20: 2675 | N20: 2675 | O20: =(M20*0.015) -> 40.125 | P20: =SUM(N20:O20) -> 2715.125 | T20: Fully Paid
B23: Member's Name: | C23: Moyo, Princess Warlene | I23: Loan Amount: | J23: 20000 | L23: Member's Name: | M23: Moyo, Princess Warlene | S23: Loan Amount: | T23: 20000
B24: Membership Number: | I24: Date: | J24: 6/20/2024 | L24: Membership Number: | S24: Date: | T24: 6/20/2024
B25: No. of Loan's Made: | I25: Interest Rate: | J25: 0.015 | L25: No. of Loan's Made: | S25: Interest Rate: | T25: 0.015
B26: Mode of Payment: | I26: No. of Months to Pay: | J26: 15 | L26: Mode of Payment: | S26: No. of Months to Pay: | T26: 15
B27: Payment's Made | C27: Present Capital Loan | D27: Constant Payment Deducted to Capital Loan | E27: Interest Amount per Payment | F27: Amount to be Paid | G27: Paid Amount | H27: Date of Payment | I27: Receipt Number | J27: REMARKS | L27: Payment's Made | M27: Present Capital Loan | N27: Constant Payment Deducted to Capital Loan | O27: Interest Amount per Payment | P27: Amount to be Paid | Q27: Paid Amount | R27: Date of Payment | S27: Receipt Number | T27: REMARKS
B28: 1st Payment: | C28: =J23 -> 20000 | D28: =J23/J26 -> 1333.3333 | E28: =(C28*0.015) -> 300 | F28: =SUM(D28:E28) -> 1633.3333 | L28: 1st Payment: | M28: =T23 -> 20000 | N28: =T23/T26 -> 1333.3333 | O28: =(M28*0.015) -> 300 | P28: =SUM(N28:O28) -> 1633.3333
B29: 2nd Payment: | C29: 18662 | D29: 1333 | E29: =(C29*0.015) -> 279.93 | F29: =SUM(D29:E29) -> 1612.93 | L29: 2nd Payment: | M29: 18662 | N29: 1333 | O29: =(M29*0.015) -> 279.93 | P29: =SUM(N29:O29) -> 1612.93
B30: 3rd Payment: | C30: 17329 | D30: 1333 | E30: =(C30*0.015) -> 259.935 | F30: =SUM(D30:E30) -> 1592.935 | L30: 3rd Payment: | M30: 17329 | N30: 1333 | O30: =(M30*0.015) -> 259.935 | P30: =SUM(N30:O30) -> 1592.935
B31: 4th Payment: | C31: 15996 | D31: 1333 | E31: =(C31*0.015) -> 239.94 | F31: =SUM(D31:E31) -> 1572.94 | L31: 4th Payment: | M31: 15996 | N31: 1333 | O31: =(M31*0.015) -> 239.94 | P31: =SUM(N31:O31) -> 1572.94
B32: 5th Payment: | C32: 14663 | D32: 1333 | E32: =(C32*0.015) -> 219.945 | F32: =SUM(D32:E32) -> 1552.945 | L32: 5th Payment: | M32: 14663 | N32: 1333 | O32: =(M32*0.015) -> 219.945 | P32: =SUM(N32:O32) -> 1552.945
B33: 6th Payment: | C33: 13330 | D33: 1333 | E33: =(C33*0.015) -> 199.95 | F33: =SUM(D33:E33) -> 1532.95 | L33: 6th Payment: | M33: 13330 | N33: 1333 | O33: =(M33*0.015) -> 199.95 | P33: =SUM(N33:O33) -> 1532.95
B34: 7th Payment: | C34: 11997 | D34: 1333 | E34: =(C34*0.015) -> 179.955 | F34: =SUM(D34:E34) -> 1512.955 | L34: 7th Payment: | M34: 11997 | N34: 1333 | O34: =(M34*0.015) -> 179.955 | P34: =SUM(N34:O34) -> 1512.955
B35: 8th Payment: | C35: 10664 | D35: 1333 | E35: =(C35*0.015) -> 159.96 | F35: =SUM(D35:E35) -> 1492.96 | L35: 8th Payment: | M35: 10664 | N35: 1333 | O35: =(M35*0.015) -> 159.96 | P35: =SUM(N35:O35) -> 1492.96
B36: 9th Payment: | C36: 9331 | D36: 1333 | E36: =(C36*0.015) -> 139.965 | F36: =SUM(D36:E36) -> 1472.965 | L36: 9th Payment: | M36: 9331 | N36: 1333 | O36: =(M36*0.015) -> 139.965 | P36: =SUM(N36:O36) -> 1472.965
B37: 10th Payment: | C37: 7998 | D37: 1333 | E37: =(C37*0.015) -> 119.97 | F37: =SUM(D37:E37) -> 1452.97 | L37: 10th Payment: | M37: 7998 | N37: 1333 | O37: =(M37*0.015) -> 119.97 | P37: =SUM(N37:O37) -> 1452.97
B38: 11th Payment: | C38: 6665 | D38: 1333 | E38: =(C38*0.015) -> 99.975 | F38: =SUM(D38:E38) -> 1432.975 | L38: 11th Payment: | M38: 6665 | N38: 1333 | O38: =(M38*0.015) -> 99.975 | P38: =SUM(N38:O38) -> 1432.975
B39: 12th Payment: | C39: 5332 | D39: 1333 | E39: =(C39*0.015) -> 79.98 | F39: =SUM(D39:E39) -> 1412.98 | L39: 12th Payment: | M39: 5332 | N39: 1333 | O39: =(M39*0.015) -> 79.98 | P39: =SUM(N39:O39) -> 1412.98
B40: 13th Payment: | C40: 3999 | D40: 1333 | E40: =(C40*0.015) -> 59.985 | F40: =SUM(D40:E40) -> 1392.985 | L40: 13th Payment: | M40: 3999 | N40: 1333 | O40: =(M40*0.015) -> 59.985 | P40: =SUM(N40:O40) -> 1392.985
B41: 14th Payment: | C41: 2666 | D41: 1333 | E41: =(C41*0.015) -> 39.99 | F41: =SUM(D41:E41) -> 1372.99 | L41: 14th Payment: | M41: 2666 | N41: 1333 | O41: =(M41*0.015) -> 39.99 | P41: =SUM(N41:O41) -> 1372.99
B42: 15th Payment: | C42: 1333 | D42: 1333 | E42: =(C42*0.015) -> 19.995 | F42: =SUM(D42:E42) -> 1352.995 | J42: Fully Paid | L42: 15th Payment: | M42: 1333 | N42: 1333 | O42: =(M42*0.015) -> 19.995 | P42: =SUM(N42:O42) -> 1352.995 | T42: Fully Paid
O43: =SUM(O28:O42) -> 2399.475
B45: Member's Name: | I45: Loan Amount: | J45: 150000 | L45: Member's Name: | S45: Loan Amount: | T45: 150000
B46: Membership Number: | I46: Date: | J46: 4/28/2025 | L46: Membership Number: | S46: Date: | T46: 4/28/2025
B47: No. of Loan's Made: | I47: Interest Rate: | J47: 0.015 | L47: No. of Loan's Made: | S47: Interest Rate: | T47: 0.015
B48: Mode of Payment: | I48: No. of Months to Pay: | J48: 15 | L48: Mode of Payment: | S48: No. of Months to Pay: | T48: 15
B49: Payment's Made | C49: Present Capital Loan | D49: Constant Payment Deducted to Capital Loan | E49: Interest Amount per Payment | F49: Amount to be Paid | G49: Paid Amount | H49: Date of Payment | I49: Receipt Number | J49: REMARKS | L49: Payment's Made | M49: Present Capital Loan | N49: Constant Payment Deducted to Capital Loan | O49: Interest Amount per Payment | P49: Amount to be Paid | Q49: Paid Amount | R49: Date of Payment | S49: Receipt Number | T49: REMARKS
B50: 1st Payment: | C50: =J45 -> 150000 | D50: =J45/J48 -> 10000 | E50: =(C50*0.015) -> 2250 | F50: =SUM(D50:E50) -> 12250 | L50: 1st Payment: | M50: =T45 -> 150000 | N50: =T45/T48 -> 10000 | O50: =(M50*0.015) -> 2250 | P50: =SUM(N50:O50) -> 12250
B51: 2nd Payment: | C51: 140000 | D51: 10000 | E51: =(C51*0.015) -> 2100 | F51: =SUM(D51:E51) -> 12100 | L51: 2nd Payment: | M51: 140000 | N51: 10000 | O51: =(M51*0.015) -> 2100 | P51: =SUM(N51:O51) -> 12100
B52: 3rd Payment: | C52: 130000 | D52: 10000 | E52: =(C52*0.015) -> 1950 | F52: =SUM(D52:E52) -> 11950 | L52: 3rd Payment: | M52: 130000 | N52: 10000 | O52: =(M52*0.015) -> 1950 | P52: =SUM(N52:O52) -> 11950
B53: 4th Payment: | C53: 120000 | D53: 10000 | E53: =(C53*0.015) -> 1800 | F53: =SUM(D53:E53) -> 11800 | L53: 4th Payment: | M53: 120000 | N53: 10000 | O53: =(M53*0.015) -> 1800 | P53: =SUM(N53:O53) -> 11800
B54: 5th Payment: | C54: 110000 | D54: 10000 | E54: =(C54*0.015) -> 1650 | F54: =SUM(D54:E54) -> 11650 | L54: 5th Payment: | M54: 110000 | N54: 10000 | O54: =(M54*0.015) -> 1650 | P54: =SUM(N54:O54) -> 11650
B55: 6th Payment: | C55: 100000 | D55: 10000 | E55: =(C55*0.015) -> 1500 | F55: =SUM(D55:E55) -> 11500 | L55: 6th Payment: | M55: 100000 | N55: 10000 | O55: =(M55*0.015) -> 1500 | P55: =SUM(N55:O55) -> 11500
B56: 7th Payment: | C56: 90000 | D56: 10000 | E56: =(C56*0.015) -> 1350 | F56: =SUM(D56:E56) -> 11350 | L56: 7th Payment: | M56: 90000 | N56: 10000 | O56: =(M56*0.015) -> 1350 | P56: =SUM(N56:O56) -> 11350
B57: 8th Payment: | C57: 80000 | D57: 10000 | E57: =(C57*0.015) -> 1200 | F57: =SUM(D57:E57) -> 11200 | L57: 8th Payment: | M57: 80000 | N57: 10000 | O57: =(M57*0.015) -> 1200 | P57: =SUM(N57:O57) -> 11200
B58: 9th Payment: | C58: 70000 | D58: 10000 | E58: =(C58*0.015) -> 1050 | F58: =SUM(D58:E58) -> 11050 | L58: 9th Payment: | M58: 70000 | N58: 10000 | O58: =(M58*0.015) -> 1050 | P58: =SUM(N58:O58) -> 11050
B59: 10th Payment: | C59: 60000 | D59: 10000 | E59: =(C59*0.015) -> 900 | F59: =SUM(D59:E59) -> 10900 | L59: 10th Payment: | M59: 60000 | N59: 10000 | O59: =(M59*0.015) -> 900 | P59: =SUM(N59:O59) -> 10900
B60: 11th Payment: | C60: 50000 | D60: 10000 | E60: =(C60*0.015) -> 750 | F60: =SUM(D60:E60) -> 10750 | L60: 11th Payment: | M60: 50000 | N60: 10000 | O60: =(M60*0.015) -> 750 | P60: =SUM(N60:O60) -> 10750
B61: 12th Payment: | C61: 40000 | D61: 10000 | E61: =(C61*0.015) -> 600 | F61: =SUM(D61:E61) -> 10600 | L61: 12th Payment: | M61: 40000 | N61: 10000 | O61: =(M61*0.015) -> 600 | P61: =SUM(N61:O61) -> 10600
B62: 13th Payment: | C62: 30000 | D62: 10000 | E62: =(C62*0.015) -> 450 | F62: =SUM(D62:E62) -> 10450 | L62: 13th Payment: | M62: 30000 | N62: 10000 | O62: =(M62*0.015) -> 450 | P62: =SUM(N62:O62) -> 10450
B63: 14th Payment: | C63: 20000 | D63: 10000 | E63: =(C63*0.015) -> 300 | F63: =SUM(D63:E63) -> 10300 | L63: 14th Payment: | M63: 20000 | N63: 10000 | O63: =(M63*0.015) -> 300 | P63: =SUM(N63:O63) -> 10300
B64: 15th Payment: | C64: 10000 | D64: 10000 | E64: =(C64*0.015) -> 150 | F64: =SUM(D64:E64) -> 10150 | J64: Fully Paid | L64: 15th Payment: | M64: 10000 | N64: 10000 | O64: =(M64*0.015) -> 150 | P64: =SUM(N64:O64) -> 10150 | T64: Fully Paid
B67: Member's Name: | C67: Gapasin, Marina | I67: Loan Amount: | J67: 150000 | L67: Member's Name: | M67: Gapasin, Marina | S67: Loan Amount: | T67: 150000
B68: Membership Number: | I68: Date: | J68: 4/30/2025 | L68: Membership Number: | S68: Date: | T68: 4/30/2025
B69: No. of Loan's Made: | I69: Interest Rate: | J69: 0.015 | L69: No. of Loan's Made: | S69: Interest Rate: | T69: 0.015
B70: Mode of Payment: | I70: No. of Months to Pay: | J70: 15 | L70: Mode of Payment: | S70: No. of Months to Pay: | T70: 15
B71: Payment's Made | C71: Present Capital Loan | D71: Constant Payment Deducted to Capital Loan | E71: Interest Amount per Payment | F71: Amount to be Paid | G71: Paid Amount | H71: Date of Payment | I71: Receipt Number | J71: REMARKS | L71: Payment's Made | M71: Present Capital Loan | N71: Constant Payment Deducted to Capital Loan | O71: Interest Amount per Payment | P71: Amount to be Paid | Q71: Paid Amount | R71: Date of Payment | S71: Receipt Number | T71: REMARKS
B72: 1st Payment: | C72: =J67 -> 150000 | D72: =J67/J70 -> 10000 | E72: =(C72*0.015) -> 2250 | F72: =SUM(D72:E72) -> 12250 | L72: 1st Payment: | M72: =T67 -> 150000 | N72: =T67/T70 -> 10000 | O72: =(M72*0.015) -> 2250 | P72: =SUM(N72:O72) -> 12250
B73: 2nd Payment: | C73: 140000 | D73: 10000 | E73: =(C73*0.015) -> 2100 | F73: =SUM(D73:E73) -> 12100 | L73: 2nd Payment: | M73: 140000 | N73: 10000 | O73: =(M73*0.015) -> 2100 | P73: =SUM(N73:O73) -> 12100
B74: 3rd Payment: | C74: 130000 | D74: 10000 | E74: =(C74*0.015) -> 1950 | F74: =SUM(D74:E74) -> 11950 | L74: 3rd Payment: | M74: 130000 | N74: 10000 | O74: =(M74*0.015) -> 1950 | P74: =SUM(N74:O74) -> 11950
B75: 4th Payment: | C75: 120000 | D75: 10000 | E75: =(C75*0.015) -> 1800 | F75: =SUM(D75:E75) -> 11800 | L75: 4th Payment: | M75: 120000 | N75: 10000 | O75: =(M75*0.015) -> 1800 | P75: =SUM(N75:O75) -> 11800
B76: 5th Payment: | C76: 110000 | D76: 10000 | E76: =(C76*0.015) -> 1650 | F76: =SUM(D76:E76) -> 11650 | L76: 5th Payment: | M76: 110000 | N76: 10000 | O76: =(M76*0.015) -> 1650 | P76: =SUM(N76:O76) -> 11650
B77: 6th Payment: | C77: 100000 | D77: 10000 | E77: =(C77*0.015) -> 1500 | F77: =SUM(D77:E77) -> 11500 | L77: 6th Payment: | M77: 100000 | N77: 10000 | O77: =(M77*0.015) -> 1500 | P77: =SUM(N77:O77) -> 11500
B78: 7th Payment: | C78: 90000 | D78: 10000 | E78: =(C78*0.015) -> 1350 | F78: =SUM(D78:E78) -> 11350 | L78: 7th Payment: | M78: 90000 | N78: 10000 | O78: =(M78*0.015) -> 1350 | P78: =SUM(N78:O78) -> 11350
B79: 8th Payment: | C79: 80000 | D79: 10000 | E79: =(C79*0.015) -> 1200 | F79: =SUM(D79:E79) -> 11200 | L79: 8th Payment: | M79: 80000 | N79: 10000 | O79: =(M79*0.015) -> 1200 | P79: =SUM(N79:O79) -> 11200
B80: 9th Payment: | C80: 70000 | D80: 10000 | E80: =(C80*0.015) -> 1050 | F80: =SUM(D80:E80) -> 11050 | L80: 9th Payment: | M80: 70000 | N80: 10000 | O80: =(M80*0.015) -> 1050 | P80: =SUM(N80:O80) -> 11050
B81: 10th Payment: | C81: 60000 | D81: 10000 | E81: =(C81*0.015) -> 900 | F81: =SUM(D81:E81) -> 10900 | L81: 10th Payment: | M81: 60000 | N81: 10000 | O81: =(M81*0.015) -> 900 | P81: =SUM(N81:O81) -> 10900
B82: 11th Payment: | C82: 50000 | D82: 10000 | E82: =(C82*0.015) -> 750 | F82: =SUM(D82:E82) -> 10750 | L82: 11th Payment: | M82: 50000 | N82: 10000 | O82: =(M82*0.015) -> 750 | P82: =SUM(N82:O82) -> 10750
B83: 12th Payment: | C83: 40000 | D83: 10000 | E83: =(C83*0.015) -> 600 | F83: =SUM(D83:E83) -> 10600 | L83: 12th Payment: | M83: 40000 | N83: 10000 | O83: =(M83*0.015) -> 600 | P83: =SUM(N83:O83) -> 10600
B84: 13th Payment: | C84: 30000 | D84: 10000 | E84: =(C84*0.015) -> 450 | F84: =SUM(D84:E84) -> 10450 | L84: 13th Payment: | M84: 30000 | N84: 10000 | O84: =(M84*0.015) -> 450 | P84: =SUM(N84:O84) -> 10450
B85: 14th Payment: | C85: 20000 | D85: 10000 | E85: =(C85*0.015) -> 300 | F85: =SUM(D85:E85) -> 10300 | L85: 14th Payment: | M85: 20000 | N85: 10000 | O85: =(M85*0.015) -> 300 | P85: =SUM(N85:O85) -> 10300
B86: 15th Payment: | C86: 10000 | D86: 10000 | E86: =(C86*0.015) -> 150 | F86: =SUM(D86:E86) -> 10150 | J86: Fully Paid | L86: 15th Payment: | M86: 10000 | N86: 10000 | O86: =(M86*0.015) -> 150 | P86: =SUM(N86:O86) -> 10150 | T86: Fully Paid

Sheet 20 mos
B1: Member's Name: | C1: Almorin, Santos | I1: Loan Amount: | J1: 30000 | L1: Member's Name: | M1: Almorin, Santos | S1: Loan Amount: | T1: 30000
B2: Membership Number: | I2: Date: | J2: 12/7/2024 | L2: Membership Number: | S2: Date: | T2: 12/7/2024
B3: No. of Loan's Made: | I3: Interest Rate: | J3: 0.015 | L3: No. of Loan's Made: | S3: Interest Rate: | T3: 0.015
B4: Mode of Payment: | I4: No. of Months to Pay: | J4: 20 | L4: Mode of Payment: | S4: No. of Months to Pay: | T4: 20
B5: Payment's Made | C5: Present Capital Loan | D5: Constant Payment Deducted to Capital Loan | E5: Interest Amount per Payment | F5: Amount to be Paid | G5: Paid Amount | H5: Date of Payment | I5: Receipt Number | J5: REMARKS | L5: Payment's Made | M5: Present Capital Loan | N5: Constant Payment Deducted to Capital Loan | O5: Interest Amount per Payment | P5: Amount to be Paid | Q5: Paid Amount | R5: Date of Payment | S5: Receipt Number | T5: REMARKS
B6: 1st Payment: | C6: 30000 | D6: =J1/J4 -> 1500 | E6: =(C6*0.015) -> 450 | F6: =SUM(D6:E6) -> 1950 | G6: 1950 | L6: 1st Payment: | M6: 30000 | N6: =T1/T4 -> 1500 | O6: =(M6*0.015) -> 450 | P6: =SUM(N6:O6) -> 1950
B7: 2nd Payment: | C7: 28500 | D7: 1500 | E7: =(C7*0.015) -> 427.5 | F7: =SUM(D7:E7) -> 1927.5 | G7: 1928 | L7: 2nd Payment: | M7: 28500 | N7: 1500 | O7: =(M7*0.015) -> 427.5 | P7: =SUM(N7:O7) -> 1927.5
B8: 3rd Payment: | C8: 27000 | D8: 1500 | E8: =(C8*0.015) -> 405 | F8: =SUM(D8:E8) -> 1905 | G8: 1905 | L8: 3rd Payment: | M8: 27000 | N8: 1500 | O8: =(M8*0.015) -> 405 | P8: =SUM(N8:O8) -> 1905
B9: 4th Payment: | C9: 25500 | D9: 1500 | E9: =(C9*0.015) -> 382.5 | F9: =SUM(D9:E9) -> 1882.5 | G9: 1883 | L9: 4th Payment: | M9: 25500 | N9: 1500 | O9: =(M9*0.015) -> 382.5 | P9: =SUM(N9:O9) -> 1882.5
B10: 5th Payment: | C10: 24000 | D10: 1500 | E10: =(C10*0.015) -> 360 | F10: =SUM(D10:E10) -> 1860 | G10: 3698 | L10: 5th Payment: | M10: 24000 | N10: 1500 | O10: =(M10*0.015) -> 360 | P10: =SUM(N10:O10) -> 1860
B11: 6th Payment: | C11: 22500 | D11: 1500 | E11: =(C11*0.015) -> 337.5 | F11: =SUM(D11:E11) -> 1837.5 | G11: 3608 | L11: 6th Payment: | M11: 22500 | N11: 1500 | O11: =(M11*0.015) -> 337.5 | P11: =SUM(N11:O11) -> 1837.5
B12: 7th Payment: | C12: 21000 | D12: 1500 | E12: =(C12*0.015) -> 315 | F12: =SUM(D12:E12) -> 1815 | G12: 3518 | L12: 7th Payment: | M12: 21000 | N12: 1500 | O12: =(M12*0.015) -> 315 | P12: =SUM(N12:O12) -> 1815
B13: 8th Payment: | C13: 19500 | D13: 1500 | E13: =(C13*0.015) -> 292.5 | F13: =SUM(D13:E13) -> 1792.5 | L13: 8th Payment: | M13: 19500 | N13: 1500 | O13: =(M13*0.015) -> 292.5 | P13: =SUM(N13:O13) -> 1792.5
B14: 9th Payment: | C14: 18000 | D14: 1500 | E14: =(C14*0.015) -> 270 | F14: =SUM(D14:E14) -> 1770 | L14: 9th Payment: | M14: 18000 | N14: 1500 | O14: =(M14*0.015) -> 270 | P14: =SUM(N14:O14) -> 1770
B15: 10th Payment: | C15: 16500 | D15: 1500 | E15: =(C15*0.015) -> 247.5 | F15: =SUM(D15:E15) -> 1747.5 | L15: 10th Payment: | M15: 16500 | N15: 1500 | O15: =(M15*0.015) -> 247.5 | P15: =SUM(N15:O15) -> 1747.5
B16: 11th Payment: | C16: 15000 | D16: 1500 | E16: =(C16*0.015) -> 225 | F16: =SUM(D16:E16) -> 1725 | L16: 11th Payment: | M16: 15000 | N16: 1500 | O16: =(M16*0.015) -> 225 | P16: =SUM(N16:O16) -> 1725
B17: 12th Payment: | C17: 13500 | D17: 1500 | E17: =(C17*0.015) -> 202.5 | F17: =SUM(D17:E17) -> 1702.5 | L17: 12th Payment: | M17: 13500 | N17: 1500 | O17: =(M17*0.015) -> 202.5 | P17: =SUM(N17:O17) -> 1702.5
B18: 13th Payment: | C18: 12000 | D18: 1500 | E18: =(C18*0.015) -> 180 | F18: =SUM(D18:E18) -> 1680 | L18: 13th Payment: | M18: 12000 | N18: 1500 | O18: =(M18*0.015) -> 180 | P18: =SUM(N18:O18) -> 1680
B19: 14th Payment: | C19: 10500 | D19: 1500 | E19: =(C19*0.015) -> 157.5 | F19: =SUM(D19:E19) -> 1657.5 | L19: 14th Payment: | M19: 10500 | N19: 1500 | O19: =(M19*0.015) -> 157.5 | P19: =SUM(N19:O19) -> 1657.5
B20: 15th Payment: | C20: 9000 | D20: 1500 | E20: =(C20*0.015) -> 135 | F20: =SUM(D20:E20) -> 1635 | L20: 15th Payment: | M20: 9000 | N20: 1500 | O20: =(M20*0.015) -> 135 | P20: =SUM(N20:O20) -> 1635
B21: 16th Payment: | C21: 7500 | D21: 1500 | E21: =(C21*0.015) -> 112.5 | F21: =SUM(D21:E21) -> 1612.5 | L21: 16th Payment: | M21: 7500 | N21: 1500 | O21: =(M21*0.015) -> 112.5 | P21: =SUM(N21:O21) -> 1612.5
B22: 17th Payment: | C22: 6000 | D22: 1500 | E22: =(C22*0.015) -> 90 | F22: =SUM(D22:E22) -> 1590 | L22: 17th Payment: | M22: 6000 | N22: 1500 | O22: =(M22*0.015) -> 90 | P22: =SUM(N22:O22) -> 1590
B23: 18th Payment: | C23: 4500 | D23: 1500 | E23: =(C23*0.015) -> 67.5 | F23: =SUM(D23:E23) -> 1567.5 | L23: 18th Payment: | M23: 4500 | N23: 1500 | O23: =(M23*0.015) -> 67.5 | P23: =SUM(N23:O23) -> 1567.5
B24: 19th Payment: | C24: 3000 | D24: 1500 | E24: =(C24*0.015) -> 45 | F24: =SUM(D24:E24) -> 1545 | L24: 19th Payment: | M24: 3000 | N24: 1500 | O24: =(M24*0.015) -> 45 | P24: =SUM(N24:O24) -> 1545
B25: 20th Payment: | C25: 1500 | D25: 1500 | E25: =(C25*0.015) -> 22.5 | F25: =SUM(D25:E25) -> 1522.5 | J25: Fully Paid | L25: 20th Payment: | M25: 1500 | N25: 1500 | O25: =(M25*0.015) -> 22.5 | P25: =SUM(N25:O25) -> 1522.5 | T25: Fully Paid
F26: =SUM(F6:F25) -> 34725 | G26: =SUM(G6:G25) -> 18490

Sheet 7 mos
B1: Member's Name: | C1: Anzures, Nancy | H1: Loan Amount: | J1: 7000 | L1: Member's Name: | M1: Anzures, Nancy | R1: Loan Amount: | T1: 7000
B2: Membership Number: | I2: Date: | J2: 2/1/23 | L2: Membership Number: | S2: Date: | T2: 2/1/23
B3: No. of Loan's Made: | F3: Interest Rate: | J3: 0.015 | L3: No. of Loan's Made: | P3: Interest Rate: | T3: 0.015
B4: Mode of Payment: | E4: No. of Months to Pay: | J4: 7 | L4: Mode of Payment: | O4: No. of Months to Pay: | T4: 7
B5: Payment's Made | C5: Present Capital Loan | D5: Constant Payment Deducted to Capital Loan | E5: Interest Amount per Payment | F5: Amount to be Paid | G5: Paid Amount | H5: Date of Payment | I5: Receipt Number | J5: REMARKS | L5: Payment's Made | M5: Present Capital Loan | N5: Constant Payment Deducted to Capital Loan | O5: Interest Amount per Payment | P5: Amount to be Paid | Q5: Paid Amount | R5: Date of Payment | S5: Receipt Number | T5: REMARKS
B6: 1st Payment: | C6: =J1 -> 7000 | D6: =J1/J4 -> 1000 | E6: =(C6*0.015) -> 105 | F6: =SUM(D6:E6) -> 1105 | L6: 1st Payment: | M6: =T1 -> 7000 | N6: =T1/T4 -> 1000 | O6: =(M6*0.015) -> 105 | P6: =SUM(N6:O6) -> 1105
B7: 2nd Payment: | C7: 6000 | D7: 1000 | E7: =(C7*0.015) -> 90 | F7: =SUM(D7:E7) -> 1090 | L7: 2nd Payment: | M7: 6000 | N7: 1000 | O7: =(M7*0.015) -> 90 | P7: =SUM(N7:O7) -> 1090
B8: 3rd Payment: | C8: 5000 | D8: 1000 | E8: =(C8*0.015) -> 75 | F8: =SUM(D8:E8) -> 1075 | L8: 3rd Payment: | M8: 5000 | N8: 1000 | O8: =(M8*0.015) -> 75 | P8: =SUM(N8:O8) -> 1075
B9: 4th Payment: | C9: 4000 | D9: 1000 | E9: =(C9*0.015) -> 60 | F9: =SUM(D9:E9) -> 1060 | L9: 4th Payment: | M9: 4000 | N9: 1000 | O9: =(M9*0.015) -> 60 | P9: =SUM(N9:O9) -> 1060
B10: 5th Payment: | C10: 3000 | D10: 1000 | E10: =(C10*0.015) -> 45 | F10: =SUM(D10:E10) -> 1045 | L10: 5th Payment: | M10: 3000 | N10: 1000 | O10: =(M10*0.015) -> 45 | P10: =SUM(N10:O10) -> 1045
B11: 6th Payment: | C11: 2000 | D11: 1000 | E11: =(C11*0.015) -> 30 | F11: =SUM(D11:E11) -> 1030 | L11: 6th Payment: | M11: 2000 | N11: 1000 | O11: =(M11*0.015) -> 30 | P11: =SUM(N11:O11) -> 1030
B12: 7th Payment: | C12: 1000 | D12: 1000 | E12: =(C12*0.015) -> 15 | F12: =SUM(D12:E12) -> 1015 | J12: Fully Paid | L12: 7th Payment: | M12: 1000 | N12: 1000 | O12: =(M12*0.015) -> 15 | P12: =SUM(N12:O12) -> 1015 | T12: Fully Paid

Sheet 5 mos
B1: Member's Name: | C1: Crisostomo, Sofia | H1: Loan Amount: | J1: 100000 | L1: Member's Name: | M1: Crisostomo, Sofia | R1: Loan Amount: | T1: 100000
B2: Membership Number: | I2: Date: | J2: 3/25/2025 | L2: Membership Number: | S2: Date: | T2: 3/25/2025
B3: No. of Loan's Made: | F3: Interest Rate: | J3: 0.015 | L3: No. of Loan's Made: | P3: Interest Rate: | T3: 0.015
B4: Mode of Payment: | E4: No. of Months to Pay: | J4: 5 | L4: Mode of Payment: | O4: No. of Months to Pay: | T4: 5
B5: Payment's Made | C5: Present Capital Loan | D5: Constant Payment Deducted to Capital Loan | E5: Interest Amount per Payment | F5: Amount to be Paid | G5: Paid Amount | H5: Date of Payment | I5: Receipt Number | J5: REMARKS | L5: Payment's Made | M5: Present Capital Loan | N5: Constant Payment Deducted to Capital Loan | O5: Interest Amount per Payment | P5: Amount to be Paid | Q5: Paid Amount | R5: Date of Payment | S5: Receipt Number | T5: REMARKS
B6: 1st Payment: | C6: =J1 -> 100000 | D6: =J1/J4 -> 20000 | E6: =(C6*0.015) -> 1500 | F6: =SUM(D6:E6) -> 21500 | L6: 1st Payment: | M6: =T1 -> 100000 | N6: =T1/T4 -> 20000 | O6: =(M6*0.015) -> 1500 | P6: =SUM(N6:O6) -> 21500
B7: 2nd Payment: | C7: 80000 | D7: 20000 | E7: =(C7*0.015) -> 1200 | F7: =SUM(D7:E7) -> 21200 | L7: 2nd Payment: | M7: 80000 | N7: 20000 | O7: =(M7*0.015) -> 1200 | P7: =SUM(N7:O7) -> 21200
B8: 3rd Payment: | C8: 60000 | D8: 20000 | E8: =(C8*0.015) -> 900 | F8: =SUM(D8:E8) -> 20900 | L8: 3rd Payment: | M8: 60000 | N8: 20000 | O8: =(M8*0.015) -> 900 | P8: =SUM(N8:O8) -> 20900
B9: 4th Payment: | C9: 40000 | D9: 20000 | E9: =(C9*0.015) -> 600 | F9: =SUM(D9:E9) -> 20600 | L9: 4th Payment: | M9: 40000 | N9: 20000 | O9: =(M9*0.015) -> 600 | P9: =SUM(N9:O9) -> 20600
B10: 5th Payment: | C10: 20000 | D10: 20000 | E10: =(C10*0.015) -> 300 | F10: =SUM(D10:E10) -> 20300 | J10: Fully Paid | L10: 5th Payment: | M10: 20000 | N10: 20000 | O10: =(M10*0.015) -> 300 | P10: =SUM(N10:O10) -> 20300 | T10: Fully Paid
B13: Member's Name: | C13: Velasco, Virgilia | F13: Emergency Loan | H13: Loan Amount: | J13: 10000 | L13: Member's Name: | M13: Velasco, Virgilia | P13: Emergency Loan | R13: Loan Amount: | T13: 10000
B14: Membership Number: | I14: Date: | J14: 2/12/2024 | L14: Membership Number: | S14: Date: | T14: 2/12/2024
B15: No. of Loan's Made: | F15: Interest Rate: | J15: 0.015 | L15: No. of Loan's Made: | P15: Interest Rate: | T15: 0.015
B16: Mode of Payment: | E16: No. of Months to Pay: | J16: 5 | L16: Mode of Payment: | O16: No. of Months to Pay: | T16: 5
B17: Payment's Made | C17: Present Capital Loan | D17: Constant Payment Deducted to Capital Loan | E17: Interest Amount per Payment | F17: Amount to be Paid | G17: Paid Amount | H17: Date of Payment | I17: Receipt Number | J17: REMARKS | L17: Payment's Made | M17: Present Capital Loan | N17: Constant Payment Deducted to Capital Loan | O17: Interest Amount per Payment | P17: Amount to be Paid | Q17: Paid Amount | R17: Date of Payment | S17: Receipt Number | T17: REMARKS
B18: 1st Payment: | C18: =J13 -> 10000 | D18: =J13/J16 -> 2000 | E18: =(C18*0.015) -> 150 | F18: =SUM(D18:E18) -> 2150 | L18: 1st Payment: | M18: =T13 -> 10000 | N18: =T13/T16 -> 2000 | O18: =(M18*0.015) -> 150 | P18: =SUM(N18:O18) -> 2150
B19: 2nd Payment: | C19: 8000 | D19: 2000 | E19: =(C19*0.015) -> 120 | F19: =SUM(D19:E19) -> 2120 | L19: 2nd Payment: | M19: 8000 | N19: 2000 | O19: =(M19*0.015) -> 120 | P19: =SUM(N19:O19) -> 2120
B20: 3rd Payment: | C20: 6000 | D20: 2000 | E20: =(C20*0.015) -> 90 | F20: =SUM(D20:E20) -> 2090 | L20: 3rd Payment: | M20: 6000 | N20: 2000 | O20: =(M20*0.015) -> 90 | P20: =SUM(N20:O20) -> 2090
B21: 4th Payment: | C21: 4000 | D21: 2000 | E21: =(C21*0.015) -> 60 | F21: =SUM(D21:E21) -> 2060 | L21: 4th Payment: | M21: 4000 | N21: 2000 | O21: =(M21*0.015) -> 60 | P21: =SUM(N21:O21) -> 2060
B22: 5th Payment: | C22: 2000 | D22: 2000 | E22: =(C22*0.015) -> 30 | F22: =SUM(D22:E22) -> 2030 | J22: Fully Paid | L22: 5th Payment: | M22: 2000 | N22: 2000 | O22: =(M22*0.015) -> 30 | P22: =SUM(N22:O22) -> 2030 | T22: Fully Paid
B25: Member's Name: | C25: Duran, Rosana | H25: Loan Amount: | J25: 10000 | L25: Member's Name: | M25: Duran, Rosana | R25: Loan Amount: | T25: 10000
B26: Membership Number: | I26: Date: | J26: 7/4/2025 | L26: Membership Number: | S26: Date: | T26: 7/4/2025
B27: No. of Loan's Made: | F27: Interest Rate: | J27: 0.015 | L27: No. of Loan's Made: | P27: Interest Rate: | T27: 0.015
B28: Mode of Payment: | E28: No. of Months to Pay: | J28: 5 | L28: Mode of Payment: | O28: No. of Months to Pay: | T28: 5
B29: Payment's Made | C29: Present Capital Loan | D29: Constant Payment Deducted to Capital Loan | E29: Interest Amount per Payment | F29: Amount to be Paid | G29: Paid Amount | H29: Date of Payment | I29: Receipt Number | J29: REMARKS | L29: Payment's Made | M29: Present Capital Loan | N29: Constant Payment Deducted to Capital Loan | O29: Interest Amount per Payment | P29: Amount to be Paid | Q29: Paid Amount | R29: Date of Payment | S29: Receipt Number | T29: REMARKS
B30: 1st Payment: | C30: =J25 -> 10000 | D30: =J25/J28 -> 2000 | E30: =(C30*0.015) -> 150 | F30: =SUM(D30:E30) -> 2150 | L30: 1st Payment: | M30: =T25 -> 10000 | N30: =T25/T28 -> 2000 | O30: =(M30*0.015) -> 150 | P30: =SUM(N30:O30) -> 2150
B31: 2nd Payment: | C31: 8000 | D31: 2000 | E31: =(C31*0.015) -> 120 | F31: =SUM(D31:E31) -> 2120 | L31: 2nd Payment: | M31: 8000 | N31: 2000 | O31: =(M31*0.015) -> 120 | P31: =SUM(N31:O31) -> 2120
B32: 3rd Payment: | C32: 6000 | D32: 2000 | E32: =(C32*0.015) -> 90 | F32: =SUM(D32:E32) -> 2090 | L32: 3rd Payment: | M32: 6000 | N32: 2000 | O32: =(M32*0.015) -> 90 | P32: =SUM(N32:O32) -> 2090
B33: 4th Payment: | C33: 4000 | D33: 2000 | E33: =(C33*0.015) -> 60 | F33: =SUM(D33:E33) -> 2060 | L33: 4th Payment: | M33: 4000 | N33: 2000 | O33: =(M33*0.015) -> 60 | P33: =SUM(N33:O33) -> 2060
B34: 5th Payment: | C34: 2000 | D34: 2000 | E34: =(C34*0.015) -> 30 | F34: =SUM(D34:E34) -> 2030 | J34: Fully Paid | L34: 5th Payment: | M34: 2000 | N34: 2000 | O34: =(M34*0.015) -> 30 | P34: =SUM(N34:O34) -> 2030 | T34: Fully Paid
B38: Member's Name: | C38: Tangtang, Neddie | F38: Emergency Loan | I38: Loan Amount: | J38: 5000 | L38: Member's Name: | M38: Tangtang, Neddie | P38: Emergency Loan | S38: Loan Amount: | T38: 5000
B39: Membership Number: | I39: Date: | J39: 4/5/2025 | L39: Membership Number: | S39: Date: | T39: 1/19/2024
B40: No. of Loan's Made: | I40: Interest Rate: | J40: 0.015 | L40: No. of Loan's Made: | S40: Interest Rate: | T40: 0.015
B41: Mode of Payment: | I41: No. of Months to Pay: | J41: 12 | L41: Mode of Payment: | S41: No. of Months to Pay: | T41: 12
B42: Payment's Made | C42: Present Capital Loan | D42: Constant Payment Deducted to Capital Loan | E42: Interest Amount per Payment | F42: Amount to be Paid | G42: Paid Amount | H42: Date of Payment | I42: Receipt Number | J42: REMARKS | L42: Payment's Made | M42: Present Capital Loan | N42: Constant Payment Deducted to Capital Loan | O42: Interest Amount per Payment | P42: Amount to be Paid | Q42: Paid Amount | R42: Date of Payment | S42: Receipt Number | T42: REMARKS
B43: 1st Payment: | C43: =J38 -> 5000 | D43: =J38/J41 -> 416.66667 | E43: =(C43*0.015) -> 75 | F43: =SUM(D43:E43) -> 491.66667 | L43: 1st Payment: | M43: =T38 -> 5000 | N43: =T38/T41 -> 416.66667 | O43: =(M43*0.015) -> 75 | P43: =SUM(N43:O43) -> 491.66667
B44: 2nd Payment: | C44: 4587 | D44: 417 | E44: =(C44*0.015) -> 68.805 | F44: =SUM(D44:E44) -> 485.805 | L44: 2nd Payment: | M44: 4587 | N44: 417 | O44: =(M44*0.015) -> 68.805 | P44: =SUM(N44:O44) -> 485.805
B45: 3rd Payment: | C45: 4170 | D45: 417 | E45: =(C45*0.015) -> 62.55 | F45: =SUM(D45:E45) -> 479.55 | L45: 3rd Payment: | M45: 4170 | N45: 417 | O45: =(M45*0.015) -> 62.55 | P45: =SUM(N45:O45) -> 479.55
B46: 4th Payment: | C46: 3753 | D46: 417 | E46: =(C46*0.015) -> 56.295 | F46: =SUM(D46:E46) -> 473.295 | L46: 4th Payment: | M46: 3753 | N46: 417 | O46: =(M46*0.015) -> 56.295 | P46: =SUM(N46:O46) -> 473.295
B47: 5th Payment: | C47: 3336 | D47: 417 | E47: =(C47*0.015) -> 50.04 | F47: =SUM(D47:E47) -> 467.04 | L47: 5th Payment: | M47: 3336 | N47: 417 | O47: =(M47*0.015) -> 50.04 | P47: =SUM(N47:O47) -> 467.04
B48: 6th Payment: | C48: 2919 | D48: 417 | E48: =(C48*0.015) -> 43.785 | F48: =SUM(D48:E48) -> 460.785 | L48: 6th Payment: | M48: 2919 | N48: 417 | O48: =(M48*0.015) -> 43.785 | P48: =SUM(N48:O48) -> 460.785
B49: 7th Payment: | C49: 2502 | D49: 417 | E49: =(C49*0.015) -> 37.53 | F49: =SUM(D49:E49) -> 454.53 | L49: 7th Payment: | M49: 2502 | N49: 417 | O49: =(M49*0.015) -> 37.53 | P49: =SUM(N49:O49) -> 454.53
B50: 8th Payment: | C50: 2085 | D50: 417 | E50: =(C50*0.015) -> 31.275 | F50: =SUM(D50:E50) -> 448.275 | L50: 8th Payment: | M50: 2085 | N50: 417 | O50: =(M50*0.015) -> 31.275 | P50: =SUM(N50:O50) -> 448.275
B51: 9th Payment: | C51: 1668 | D51: 417 | E51: =(C51*0.015) -> 25.02 | F51: =SUM(D51:E51) -> 442.02 | L51: 9th Payment: | M51: 1668 | N51: 417 | O51: =(M51*0.015) -> 25.02 | P51: =SUM(N51:O51) -> 442.02
B52: 10th Payment: | C52: 1251 | D52: 417 | E52: =(C52*0.015) -> 18.765 | F52: =SUM(D52:E52) -> 435.765 | L52: 10th Payment: | M52: 1251 | N52: 417 | O52: =(M52*0.015) -> 18.765 | P52: =SUM(N52:O52) -> 435.765
B53: 11th Payment: | C53: 834 | D53: 417 | E53: =(C53*0.015) -> 12.51 | F53: =SUM(D53:E53) -> 429.51 | L53: 11th Payment: | M53: 834 | N53: 417 | O53: =(M53*0.015) -> 12.51 | P53: =SUM(N53:O53) -> 429.51
B54: 12th Payment: | C54: 417 | D54: 417 | E54: =(C54*0.015) -> 6.255 | F54: =SUM(D54:E54) -> 423.255 | J54: Fully Paid | L54: 12th Payment: | M54: 417 | N54: 417 | O54: =(M54*0.015) -> 6.255 | P54: =SUM(N54:O54) -> 423.255 | T54: Fully Paid
B58: Member's Name: | C58: De Mesa, Danilo | H58: Loan Amount: | J58: 40000 | L58: Member's Name: | M58: De Mesa, Danilo | R58: Loan Amount: | T58: 40000
B59: Membership Number: | I59: Date: | J59: 5/5/2025 | L59: Membership Number: | S59: Date: | T59: 5/5/2025
B60: No. of Loan's Made: | F60: Interest Rate: | J60: 0.015 | L60: No. of Loan's Made: | P60: Interest Rate: | T60: 0.015
B61: Mode of Payment: | E61: No. of Months to Pay: | J61: 5 | L61: Mode of Payment: | O61: No. of Months to Pay: | T61: 5
B62: Payment's Made | C62: Present Capital Loan | D62: Constant Payment Deducted to Capital Loan | E62: Interest Amount per Payment | F62: Amount to be Paid | G62: Paid Amount | H62: Date of Payment | I62: Receipt Number | J62: REMARKS | L62: Payment's Made | M62: Present Capital Loan | N62: Constant Payment Deducted to Capital Loan | O62: Interest Amount per Payment | P62: Amount to be Paid | Q62: Paid Amount | R62: Date of Payment | S62: Receipt Number | T62: REMARKS
B63: 1st Payment: | C63: =J58 -> 40000 | D63: =J58/J61 -> 8000 | E63: =(C63*0.015) -> 600 | F63: =SUM(D63:E63) -> 8600 | L63: 1st Payment: | M63: =T58 -> 40000 | N63: =T58/T61 -> 8000 | O63: =(M63*0.015) -> 600 | P63: =SUM(N63:O63) -> 8600
B64: 2nd Payment: | C64: 32000 | D64: 8000 | E64: =(C64*0.015) -> 480 | F64: =SUM(D64:E64) -> 8480 | L64: 2nd Payment: | M64: 32000 | N64: 8000 | O64: =(M64*0.015) -> 480 | P64: =SUM(N64:O64) -> 8480
B65: 3rd Payment: | C65: 24000 | D65: 8000 | E65: =(C65*0.015) -> 360 | F65: =SUM(D65:E65) -> 8360 | L65: 3rd Payment: | M65: 24000 | N65: 8000 | O65: =(M65*0.015) -> 360 | P65: =SUM(N65:O65) -> 8360
B66: 4th Payment: | C66: 16000 | D66: 8000 | E66: =(C66*0.015) -> 240 | F66: =SUM(D66:E66) -> 8240 | L66: 4th Payment: | M66: 16000 | N66: 8000 | O66: =(M66*0.015) -> 240 | P66: =SUM(N66:O66) -> 8240
B67: 5th Payment: | C67: 8000 | D67: 8000 | E67: =(C67*0.015) -> 120 | F67: =SUM(D67:E67) -> 8120 | J67: Fully Paid | L67: 5th Payment: | M67: 8000 | N67: 8000 | O67: =(M67*0.015) -> 120 | P67: =SUM(N67:O67) -> 8120 | T67: Fully Paid
B70: Member's Name: | C70: De Mesa, Juczvil | H70: Loan Amount: | J70: 40000 | L70: Member's Name: | M70: De Mesa, Juczvil | R70: Loan Amount: | T70: 40000
B71: Membership Number: | I71: Date: | J71: 5/5/2025 | L71: Membership Number: | S71: Date: | T71: 5/5/2025
B72: No. of Loan's Made: | F72: Interest Rate: | J72: 0.015 | L72: No. of Loan's Made: | P72: Interest Rate: | T72: 0.015
B73: Mode of Payment: | E73: No. of Months to Pay: | J73: 5 | L73: Mode of Payment: | O73: No. of Months to Pay: | T73: 5
B74: Payment's Made | C74: Present Capital Loan | D74: Constant Payment Deducted to Capital Loan | E74: Interest Amount per Payment | F74: Amount to be Paid | G74: Paid Amount | H74: Date of Payment | I74: Receipt Number | J74: REMARKS | L74: Payment's Made | M74: Present Capital Loan | N74: Constant Payment Deducted to Capital Loan | O74: Interest Amount per Payment | P74: Amount to be Paid | Q74: Paid Amount | R74: Date of Payment | S74: Receipt Number | T74: REMARKS
B75: 1st Payment: | C75: =J70 -> 40000 | D75: =J70/J73 -> 8000 | E75: =(C75*0.015) -> 600 | F75: =SUM(D75:E75) -> 8600 | L75: 1st Payment: | M75: =T70 -> 40000 | N75: =T70/T73 -> 8000 | O75: =(M75*0.015) -> 600 | P75: =SUM(N75:O75) -> 8600
B76: 2nd Payment: | C76: 32000 | D76: 8000 | E76: =(C76*0.015) -> 480 | F76: =SUM(D76:E76) -> 8480 | L76: 2nd Payment: | M76: 32000 | N76: 8000 | O76: =(M76*0.015) -> 480 | P76: =SUM(N76:O76) -> 8480
B77: 3rd Payment: | C77: 24000 | D77: 8000 | E77: =(C77*0.015) -> 360 | F77: =SUM(D77:E77) -> 8360 | L77: 3rd Payment: | M77: 24000 | N77: 8000 | O77: =(M77*0.015) -> 360 | P77: =SUM(N77:O77) -> 8360
B78: 4th Payment: | C78: 16000 | D78: 8000 | E78: =(C78*0.015) -> 240 | F78: =SUM(D78:E78) -> 8240 | L78: 4th Payment: | M78: 16000 | N78: 8000 | O78: =(M78*0.015) -> 240 | P78: =SUM(N78:O78) -> 8240
B79: 5th Payment: | C79: 8000 | D79: 8000 | E79: =(C79*0.015) -> 120 | F79: =SUM(D79:E79) -> 8120 | J79: Fully Paid | L79: 5th Payment: | M79: 8000 | N79: 8000 | O79: =(M79*0.015) -> 120 | P79: =SUM(N79:O79) -> 8120 | T79: Fully Paid
B82: Member's Name: | C82: Ungriano, Dianne | F82: Emergency Loan | H82: Loan Amount: | J82: 5000 | L82: Member's Name: | M82: Ungriano, Dianne | P82: Emergency Loan | R82: Loan Amount: | T82: 5000
B83: Membership Number: | I83: Date: | J83: 6/9/2025 | L83: Membership Number: | S83: Date: | T83: 6/9/2025
B84: No. of Loan's Made: | F84: Interest Rate: | J84: 0.015 | L84: No. of Loan's Made: | P84: Interest Rate: | T84: 0.015
B85: Mode of Payment: | E85: No. of Months to Pay: | J85: 5 | L85: Mode of Payment: | O85: No. of Months to Pay: | T85: 5
B86: Payment's Made | C86: Present Capital Loan | D86: Constant Payment Deducted to Capital Loan | E86: Interest Amount per Payment | F86: Amount to be Paid | G86: Paid Amount | H86: Date of Payment | I86: Receipt Number | J86: REMARKS | L86: Payment's Made | M86: Present Capital Loan | N86: Constant Payment Deducted to Capital Loan | O86: Interest Amount per Payment | P86: Amount to be Paid | Q86: Paid Amount | R86: Date of Payment | S86: Receipt Number | T86: REMARKS
B87: 1st Payment: | C87: =J82 -> 5000 | D87: =J82/J85 -> 1000 | E87: =(C87*0.015) -> 75 | F87: =SUM(D87:E87) -> 1075 | L87: 1st Payment: | M87: =T82 -> 5000 | N87: =T82/T85 -> 1000 | O87: =(M87*0.015) -> 75 | P87: =SUM(N87:O87) -> 1075
B88: 2nd Payment: | C88: 4000 | D88: 1000 | E88: =(C88*0.015) -> 60 | F88: =SUM(D88:E88) -> 1060 | L88: 2nd Payment: | M88: 4000 | N88: 1000 | O88: =(M88*0.015) -> 60 | P88: =SUM(N88:O88) -> 1060
B89: 3rd Payment: | C89: 3000 | D89: 1000 | E89: =(C89*0.015) -> 45 | F89: =SUM(D89:E89) -> 1045 | L89: 3rd Payment: | M89: 3000 | N89: 1000 | O89: =(M89*0.015) -> 45 | P89: =SUM(N89:O89) -> 1045
B90: 4th Payment: | C90: 2000 | D90: 1000 | E90: =(C90*0.015) -> 30 | F90: =SUM(D90:E90) -> 1030 | L90: 4th Payment: | M90: 2000 | N90: 1000 | O90: =(M90*0.015) -> 30 | P90: =SUM(N90:O90) -> 1030
B91: 5th Payment: | C91: 1000 | D91: 1000 | E91: =(C91*0.015) -> 15 | F91: =SUM(D91:E91) -> 1015 | J91: Fully Paid | L91: 5th Payment: | M91: 1000 | N91: 1000 | O91: =(M91*0.015) -> 15 | P91: =SUM(N91:O91) -> 1015 | T91: Fully Paid

Sheet 10 mos
B1: Member's Name: | C1: Mirana, Yolanda | I1: Loan Amount: | J1: 15000 | L1: Member's Name: | M1: Mirana, Yolanda | S1: Loan Amount: | T1: 15000
B2: Membership Number: | I2: Date: | J2: 6/20/2023 | L2: Membership Number: | S2: Date: | T2: 6/20/2023
B3: No. of Loan's Made: | I3: Interest Rate: | J3: 0.015 | L3: No. of Loan's Made: | S3: Interest Rate: | T3: 0.015
B4: Mode of Payment: | I4: No. of Months to Pay: | J4: 10 | L4: Mode of Payment: | S4: No. of Months to Pay: | T4: 10
B5: Payment's Made | C5: Present Capital Loan | D5: Constant Payment Deducted to Capital Loan | E5: Interest Amount per Payment | F5: Amount to be Paid | G5: Paid Amount | H5: Date of Payment | I5: Receipt Number | J5: REMARKS | L5: Payment's Made | M5: Present Capital Loan | N5: Constant Payment Deducted to Capital Loan | O5: Interest Amount per Payment | P5: Amount to be Paid | Q5: Paid Amount | R5: Date of Payment | S5: Receipt Number | T5: REMARKS
B6: 1st Payment: | C6: =J1 -> 15000 | D6: =J1/J4 -> 1500 | E6: =(C6*0.015) -> 225 | F6: =SUM(D6:E6) -> 1725 | L6: 1st Payment: | M6: =T1 -> 15000 | N6: =T1/T4 -> 1500 | O6: =(M6*0.015) -> 225 | P6: =SUM(N6:O6) -> 1725
B7: 2nd Payment: | C7: 13500 | D7: 1500 | E7: =(C7*0.015) -> 202.5 | F7: =SUM(D7:E7) -> 1702.5 | L7: 2nd Payment: | M7: 13500 | N7: 1500 | O7: =(M7*0.015) -> 202.5 | P7: =SUM(N7:O7) -> 1702.5
B8: 3rd Payment: | C8: 12000 | D8: 1500 | E8: =(C8*0.015) -> 180 | F8: =SUM(D8:E8) -> 1680 | L8: 3rd Payment: | M8: 12000 | N8: 1500 | O8: =(M8*0.015) -> 180 | P8: =SUM(N8:O8) -> 1680
B9: 4th Payment: | C9: 10500 | D9: 1500 | E9: =(C9*0.015) -> 157.5 | F9: =SUM(D9:E9) -> 1657.5 | L9: 4th Payment: | M9: 10500 | N9: 1500 | O9: =(M9*0.015) -> 157.5 | P9: =SUM(N9:O9) -> 1657.5
B10: 5th Payment: | C10: 9000 | D10: 1500 | E10: =(C10*0.015) -> 135 | F10: =SUM(D10:E10) -> 1635 | L10: 5th Payment: | M10: 9000 | N10: 1500 | O10: =(M10*0.015) -> 135 | P10: =SUM(N10:O10) -> 1635
B11: 6th Payment: | C11: 7500 | D11: 1500 | E11: =(C11*0.015) -> 112.5 | F11: =SUM(D11:E11) -> 1612.5 | L11: 6th Payment: | M11: 7500 | N11: 1500 | O11: =(M11*0.015) -> 112.5 | P11: =SUM(N11:O11) -> 1612.5
B12: 7th Payment: | C12: 6000 | D12: 1500 | E12: =(C12*0.015) -> 90 | F12: =SUM(D12:E12) -> 1590 | L12: 7th Payment: | M12: 6000 | N12: 1500 | O12: =(M12*0.015) -> 90 | P12: =SUM(N12:O12) -> 1590
B13: 8th Payment: | C13: 4500 | D13: 1500 | E13: =(C13*0.015) -> 67.5 | F13: =SUM(D13:E13) -> 1567.5 | L13: 8th Payment: | M13: 4500 | N13: 1500 | O13: =(M13*0.015) -> 67.5 | P13: =SUM(N13:O13) -> 1567.5
B14: 9th Payment: | C14: 3000 | D14: 1500 | E14: =(C14*0.015) -> 45 | F14: =SUM(D14:E14) -> 1545 | L14: 9th Payment: | M14: 3000 | N14: 1500 | O14: =(M14*0.015) -> 45 | P14: =SUM(N14:O14) -> 1545
B15: 10th Payment: | C15: 1500 | D15: 1500 | E15: =(C15*0.015) -> 22.5 | F15: =SUM(D15:E15) -> 1522.5 | J15: Fully Paid | L15: 10th Payment: | M15: 1500 | N15: 1500 | O15: =(M15*0.015) -> 22.5 | P15: =SUM(N15:O15) -> 1522.5 | T15: Fully Paid
B18: Member's Name: | C18: Tuzon, Arlenita | I18: Loan Amount: | J18: 100000 | L18: Member's Name: | M18: Tuzon, Arlenita | S18: Loan Amount: | T18: 100000
B19: Membership Number: | I19: Date: | J19: 5/16/2025 | L19: Membership Number: | S19: Date: | T19: 5/16/2025
B20: No. of Loan's Made: | I20: Interest Rate: | J20: 0.015 | L20: No. of Loan's Made: | S20: Interest Rate: | T20: 0.015
B21: Mode of Payment: | I21: No. of Months to Pay: | J21: 10 | L21: Mode of Payment: | S21: No. of Months to Pay: | T21: 10
B22: Payment's Made | C22: Present Capital Loan | D22: Constant Payment Deducted to Capital Loan | E22: Interest Amount per Payment | F22: Amount to be Paid | G22: Paid Amount | H22: Date of Payment | I22: Receipt Number | J22: REMARKS | L22: Payment's Made | M22: Present Capital Loan | N22: Constant Payment Deducted to Capital Loan | O22: Interest Amount per Payment | P22: Amount to be Paid | Q22: Paid Amount | R22: Date of Payment | S22: Receipt Number | T22: REMARKS
B23: 1st Payment: | C23: =J18 -> 100000 | D23: =J18/J21 -> 10000 | E23: =(C23*0.015) -> 1500 | F23: =SUM(D23:E23) -> 11500 | L23: 1st Payment: | M23: =T18 -> 100000 | N23: =T18/T21 -> 10000 | O23: =(M23*0.015) -> 1500 | P23: =SUM(N23:O23) -> 11500
B24: 2nd Payment: | C24: 90000 | D24: 10000 | E24: =(C24*0.015) -> 1350 | F24: =SUM(D24:E24) -> 11350 | L24: 2nd Payment: | M24: 90000 | N24: 10000 | O24: =(M24*0.015) -> 1350 | P24: =SUM(N24:O24) -> 11350
B25: 3rd Payment: | C25: 80000 | D25: 10000 | E25: =(C25*0.015) -> 1200 | F25: =SUM(D25:E25) -> 11200 | L25: 3rd Payment: | M25: 80000 | N25: 10000 | O25: =(M25*0.015) -> 1200 | P25: =SUM(N25:O25) -> 11200
B26: 4th Payment: | C26: 70000 | D26: 10000 | E26: =(C26*0.015) -> 1050 | F26: =SUM(D26:E26) -> 11050 | L26: 4th Payment: | M26: 70000 | N26: 10000 | O26: =(M26*0.015) -> 1050 | P26: =SUM(N26:O26) -> 11050
B27: 5th Payment: | C27: 60000 | D27: 10000 | E27: =(C27*0.015) -> 900 | F27: =SUM(D27:E27) -> 10900 | L27: 5th Payment: | M27: 60000 | N27: 10000 | O27: =(M27*0.015) -> 900 | P27: =SUM(N27:O27) -> 10900
B28: 6th Payment: | C28: 50000 | D28: 10000 | E28: =(C28*0.015) -> 750 | F28: =SUM(D28:E28) -> 10750 | L28: 6th Payment: | M28: 50000 | N28: 10000 | O28: =(M28*0.015) -> 750 | P28: =SUM(N28:O28) -> 10750
B29: 7th Payment: | C29: 40000 | D29: 10000 | E29: =(C29*0.015) -> 600 | F29: =SUM(D29:E29) -> 10600 | L29: 7th Payment: | M29: 40000 | N29: 10000 | O29: =(M29*0.015) -> 600 | P29: =SUM(N29:O29) -> 10600
B30: 8th Payment: | C30: 30000 | D30: 10000 | E30: =(C30*0.015) -> 450 | F30: =SUM(D30:E30) -> 10450 | L30: 8th Payment: | M30: 30000 | N30: 10000 | O30: =(M30*0.015) -> 450 | P30: =SUM(N30:O30) -> 10450
B31: 9th Payment: | C31: 20000 | D31: 10000 | E31: =(C31*0.015) -> 300 | F31: =SUM(D31:E31) -> 10300 | L31: 9th Payment: | M31: 20000 | N31: 10000 | O31: =(M31*0.015) -> 300 | P31: =SUM(N31:O31) -> 10300
B32: 10th Payment: | C32: 10000 | D32: 10000 | E32: =(C32*0.015) -> 150 | F32: =SUM(D32:E32) -> 10150 | J32: Fully Paid | L32: 10th Payment: | M32: 10000 | N32: 10000 | O32: =(M32*0.015) -> 150 | P32: =SUM(N32:O32) -> 10150 | T32: Fully Paid
B35: Member's Name: | C35: Gonzales, Emerita | I35: Loan Amount: | J35: 30000 | L35: Member's Name: | M35: Gonzales, Emerita | S35: Loan Amount: | T35: 30000
B36: Membership Number: | I36: Date: | J36: 7/16/2025 | L36: Membership Number: | S36: Date: | T36: 7/16/2025
B37: No. of Loan's Made: | I37: Interest Rate: | J37: 0.015 | L37: No. of Loan's Made: | S37: Interest Rate: | T37: 0.015
B38: Mode of Payment: | I38: No. of Months to Pay: | J38: 10 | L38: Mode of Payment: | S38: No. of Months to Pay: | T38: 10
B39: Payment's Made | C39: Present Capital Loan | D39: Constant Payment Deducted to Capital Loan | E39: Interest Amount per Payment | F39: Amount to be Paid | G39: Paid Amount | H39: Date of Payment | I39: Receipt Number | J39: REMARKS | L39: Payment's Made | M39: Present Capital Loan | N39: Constant Payment Deducted to Capital Loan | O39: Interest Amount per Payment | P39: Amount to be Paid | Q39: Paid Amount | R39: Date of Payment | S39: Receipt Number | T39: REMARKS
B40: 1st Payment: | C40: =J35 -> 30000 | D40: =J35/J38 -> 3000 | E40: =(C40*0.015) -> 450 | F40: =SUM(D40:E40) -> 3450 | L40: 1st Payment: | M40: =T35 -> 30000 | N40: =T35/T38 -> 3000 | O40: =(M40*0.015) -> 450 | P40: =SUM(N40:O40) -> 3450
B41: 2nd Payment: | C41: 27000 | D41: 3000 | E41: =(C41*0.015) -> 405 | F41: =SUM(D41:E41) -> 3405 | L41: 2nd Payment: | M41: 27000 | N41: 3000 | O41: =(M41*0.015) -> 405 | P41: =SUM(N41:O41) -> 3405
B42: 3rd Payment: | C42: 24000 | D42: 3000 | E42: =(C42*0.015) -> 360 | F42: =SUM(D42:E42) -> 3360 | L42: 3rd Payment: | M42: 24000 | N42: 3000 | O42: =(M42*0.015) -> 360 | P42: =SUM(N42:O42) -> 3360
B43: 4th Payment: | C43: 21000 | D43: 3000 | E43: =(C43*0.015) -> 315 | F43: =SUM(D43:E43) -> 3315 | L43: 4th Payment: | M43: 21000 | N43: 3000 | O43: =(M43*0.015) -> 315 | P43: =SUM(N43:O43) -> 3315
B44: 5th Payment: | C44: 18000 | D44: 3000 | E44: =(C44*0.015) -> 270 | F44: =SUM(D44:E44) -> 3270 | L44: 5th Payment: | M44: 18000 | N44: 3000 | O44: =(M44*0.015) -> 270 | P44: =SUM(N44:O44) -> 3270
B45: 6th Payment: | C45: 15000 | D45: 3000 | E45: =(C45*0.015) -> 225 | F45: =SUM(D45:E45) -> 3225 | L45: 6th Payment: | M45: 15000 | N45: 3000 | O45: =(M45*0.015) -> 225 | P45: =SUM(N45:O45) -> 3225
B46: 7th Payment: | C46: 12000 | D46: 3000 | E46: =(C46*0.015) -> 180 | F46: =SUM(D46:E46) -> 3180 | L46: 7th Payment: | M46: 12000 | N46: 3000 | O46: =(M46*0.015) -> 180 | P46: =SUM(N46:O46) -> 3180
B47: 8th Payment: | C47: 9000 | D47: 3000 | E47: =(C47*0.015) -> 135 | F47: =SUM(D47:E47) -> 3135 | L47: 8th Payment: | M47: 9000 | N47: 3000 | O47: =(M47*0.015) -> 135 | P47: =SUM(N47:O47) -> 3135
B48: 9th Payment: | C48: 6000 | D48: 3000 | E48: =(C48*0.015) -> 90 | F48: =SUM(D48:E48) -> 3090 | L48: 9th Payment: | M48: 6000 | N48: 3000 | O48: =(M48*0.015) -> 90 | P48: =SUM(N48:O48) -> 3090
B49: 10th Payment: | C49: 3000 | D49: 3000 | E49: =(C49*0.015) -> 45 | F49: =SUM(D49:E49) -> 3045 | J49: Fully Paid | L49: 10th Payment: | M49: 3000 | N49: 3000 | O49: =(M49*0.015) -> 45 | P49: =SUM(N49:O49) -> 3045 | T49: Fully Paid
B52: Member's Name: | C52: Gonzales, Emerita | I52: Loan Amount: | J52: 30000 | L52: Member's Name: | M52: Gonzales, Emerita | S52: Loan Amount: | T52: 30000
B53: Membership Number: | I53: Date: | J53: 7/16/2025 | L53: Membership Number: | S53: Date: | T53: 7/16/2025
B54: No. of Loan's Made: | I54: Interest Rate: | J54: 0.015 | L54: No. of Loan's Made: | S54: Interest Rate: | T54: 0.015
B55: Mode of Payment: | I55: No. of Months to Pay: | J55: 10 | L55: Mode of Payment: | S55: No. of Months to Pay: | T55: 10
B56: Payment's Made | C56: Present Capital Loan | D56: Constant Payment Deducted to Capital Loan | E56: Interest Amount per Payment | F56: Amount to be Paid | G56: Paid Amount | H56: Date of Payment | I56: Receipt Number | J56: REMARKS | L56: Payment's Made | M56: Present Capital Loan | N56: Constant Payment Deducted to Capital Loan | O56: Interest Amount per Payment | P56: Amount to be Paid | Q56: Paid Amount | R56: Date of Payment | S56: Receipt Number | T56: REMARKS
B57: 1st Payment: | C57: =J52 -> 30000 | D57: =J52/J55 -> 3000 | E57: =(C57*0.015) -> 450 | F57: =SUM(D57:E57) -> 3450 | L57: 1st Payment: | M57: =T52 -> 30000 | N57: =T52/T55 -> 3000 | O57: =(M57*0.015) -> 450 | P57: =SUM(N57:O57) -> 3450
B58: 2nd Payment: | C58: 27000 | D58: 3000 | E58: =(C58*0.015) -> 405 | F58: =SUM(D58:E58) -> 3405 | L58: 2nd Payment: | M58: 27000 | N58: 3000 | O58: =(M58*0.015) -> 405 | P58: =SUM(N58:O58) -> 3405
B59: 3rd Payment: | C59: 24000 | D59: 3000 | E59: =(C59*0.015) -> 360 | F59: =SUM(D59:E59) -> 3360 | L59: 3rd Payment: | M59: 24000 | N59: 3000 | O59: =(M59*0.015) -> 360 | P59: =SUM(N59:O59) -> 3360
B60: 4th Payment: | C60: 21000 | D60: 3000 | E60: =(C60*0.015) -> 315 | F60: =SUM(D60:E60) -> 3315 | L60: 4th Payment: | M60: 21000 | N60: 3000 | O60: =(M60*0.015) -> 315 | P60: =SUM(N60:O60) -> 3315
B61: 5th Payment: | C61: 18000 | D61: 3000 | E61: =(C61*0.015) -> 270 | F61: =SUM(D61:E61) -> 3270 | L61: 5th Payment: | M61: 18000 | N61: 3000 | O61: =(M61*0.015) -> 270 | P61: =SUM(N61:O61) -> 3270
B62: 6th Payment: | C62: 15000 | D62: 3000 | E62: =(C62*0.015) -> 225 | F62: =SUM(D62:E62) -> 3225 | L62: 6th Payment: | M62: 15000 | N62: 3000 | O62: =(M62*0.015) -> 225 | P62: =SUM(N62:O62) -> 3225
B63: 7th Payment: | C63: 12000 | D63: 3000 | E63: =(C63*0.015) -> 180 | F63: =SUM(D63:E63) -> 3180 | L63: 7th Payment: | M63: 12000 | N63: 3000 | O63: =(M63*0.015) -> 180 | P63: =SUM(N63:O63) -> 3180
B64: 8th Payment: | C64: 9000 | D64: 3000 | E64: =(C64*0.015) -> 135 | F64: =SUM(D64:E64) -> 3135 | L64: 8th Payment: | M64: 9000 | N64: 3000 | O64: =(M64*0.015) -> 135 | P64: =SUM(N64:O64) -> 3135
B65: 9th Payment: | C65: 6000 | D65: 3000 | E65: =(C65*0.015) -> 90 | F65: =SUM(D65:E65) -> 3090 | L65: 9th Payment: | M65: 6000 | N65: 3000 | O65: =(M65*0.015) -> 90 | P65: =SUM(N65:O65) -> 3090
B66: 10th Payment: | C66: 3000 | D66: 3000 | E66: =(C66*0.015) -> 45 | F66: =SUM(D66:E66) -> 3045 | J66: Fully Paid | L66: 10th Payment: | M66: 3000 | N66: 3000 | O66: =(M66*0.015) -> 45 | P66: =SUM(N66:O66) -> 3045 | T66: Fully Paid
F67: =SUM(F57:F66) -> 32475
B239: Member's Name: | C239: Pineda, Rogelio | I239: Loan Amount: | J239: 40000 | L239: Member's Name: | M239: Pineda, Rogelio | S239: Loan Amount: | T239: 40000
B240: Membership Number: | I240: Date: | J240: 4/19/2024 | L240: Membership Number: | S240: Date: | T240: 4/19/2024
B241: No. of Loan's Made: | I241: Interest Rate: | J241: 0.015 | L241: No. of Loan's Made: | S241: Interest Rate: | T241: 0.015
B242: Mode of Payment: | I242: No. of Months to Pay: | J242: 10 | L242: Mode of Payment: | S242: No. of Months to Pay: | T242: 10
B243: Payment's Made | C243: Present Capital Loan | D243: Constant Payment Deducted to Capital Loan | E243: Interest Amount per Payment | F243: Amount to be Paid | G243: Paid Amount | H243: Date of Payment | I243: Receipt Number | J243: REMARKS | L243: Payment's Made | M243: Present Capital Loan | N243: Constant Payment Deducted to Capital Loan | O243: Interest Amount per Payment | P243: Amount to be Paid | Q243: Paid Amount | R243: Date of Payment | S243: Receipt Number | T243: REMARKS
B244: 1st Payment: | C244: =J239 -> 40000 | D244: =J239/J242 -> 4000 | E244: =(C244*0.015) -> 600 | F244: =SUM(D244:E244) -> 4600 | L244: 1st Payment: | M244: =T239 -> 40000 | N244: =T239/T242 -> 4000 | O244: =(M244*0.015) -> 600 | P244: =SUM(N244:O244) -> 4600
B245: 2nd Payment: | C245: 36000 | D245: 4000 | E245: =(C245*0.015) -> 540 | F245: =SUM(D245:E245) -> 4540 | L245: 2nd Payment: | M245: 36000 | N245: 4000 | O245: =(M245*0.015) -> 540 | P245: =SUM(N245:O245) -> 4540
B246: 3rd Payment: | C246: 32000 | D246: 4000 | E246: 500 | F246: =SUM(D246:E246) -> 4500 | L246: 3rd Payment: | M246: 32000 | N246: 4000 | O246: 500 | P246: =SUM(N246:O246) -> 4500
B247: 4th Payment: | C247: 28000 | D247: 4000 | E247: =(C247*0.015) -> 420 | F247: =SUM(D247:E247) -> 4420 | L247: 4th Payment: | M247: 28000 | N247: 4000 | O247: =(M247*0.015) -> 420 | P247: =SUM(N247:O247) -> 4420
B248: 5th Payment: | C248: 24000 | D248: 4000 | E248: =(C248*0.015) -> 360 | F248: =SUM(D248:E248) -> 4360 | L248: 5th Payment: | M248: 24000 | N248: 4000 | O248: =(M248*0.015) -> 360 | P248: =SUM(N248:O248) -> 4360
B249: 6th Payment: | C249: 20000 | D249: 4000 | E249: =(C249*0.015) -> 300 | F249: =SUM(D249:E249) -> 4300 | L249: 6th Payment: | M249: 20000 | N249: 4000 | O249: =(M249*0.015) -> 300 | P249: =SUM(N249:O249) -> 4300
B250: 7th Payment: | C250: 16000 | D250: 4000 | E250: =(C250*0.015) -> 240 | F250: =SUM(D250:E250) -> 4240 | L250: 7th Payment: | M250: 16000 | N250: 4000 | O250: =(M250*0.015) -> 240 | P250: =SUM(N250:O250) -> 4240
B251: 8th Payment: | C251: 12000 | D251: 4000 | E251: =(C251*0.015) -> 180 | F251: =SUM(D251:E251) -> 4180 | L251: 8th Payment: | M251: 12000 | N251: 4000 | O251: =(M251*0.015) -> 180 | P251: =SUM(N251:O251) -> 4180
B252: 9th Payment: | C252: 8000 | D252: 4000 | E252: =(C252*0.015) -> 120 | F252: =SUM(D252:E252) -> 4120 | L252: 9th Payment: | M252: 8000 | N252: 4000 | O252: =(M252*0.015) -> 120 | P252: =SUM(N252:O252) -> 4120
B253: 10th Payment: | C253: 4000 | D253: 4000 | E253: =(C253*0.015) -> 60 | F253: =SUM(D253:E253) -> 4060 | J253: Fully Paid | L253: 10th Payment: | M253: 4000 | N253: 4000 | O253: =(M253*0.015) -> 60 | P253: =SUM(N253:O253) -> 4060 | T253: Fully Paid
B257: Member's Name: | C257: Payawal, Rowena | F257: Emergency Loan | H257: Loan Amount: | J257: 10000 | L257: Member's Name: | M257: Payawal, Rowena | P257: Emergency Loan | R257: Loan Amount: | T257: 10000
B258: Membership Number: | I258: Date: | J258: 5/24/2024 | L258: Membership Number: | S258: Date: | T258: 5/24/2024
B259: No. of Loan's Made: | F259: Interest Rate: | J259: 0.015 | L259: No. of Loan's Made: | P259: Interest Rate: | T259: 0.015
B260: Mode of Payment: | E260: No. of Months to Pay: | J260: 10 | L260: Mode of Payment: | O260: No. of Months to Pay: | T260: 10
B261: Payment's Made | C261: Present Capital Loan | D261: Constant Payment Deducted to Capital Loan | E261: Interest Amount per Payment | F261: Amount to be Paid | G261: Paid Amount | H261: Date of Payment | I261: Receipt Number | J261: REMARKS | L261: Payment's Made | M261: Present Capital Loan | N261: Constant Payment Deducted to Capital Loan | O261: Interest Amount per Payment | P261: Amount to be Paid | Q261: Paid Amount | R261: Date of Payment | S261: Receipt Number | T261: REMARKS
B262: 1st Payment: | C262: =J257 -> 10000 | D262: 1000 | E262: =(C262*0.015) -> 150 | F262: =SUM(D262:E262) -> 1150 | L262: 1st Payment: | M262: =T257 -> 10000 | N262: 1000 | O262: =(M262*0.015) -> 150 | P262: =SUM(N262:O262) -> 1150
B263: 2nd Payment: | C263: 9000 | D263: 1000 | E263: =(C263*0.015) -> 135 | F263: =SUM(D263:E263) -> 1135 | L263: 2nd Payment: | M263: 9000 | N263: 1000 | O263: =(M263*0.015) -> 135 | P263: =SUM(N263:O263) -> 1135
B264: 3rd Payment: | C264: 8000 | D264: 1000 | E264: =(C264*0.015) -> 120 | F264: =SUM(D264:E264) -> 1120 | L264: 3rd Payment: | M264: 8000 | N264: 1000 | O264: =(M264*0.015) -> 120 | P264: =SUM(N264:O264) -> 1120
B265: 4th Payment: | C265: 7000 | D265: 1000 | E265: =(C265*0.015) -> 105 | F265: =SUM(D265:E265) -> 1105 | L265: 4th Payment: | M265: 7000 | N265: 1000 | O265: =(M265*0.015) -> 105 | P265: =SUM(N265:O265) -> 1105
B266: 5th Payment: | C266: 6000 | D266: 1000 | E266: =(C266*0.015) -> 90 | F266: =SUM(D266:E266) -> 1090 | L266: 5th Payment: | M266: 6000 | N266: 1000 | O266: =(M266*0.015) -> 90 | P266: =SUM(N266:O266) -> 1090
B267: 6th Payment: | C267: 5000 | D267: 1000 | E267: =(C267*0.015) -> 75 | F267: =SUM(D267:E267) -> 1075 | L267: 6th Payment: | M267: 5000 | N267: 1000 | O267: =(M267*0.015) -> 75 | P267: =SUM(N267:O267) -> 1075
B268: 7th Payment: | C268: 4000 | D268: 1000 | E268: =(C268*0.015) -> 60 | F268: =SUM(D268:E268) -> 1060 | L268: 7th Payment: | M268: 4000 | N268: 1000 | O268: =(M268*0.015) -> 60 | P268: =SUM(N268:O268) -> 1060
B269: 8th Payment: | C269: 3000 | D269: 1000 | E269: =(C269*0.015) -> 45 | F269: =SUM(D269:E269) -> 1045 | L269: 8th Payment: | M269: 3000 | N269: 1000 | O269: =(M269*0.015) -> 45 | P269: =SUM(N269:O269) -> 1045
B270: 9th Payment: | C270: 2000 | D270: 1000 | E270: =(C270*0.015) -> 30 | F270: =SUM(D270:E270) -> 1030 | L270: 9th Payment: | M270: 2000 | N270: 1000 | O270: =(M270*0.015) -> 30 | P270: =SUM(N270:O270) -> 1030
B271: 10th Payment: | C271: 1000 | D271: 1000 | E271: =(C271*0.015) -> 15 | F271: =SUM(D271:E271) -> 1015 | J271: Fully Paid | L271: 10th Payment: | M271: 1000 | N271: 1000 | O271: =(M271*0.015) -> 15 | P271: =SUM(N271:O271) -> 1015 | T271: Fully Paid
F272: =SUM(F262:F271) -> 10825
B293: Member's Name: | C293: Coronel, Elizabeth | H293: Loan Amount: | J293: 10000 | L293: Member's Name: | M293: Coronel, Elizabeth | R293: Loan Amount: | T293: 10000
B294: Membership Number: | I294: Date: | J294: 11/22/2024 | L294: Membership Number: | S294: Date: | T294: 11/22/2024
B295: No. of Loan's Made: | F295: Interest Rate: | J295: 0.015 | L295: No. of Loan's Made: | P295: Interest Rate: | T295: 0.015
B296: Mode of Payment: | E296: No. of Months to Pay: | J296: 5 | L296: Mode of Payment: | O296: No. of Months to Pay: | T296: 5
B297: Payment's Made | C297: Present Capital Loan | D297: Constant Payment Deducted to Capital Loan | E297: Interest Amount per Payment | F297: Amount to be Paid | G297: Paid Amount | H297: Date of Payment | I297: Receipt Number | J297: REMARKS | L297: Payment's Made | M297: Present Capital Loan | N297: Constant Payment Deducted to Capital Loan | O297: Interest Amount per Payment | P297: Amount to be Paid | Q297: Paid Amount | R297: Date of Payment | S297: Receipt Number | T297: REMARKS
B298: 1st Payment: | C298: =J293 -> 10000 | D298: =J293/J296 -> 2000 | E298: =(C298*0.015) -> 150 | F298: =SUM(D298:E298) -> 2150 | L298: 1st Payment: | M298: =T293 -> 10000 | N298: =T293/T296 -> 2000 | O298: =(M298*0.015) -> 150 | P298: =SUM(N298:O298) -> 2150
B299: 2nd Payment: | C299: 8000 | D299: 2000 | E299: =(C299*0.015) -> 120 | F299: =SUM(D299:E299) -> 2120 | L299: 2nd Payment: | M299: 8000 | N299: 2000 | O299: =(M299*0.015) -> 120 | P299: =SUM(N299:O299) -> 2120
B300: 3rd Payment: | C300: 6000 | D300: 2000 | E300: =(C300*0.015) -> 90 | F300: =SUM(D300:E300) -> 2090 | L300: 3rd Payment: | M300: 6000 | N300: 2000 | O300: =(M300*0.015) -> 90 | P300: =SUM(N300:O300) -> 2090
...

Sheet 12 mos
B1: Member's Name: | C1: Anastacio, Asuncion | H1: Loan Amount: | J1: 80000 | L1: Member's Name: | M1: Anastacio, Asuncion | R1: Loan Amount: | T1: 80000
B2: Membership Number: | I2: Date: | J2: 3/7/2024 | L2: Membership Number: | S2: Date: | T2: 3/7/2024
B3: No. of Loan's Made: | F3: Interest Rate: | J3: 0.015 | L3: No. of Loan's Made: | P3: Interest Rate: | T3: 0.015
B4: Mode of Payment: | E4: No. of Months to Pay: | J4: 12 | L4: Mode of Payment: | O4: No. of Months to Pay: | T4: 12
B5: Payment's Made | C5: Present Capital Loan | D5: Constant Payment Deducted to Capital Loan | E5: Interest Amount per Payment | F5: Amount to be Paid | G5: Paid Amount | H5: Date of Payment | I5: Receipt Number | J5: REMARKS | L5: Payment's Made | M5: Present Capital Loan | N5: Constant Payment Deducted to Capital Loan | O5: Interest Amount per Payment | P5: Amount to be Paid | Q5: Paid Amount | R5: Date of Payment | S5: Receipt Number | T5: REMARKS
B6: 1st Payment: | C6: =J1 -> 80000 | D6: =J1/J4 -> 6666.6667 | E6: =(C6*0.015) -> 1200 | F6: =SUM(D6:E6) -> 7866.6667 | G6: 7500 | L6: 1st Payment: | M6: =T1 -> 80000 | N6: =T1/T4 -> 6666.6667 | O6: =(M6*0.015) -> 1200 | P6: =SUM(N6:O6) -> 7866.6667
B7: 2nd Payment: | C7: 73337 | D7: 6667 | E7: =(C7*0.015) -> 1100.055 | F7: =SUM(D7:E7) -> 7767.055 | L7: 2nd Payment: | M7: 73337 | N7: 6667 | O7: =(M7*0.015) -> 1100.055 | P7: =SUM(N7:O7) -> 7767.055
B8: 3rd Payment: | C8: 66670 | D8: 6667 | E8: =(C8*0.015) -> 1000.05 | F8: =SUM(D8:E8) -> 7667.05 | L8: 3rd Payment: | M8: 66670 | N8: 6667 | O8: =(M8*0.015) -> 1000.05 | P8: =SUM(N8:O8) -> 7667.05
B9: 4th Payment: | C9: 60003 | D9: 6667 | E9: =(C9*0.015) -> 900.045 | F9: =SUM(D9:E9) -> 7567.045 | L9: 4th Payment: | M9: 60003 | N9: 6667 | O9: =(M9*0.015) -> 900.045 | P9: =SUM(N9:O9) -> 7567.045
B10: 5th Payment: | C10: 53336 | D10: 6667 | E10: =(C10*0.015) -> 800.04 | F10: =SUM(D10:E10) -> 7467.04 | L10: 5th Payment: | M10: 53336 | N10: 6667 | O10: =(M10*0.015) -> 800.04 | P10: =SUM(N10:O10) -> 7467.04
B11: 6th Payment: | C11: 46669 | D11: 6667 | E11: =(C11*0.015) -> 700.035 | F11: =SUM(D11:E11) -> 7367.035 | L11: 6th Payment: | M11: 46669 | N11: 6667 | O11: =(M11*0.015) -> 700.035 | P11: =SUM(N11:O11) -> 7367.035
B12: 7th Payment: | C12: 40002 | D12: 6667 | E12: =(C12*0.015) -> 600.03 | F12: =SUM(D12:E12) -> 7267.03 | L12: 7th Payment: | M12: 40002 | N12: 6667 | O12: =(M12*0.015) -> 600.03 | P12: =SUM(N12:O12) -> 7267.03
B13: 8th Payment: | C13: 33335 | D13: 6667 | E13: =(C13*0.015) -> 500.025 | F13: =SUM(D13:E13) -> 7167.025 | L13: 8th Payment: | M13: 33335 | N13: 6667 | O13: =(M13*0.015) -> 500.025 | P13: =SUM(N13:O13) -> 7167.025
B14: 9th Payment: | C14: 26668 | D14: 6667 | E14: =(C14*0.015) -> 400.02 | F14: =SUM(D14:E14) -> 7067.02 | L14: 9th Payment: | M14: 26668 | N14: 6667 | O14: =(M14*0.015) -> 400.02 | P14: =SUM(N14:O14) -> 7067.02
B15: 10th Payment: | C15: 20001 | D15: 6667 | E15: =(C15*0.015) -> 300.015 | F15: =SUM(D15:E15) -> 6967.015 | L15: 10th Payment: | M15: 20001 | N15: 6667 | O15: =(M15*0.015) -> 300.015 | P15: =SUM(N15:O15) -> 6967.015
B16: 11th Payment: | C16: 13334 | D16: 6667 | E16: =(C16*0.015) -> 200.01 | F16: =SUM(D16:E16) -> 6867.01 | L16: 11th Payment: | M16: 13334 | N16: 6667 | O16: =(M16*0.015) -> 200.01 | P16: =SUM(N16:O16) -> 6867.01
B17: 12th Payment: | C17: 6667 | D17: 6667 | E17: =(C17*0.015) -> 100.005 | F17: =SUM(D17:E17) -> 6767.005 | J17: Fully Paid | L17: 12th Payment: | M17: 6667 | N17: 6667 | O17: =(M17*0.015) -> 100.005 | P17: =SUM(N17:O17) -> 6767.005 | T17: Fully Paid
E18: =SUM(E6:E17) -> 7800.33 | F18: =SUM(F6:F17) -> 87803.997 | G18: =SUM(G6:G17) -> 7500
B20: Member's Name: | C20: Tangtang, Neddie | I20: Loan Amount: | J20: 10000 | L20: Member's Name: | M20: Tangtang, Neddie | S20: Loan Amount: | T20: 10000
B21: Membership Number: | I21: Date: | J21: 4/18/2024 | L21: Membership Number: | S21: Date: | T21: 4/18/2024
B22: No. of Loan's Made: | I22: Interest Rate: | J22: 0.015 | L22: No. of Loan's Made: | S22: Interest Rate: | T22: 0.015
B23: Mode of Payment: | I23: No. of Months to Pay: | J23: 12 | L23: Mode of Payment: | S23: No. of Months to Pay: | T23: 12
B24: Payment's Made | C24: Present Capital Loan | D24: Constant Payment Deducted to Capital Loan | E24: Interest Amount per Payment | F24: Amount to be Paid | G24: Paid Amount | H24: Date of Payment | I24: Receipt Number | J24: REMARKS | L24: Payment's Made | M24: Present Capital Loan | N24: Constant Payment Deducted to Capital Loan | O24: Interest Amount per Payment | P24: Amount to be Paid | Q24: Paid Amount | R24: Date of Payment | S24: Receipt Number | T24: REMARKS
B25: 1st Payment: | C25: =J20 -> 10000 | D25: =J20/J23 -> 833.33333 | E25: =(C25*0.015) -> 150 | F25: =SUM(D25:E25) -> 983.33333 | L25: 1st Payment: | M25: =T20 -> 10000 | N25: =T20/T23 -> 833.33333 | O25: =(M25*0.015) -> 150 | P25: =SUM(N25:O25) -> 983.33333
B26: 2nd Payment: | C26: 9163 | D26: 833 | E26: =(C26*0.015) -> 137.445 | F26: =SUM(D26:E26) -> 970.445 | L26: 2nd Payment: | M26: 9163 | N26: 833 | O26: =(M26*0.015) -> 137.445 | P26: =SUM(N26:O26) -> 970.445
B27: 3rd Payment: | C27: 8330 | D27: 833 | E27: =(C27*0.015) -> 124.95 | F27: =SUM(D27:E27) -> 957.95 | L27: 3rd Payment: | M27: 8330 | N27: 833 | O27: =(M27*0.015) -> 124.95 | P27: =SUM(N27:O27) -> 957.95
B28: 4th Payment: | C28: 7497 | D28: 833 | E28: =(C28*0.015) -> 112.455 | F28: =SUM(D28:E28) -> 945.455 | L28: 4th Payment: | M28: 7497 | N28: 833 | O28: =(M28*0.015) -> 112.455 | P28: =SUM(N28:O28) -> 945.455
B29: 5th Payment: | C29: 6664 | D29: 833 | E29: =(C29*0.015) -> 99.96 | F29: =SUM(D29:E29) -> 932.96 | L29: 5th Payment: | M29: 6664 | N29: 833 | O29: =(M29*0.015) -> 99.96 | P29: =SUM(N29:O29) -> 932.96
B30: 6th Payment: | C30: 5831 | D30: 833 | E30: =(C30*0.015) -> 87.465 | F30: =SUM(D30:E30) -> 920.465 | L30: 6th Payment: | M30: 5831 | N30: 833 | O30: =(M30*0.015) -> 87.465 | P30: =SUM(N30:O30) -> 920.465
B31: 7th Payment: | C31: 4998 | D31: 833 | E31: =(C31*0.015) -> 74.97 | F31: =SUM(D31:E31) -> 907.97 | L31: 7th Payment: | M31: 4998 | N31: 833 | O31: =(M31*0.015) -> 74.97 | P31: =SUM(N31:O31) -> 907.97
B32: 8th Payment: | C32: 4165 | D32: 833 | E32: =(C32*0.015) -> 62.475 | F32: =SUM(D32:E32) -> 895.475 | L32: 8th Payment: | M32: 4165 | N32: 833 | O32: =(M32*0.015) -> 62.475 | P32: =SUM(N32:O32) -> 895.475
B33: 9th Payment: | C33: 3332 | D33: 833 | E33: =(C33*0.015) -> 49.98 | F33: =SUM(D33:E33) -> 882.98 | L33: 9th Payment: | M33: 3332 | N33: 833 | O33: =(M33*0.015) -> 49.98 | P33: =SUM(N33:O33) -> 882.98
B34: 10th Payment: | C34: 2499 | D34: 833 | E34: =(C34*0.015) -> 37.485 | F34: =SUM(D34:E34) -> 870.485 | L34: 10th Payment: | M34: 2499 | N34: 833 | O34: =(M34*0.015) -> 37.485 | P34: =SUM(N34:O34) -> 870.485
B35: 11th Payment: | C35: 1666 | D35: 833 | E35: =(C35*0.015) -> 24.99 | F35: =SUM(D35:E35) -> 857.99 | L35: 11th Payment: | M35: 1666 | N35: 833 | O35: =(M35*0.015) -> 24.99 | P35: =SUM(N35:O35) -> 857.99
B36: 12th Payment: | C36: 833 | D36: 833 | E36: =(C36*0.015) -> 12.495 | F36: =SUM(D36:E36) -> 845.495 | J36: Fully Paid | L36: 12th Payment: | M36: 833 | N36: 833 | O36: =(M36*0.015) -> 12.495 | P36: =SUM(N36:O36) -> 845.495 | T36: Fully Paid
B39: Member's Name: | C39: Tangtang, Neddie | I39: Loan Amount: | J39: 10000 | L39: Member's Name: | M39: Tangtang, Neddie | S39: Loan Amount: | T39: 10000
B40: Membership Number: | I40: Date: | J40: 3/11/2024 | L40: Membership Number: | S40: Date: | T40: 3/11/2024
B41: No. of Loan's Made: | I41: Interest Rate: | J41: 0.015 | L41: No. of Loan's Made: | S41: Interest Rate: | T41: 0.015
B42: Mode of Payment: | I42: No. of Months to Pay: | J42: 12 | L42: Mode of Payment: | S42: No. of Months to Pay: | T42: 12
B43: Payment's Made | C43: Present Capital Loan | D43: Constant Payment Deducted to Capital Loan | E43: Interest Amount per Payment | F43: Amount to be Paid | G43: Paid Amount | H43: Date of Payment | I43: Receipt Number | J43: REMARKS | L43: Payment's Made | M43: Present Capital Loan | N43: Constant Payment Deducted to Capital Loan | O43: Interest Amount per Payment | P43: Amount to be Paid | Q43: Paid Amount | R43: Date of Payment | S43: Receipt Number | T43: REMARKS
B44: 1st Payment: | C44: =J39 -> 10000 | D44: =J39/J42 -> 833.33333 | E44: =(C44*0.015) -> 150 | F44: =SUM(D44:E44) -> 983.33333 | L44: 1st Payment: | M44: =T39 -> 10000 | N44: =T39/T42 -> 833.33333 | O44: =(M44*0.015) -> 150 | P44: =SUM(N44:O44) -> 983.33333
B45: 2nd Payment: | C45: 9163 | D45: 833 | E45: =(C45*0.015) -> 137.445 | F45: =SUM(D45:E45) -> 970.445 | L45: 2nd Payment: | M45: 9163 | N45: 833 | O45: =(M45*0.015) -> 137.445 | P45: =SUM(N45:O45) -> 970.445
B46: 3rd Payment: | C46: 8330 | D46: 833 | E46: =(C46*0.015) -> 124.95 | F46: =SUM(D46:E46) -> 957.95 | L46: 3rd Payment: | M46: 8330 | N46: 833 | O46: =(M46*0.015) -> 124.95 | P46: =SUM(N46:O46) -> 957.95
B47: 4th Payment: | C47: 7497 | D47: 833 | E47: =(C47*0.015) -> 112.455 | F47: =SUM(D47:E47) -> 945.455 | L47: 4th Payment: | M47: 7497 | N47: 833 | O47: =(M47*0.015) -> 112.455 | P47: =SUM(N47:O47) -> 945.455
B48: 5th Payment: | C48: 6664 | D48: 833 | E48: =(C48*0.015) -> 99.96 | F48: =SUM(D48:E48) -> 932.96 | L48: 5th Payment: | M48: 6664 | N48: 833 | O48: =(M48*0.015) -> 99.96 | P48: =SUM(N48:O48) -> 932.96
B49: 6th Payment: | C49: 5831 | D49: 833 | E49: =(C49*0.015) -> 87.465 | F49: =SUM(D49:E49) -> 920.465 | L49: 6th Payment: | M49: 5831 | N49: 833 | O49: =(M49*0.015) -> 87.465 | P49: =SUM(N49:O49) -> 920.465
B50: 7th Payment: | C50: 4998 | D50: 833 | E50: =(C50*0.015) -> 74.97 | F50: =SUM(D50:E50) -> 907.97 | L50: 7th Payment: | M50: 4998 | N50: 833 | O50: =(M50*0.015) -> 74.97 | P50: =SUM(N50:O50) -> 907.97
B51: 8th Payment: | C51: 4165 | D51: 833 | E51: =(C51*0.015) -> 62.475 | F51: =SUM(D51:E51) -> 895.475 | L51: 8th Payment: | M51: 4165 | N51: 833 | O51: =(M51*0.015) -> 62.475 | P51: =SUM(N51:O51) -> 895.475
B52: 9th Payment: | C52: 3332 | D52: 833 | E52: =(C52*0.015) -> 49.98 | F52: =SUM(D52:E52) -> 882.98 | L52: 9th Payment: | M52: 3332 | N52: 833 | O52: =(M52*0.015) -> 49.98 | P52: =SUM(N52:O52) -> 882.98
B53: 10th Payment: | C53: 2499 | D53: 833 | E53: =(C53*0.015) -> 37.485 | F53: =SUM(D53:E53) -> 870.485 | L53: 10th Payment: | M53: 2499 | N53: 833 | O53: =(M53*0.015) -> 37.485 | P53: =SUM(N53:O53) -> 870.485
B54: 11th Payment: | C54: 1666 | D54: 833 | E54: =(C54*0.015) -> 24.99 | F54: =SUM(D54:E54) -> 857.99 | L54: 11th Payment: | M54: 1666 | N54: 833 | O54: =(M54*0.015) -> 24.99 | P54: =SUM(N54:O54) -> 857.99
B55: 12th Payment: | C55: 833 | D55: 833 | E55: =(C55*0.015) -> 12.495 | F55: =SUM(D55:E55) -> 845.495 | J55: Fully Paid | L55: 12th Payment: | M55: 833 | N55: 833 | O55: =(M55*0.015) -> 12.495 | P55: =SUM(N55:O55) -> 845.495 | T55: Fully Paid
B58: Member's Name: | C58: Tamayo, Erlinda | H58: Loan Amount: | J58: 70000 | L58: Member's Name: | M58: Tamayo, Erlinda | S58: Loan Amount: | T58: 70000
B59: Membership Number: | I59: Date: | J59: 10/9/2024 | L59: Membership Number: | S59: Date: | T59: 10/9/2024
B60: No. of Loan's Made: | F60: Interest Rate: | J60: 0.015 | L60: No. of Loan's Made: | S60: Interest Rate: | T60: 0.015
B61: Mode of Payment: | E61: No. of Months to Pay: | J61: 12 | L61: Mode of Payment: | S61: No. of Months to Pay: | T61: 12
B62: Payment's Made | C62: Present Capital Loan | D62: Constant Payment Deducted to Capital Loan | E62: Interest Amount per Payment | F62: Amount to be Paid | G62: Paid Amount | H62: Date of Payment | I62: Receipt Number | J62: REMARKS | L62: Payment's Made | M62: Present Capital Loan | N62: Constant Payment Deducted to Capital Loan | O62: Interest Amount per Payment | P62: Amount to be Paid | Q62: Paid Amount | R62: Date of Payment | S62: Receipt Number | T62: REMARKS
B63: 1st Payment: | C63: =J58 -> 70000 | D63: =J58/J61 -> 5833.3333 | E63: =(C63*0.015) -> 1050 | F63: =SUM(D63:E63) -> 6883.3333 | L63: 1st Payment: | M63: =T58 -> 70000 | N63: =T58/T61 -> 5833.3333 | O63: =(M63*0.015) -> 1050 | P63: =SUM(N63:O63) -> 6883.3333
B64: 2nd Payment: | C64: 64163 | D64: 5833 | E64: =(C64*0.015) -> 962.445 | F64: =SUM(D64:E64) -> 6795.445 | L64: 2nd Payment: | M64: 64163 | N64: 5833 | O64: =(M64*0.015) -> 962.445 | P64: =SUM(N64:O64) -> 6795.445
B65: 3rd Payment: | C65: 58330 | D65: 5833 | E65: =(C65*0.015) -> 874.95 | F65: =SUM(D65:E65) -> 6707.95 | L65: 3rd Payment: | M65: 58330 | N65: 5833 | O65: =(M65*0.015) -> 874.95 | P65: =SUM(N65:O65) -> 6707.95
B66: 4th Payment: | C66: 52497 | D66: 5833 | E66: =(C66*0.015) -> 787.455 | F66: =SUM(D66:E66) -> 6620.455 | L66: 4th Payment: | M66: 52497 | N66: 5833 | O66: =(M66*0.015) -> 787.455 | P66: =SUM(N66:O66) -> 6620.455
B67: 5th Payment: | C67: 46664 | D67: 5833 | E67: =(C67*0.015) -> 699.96 | F67: =SUM(D67:E67) -> 6532.96 | L67: 5th Payment: | M67: 46664 | N67: 5833 | O67: =(M67*0.015) -> 699.96 | P67: =SUM(N67:O67) -> 6532.96
B68: 6th Payment: | C68: 40831 | D68: 5833 | E68: =(C68*0.015) -> 612.465 | F68: =SUM(D68:E68) -> 6445.465 | L68: 6th Payment: | M68: 40831 | N68: 5833 | O68: =(M68*0.015) -> 612.465 | P68: =SUM(N68:O68) -> 6445.465
B69: 7th Payment: | C69: 34998 | D69: 5833 | E69: =(C69*0.015) -> 524.97 | F69: =SUM(D69:E69) -> 6357.97 | L69: 7th Payment: | M69: 34998 | N69: 5833 | O69: =(M69*0.015) -> 524.97 | P69: =SUM(N69:O69) -> 6357.97
B70: 8th Payment: | C70: 29165 | D70: 5833 | E70: =(C70*0.015) -> 437.475 | F70: =SUM(D70:E70) -> 6270.475 | L70: 8th Payment: | M70: 29165 | N70: 5833 | O70: =(M70*0.015) -> 437.475 | P70: =SUM(N70:O70) -> 6270.475
B71: 9th Payment: | C71: 23332 | D71: 5833 | E71: =(C71*0.015) -> 349.98 | F71: =SUM(D71:E71) -> 6182.98 | L71: 9th Payment: | M71: 23332 | N71: 5833 | O71: =(M71*0.015) -> 349.98 | P71: =SUM(N71:O71) -> 6182.98
B72: 10th Payment: | C72: 17499 | D72: 5833 | E72: =(C72*0.015) -> 262.485 | F72: =SUM(D72:E72) -> 6095.485 | L72: 10th Payment: | M72: 17499 | N72: 5833 | O72: =(M72*0.015) -> 262.485 | P72: =SUM(N72:O72) -> 6095.485
B73: 11th Payment: | C73: 11666 | D73: 5833 | E73: =(C73*0.015) -> 174.99 | F73: =SUM(D73:E73) -> 6007.99 | L73: 11th Payment: | M73: 11666 | N73: 5833 | O73: =(M73*0.015) -> 174.99 | P73: =SUM(N73:O73) -> 6007.99
B74: 12th Payment: | C74: 5833 | D74: 5833 | E74: =(C74*0.015) -> 87.495 | F74: =SUM(D74:E74) -> 5920.495 | J74: Fully Paid | L74: 12th Payment: | M74: 5833 | N74: 5833 | O74: =(M74*0.015) -> 87.495 | P74: =SUM(N74:O74) -> 5920.495 | T74: Fully Paid
B76: Member's Name: | C76: Diwa, Janine | I76: Loan Amount: | J76: 10000 | L76: Member's Name: | M76: Diwa, Janine | S76: Loan Amount: | T76: 10000
B77: Membership Number: | I77: Date: | J77: 3/24/2025 | L77: Membership Number: | S77: Date: | T77: 3/24/2025
B78: No. of Loan's Made: | I78: Interest Rate: | J78: 0.015 | L78: No. of Loan's Made: | S78: Interest Rate: | T78: 0.015
B79: Mode of Payment: | I79: No. of Months to Pay: | J79: 12 | L79: Mode of Payment: | S79: No. of Months to Pay: | T79: 12
B80: Payment's Made | C80: Present Capital Loan | D80: Constant Payment Deducted to Capital Loan | E80: Interest Amount per Payment | F80: Amount to be Paid | G80: Paid Amount | H80: Date of Payment | I80: Receipt Number | J80: REMARKS | L80: Payment's Made | M80: Present Capital Loan | N80: Constant Payment Deducted to Capital Loan | O80: Interest Amount per Payment | P80: Amount to be Paid | Q80: Paid Amount | R80: Date of Payment | S80: Receipt Number | T80: REMARKS
B81: 1st Payment: | C81: =J76 -> 10000 | D81: =J76/J79 -> 833.33333 | E81: =(C81*0.015) -> 150 | F81: =SUM(D81:E81) -> 983.33333 | L81: 1st Payment: | M81: =T76 -> 10000 | N81: =T76/T79 -> 833.33333 | O81: =(M81*0.015) -> 150 | P81: =SUM(N81:O81) -> 983.33333
B82: 2nd Payment: | C82: 9163 | D82: 833 | E82: =(C82*0.015) -> 137.445 | F82: =SUM(D82:E82) -> 970.445 | L82: 2nd Payment: | M82: 9163 | N82: 833 | O82: =(M82*0.015) -> 137.445 | P82: =SUM(N82:O82) -> 970.445
B83: 3rd Payment: | C83: 8330 | D83: 833 | E83: =(C83*0.015) -> 124.95 | F83: =SUM(D83:E83) -> 957.95 | L83: 3rd Payment: | M83: 8330 | N83: 833 | O83: =(M83*0.015) -> 124.95 | P83: =SUM(N83:O83) -> 957.95
B84: 4th Payment: | C84: 7497 | D84: 833 | E84: =(C84*0.015) -> 112.455 | F84: =SUM(D84:E84) -> 945.455 | L84: 4th Payment: | M84: 7497 | N84: 833 | O84: =(M84*0.015) -> 112.455 | P84: =SUM(N84:O84) -> 945.455
B85: 5th Payment: | C85: 6664 | D85: 833 | E85: =(C85*0.015) -> 99.96 | F85: =SUM(D85:E85) -> 932.96 | L85: 5th Payment: | M85: 6664 | N85: 833 | O85: =(M85*0.015) -> 99.96 | P85: =SUM(N85:O85) -> 932.96
B86: 6th Payment: | C86: 5831 | D86: 833 | E86: =(C86*0.015) -> 87.465 | F86: =SUM(D86:E86) -> 920.465 | L86: 6th Payment: | M86: 5831 | N86: 833 | O86: =(M86*0.015) -> 87.465 | P86: =SUM(N86:O86) -> 920.465
B87: 7th Payment: | C87: 4998 | D87: 833 | E87: =(C87*0.015) -> 74.97 | F87: =SUM(D87:E87) -> 907.97 | L87: 7th Payment: | M87: 4998 | N87: 833 | O87: =(M87*0.015) -> 74.97 | P87: =SUM(N87:O87) -> 907.97
B88: 8th Payment: | C88: 4165 | D88: 833 | E88: =(C88*0.015) -> 62.475 | F88: =SUM(D88:E88) -> 895.475 | L88: 8th Payment: | M88: 4165 | N88: 833 | O88: =(M88*0.015) -> 62.475 | P88: =SUM(N88:O88) -> 895.475
B89: 9th Payment: | C89: 3332 | D89: 833 | E89: =(C89*0.015) -> 49.98 | F89: =SUM(D89:E89) -> 882.98 | L89: 9th Payment: | M89: 3332 | N89: 833 | O89: =(M89*0.015) -> 49.98 | P89: =SUM(N89:O89) -> 882.98
B90: 10th Payment: | C90: 2499 | D90: 833 | E90: =(C90*0.015) -> 37.485 | F90: =SUM(D90:E90) -> 870.485 | L90: 10th Payment: | M90: 2499 | N90: 833 | O90: =(M90*0.015) -> 37.485 | P90: =SUM(N90:O90) -> 870.485
B91: 11th Payment: | C91: 1666 | D91: 833 | E91: =(C91*0.015) -> 24.99 | F91: =SUM(D91:E91) -> 857.99 | L91: 11th Payment: | M91: 1666 | N91: 833 | O91: =(M91*0.015) -> 24.99 | P91: =SUM(N91:O91) -> 857.99
B92: 12th Payment: | C92: 833 | D92: 833 | E92: =(C92*0.015) -> 12.495 | F92: =SUM(D92:E92) -> 845.495 | J92: Fully Paid | L92: 12th Payment: | M92: 833 | N92: 833 | O92: =(M92*0.015) -> 12.495 | P92: =SUM(N92:O92) -> 845.495 | T92: Fully Paid
B95: Member's Name: | C95: Quintal, Melissa | I95: Loan Amount: | J95: 5000 | L95: Member's Name: | M95: Quintal, Melissa | S95: Loan Amount: | T95: 5000
B96: Membership Number: | I96: Date: | J96: 1/19/2024 | L96: Membership Number: | S96: Date: | T96: 1/19/2024
B97: No. of Loan's Made: | I97: Interest Rate: | J97: 0.015 | L97: No. of Loan's Made: | S97: Interest Rate: | T97: 0.015
B98: Mode of Payment: | I98: No. of Months to Pay: | J98: 12 | L98: Mode of Payment: | S98: No. of Months to Pay: | T98: 12
B99: Payment's Made | C99: Present Capital Loan | D99: Constant Payment Deducted to Capital Loan | E99: Interest Amount per Payment | F99: Amount to be Paid | G99: Paid Amount | H99: Date of Payment | I99: Receipt Number | J99: REMARKS | L99: Payment's Made | M99: Present Capital Loan | N99: Constant Payment Deducted to Capital Loan | O99: Interest Amount per Payment | P99: Amount to be Paid | Q99: Paid Amount | R99: Date of Payment | S99: Receipt Number | T99: REMARKS
B100: 1st Payment: | C100: =J95 -> 5000 | D100: =J95/J98 -> 416.66667 | E100: =(C100*0.015) -> 75 | F100: =SUM(D100:E100) -> 491.66667 | L100: 1st Payment: | M100: =T95 -> 5000 | N100: =T95/T98 -> 416.66667 | O100: =(M100*0.015) -> 75 | P100: =SUM(N100:O100) -> 491.66667
B101: 2nd Payment: | C101: 4587 | D101: 417 | E101: =(C101*0.015) -> 68.805 | F101: =SUM(D101:E101) -> 485.805 | L101: 2nd Payment: | M101: 4587 | N101: 417 | O101: =(M101*0.015) -> 68.805 | P101: =SUM(N101:O101) -> 485.805
B102: 3rd Payment: | C102: 4170 | D102: 417 | E102: =(C102*0.015) -> 62.55 | F102: =SUM(D102:E102) -> 479.55 | L102: 3rd Payment: | M102: 4170 | N102: 417 | O102: =(M102*0.015) -> 62.55 | P102: =SUM(N102:O102) -> 479.55
B103: 4th Payment: | C103: 3753 | D103: 417 | E103: =(C103*0.015) -> 56.295 | F103: =SUM(D103:E103) -> 473.295 | L103: 4th Payment: | M103: 3753 | N103: 417 | O103: =(M103*0.015) -> 56.295 | P103: =SUM(N103:O103) -> 473.295
B104: 5th Payment: | C104: 3336 | D104: 417 | E104: =(C104*0.015) -> 50.04 | F104: =SUM(D104:E104) -> 467.04 | L104: 5th Payment: | M104: 3336 | N104: 417 | O104: =(M104*0.015) -> 50.04 | P104: =SUM(N104:O104) -> 467.04
B105: 6th Payment: | C105: 2919 | D105: 417 | E105: =(C105*0.015) -> 43.785 | F105: =SUM(D105:E105) -> 460.785 | L105: 6th Payment: | M105: 2919 | N105: 417 | O105: =(M105*0.015) -> 43.785 | P105: =SUM(N105:O105) -> 460.785
B106: 7th Payment: | C106: 2502 | D106: 417 | E106: =(C106*0.015) -> 37.53 | F106: =SUM(D106:E106) -> 454.53 | L106: 7th Payment: | M106: 2502 | N106: 417 | O106: =(M106*0.015) -> 37.53 | P106: =SUM(N106:O106) -> 454.53
B107: 8th Payment: | C107: 2085 | D107: 417 | E107: =(C107*0.015) -> 31.275 | F107: =SUM(D107:E107) -> 448.275 | L107: 8th Payment: | M107: 2085 | N107: 417 | O107: =(M107*0.015) -> 31.275 | P107: =SUM(N107:O107) -> 448.275
B108: 9th Payment: | C108: 1668 | D108: 417 | E108: =(C108*0.015) -> 25.02 | F108: =SUM(D108:E108) -> 442.02 | L108: 9th Payment: | M108: 1668 | N108: 417 | O108: =(M108*0.015) -> 25.02 | P108: =SUM(N108:O108) -> 442.02
...

Sheet 24 mos
B1: Member's Name: | C1: Quintal, Melissa | I1: Loan Amount: | J1: 30000 | L1: Member's Name: | M1: Quintal, Melissa | S1: Loan Amount: | T1: 30000
B2: Membership Number: | I2: Date: | J2: 5/27/2025 | L2: Membership Number: | S2: Date: | T2: 5/27/2025
B3: No. of Loan's Made: | I3: Interest Rate: | J3: 0.015 | L3: No. of Loan's Made: | S3: Interest Rate: | T3: 0.015
B4: Mode of Payment: | I4: No. of Months to Pay: | J4: 24 | L4: Mode of Payment: | S4: No. of Months to Pay: | T4: 24
B5: Payment's Made | C5: Present Capital Loan | D5: Constant Payment Deducted to Capital Loan | E5: Interest Amount per Payment | F5: Amount to be Paid | G5: Paid Amount | H5: Date of Payment | I5: Receipt Number | J5: REMARKS | L5: Payment's Made | M5: Present Capital Loan | N5: Constant Payment Deducted to Capital Loan | O5: Interest Amount per Payment | P5: Amount to be Paid | Q5: Paid Amount | R5: Date of Payment | S5: Receipt Number | T5: REMARKS
B6: 1st Payment: | C6: =J1 -> 30000 | D6: =J1/J4 -> 1250 | E6: =(C6*0.015) -> 450 | F6: =SUM(D6:E6) -> 1700 | L6: 1st Payment: | M6: =T1 -> 30000 | N6: =T1/T4 -> 1250 | O6: =(M6*0.015) -> 450 | P6: =SUM(N6:O6) -> 1700
B7: 2nd Payment: | C7: 28750 | D7: 1250 | E7: =(C7*0.015) -> 431.25 | F7: =SUM(D7:E7) -> 1681.25 | L7: 2nd Payment: | M7: 28750 | N7: 1250 | O7: =(M7*0.015) -> 431.25 | P7: =SUM(N7:O7) -> 1681.25
B8: 3rd Payment: | C8: 27500 | D8: 1250 | E8: =(C8*0.015) -> 412.5 | F8: =SUM(D8:E8) -> 1662.5 | L8: 3rd Payment: | M8: 27500 | N8: 1250 | O8: =(M8*0.015) -> 412.5 | P8: =SUM(N8:O8) -> 1662.5
B9: 4th Payment: | C9: 26250 | D9: 1250 | E9: =(C9*0.015) -> 393.75 | F9: =SUM(D9:E9) -> 1643.75 | L9: 4th Payment: | M9: 26250 | N9: 1250 | O9: =(M9*0.015) -> 393.75 | P9: =SUM(N9:O9) -> 1643.75
B10: 5th Payment: | C10: 2500 | D10: 1250 | E10: =(C10*0.015) -> 37.5 | F10: =SUM(D10:E10) -> 1287.5 | L10: 5th Payment: | M10: 2500 | N10: 1250 | O10: =(M10*0.015) -> 37.5 | P10: =SUM(N10:O10) -> 1287.5
B11: 6th Payment: | C11: 23750 | D11: 1250 | E11: =(C11*0.015) -> 356.25 | F11: =SUM(D11:E11) -> 1606.25 | L11: 6th Payment: | M11: 23750 | N11: 1250 | O11: =(M11*0.015) -> 356.25 | P11: =SUM(N11:O11) -> 1606.25
B12: 7th Payment: | C12: 22500 | D12: 1250 | E12: =(C12*0.015) -> 337.5 | F12: =SUM(D12:E12) -> 1587.5 | L12: 7th Payment: | M12: 22500 | N12: 1250 | O12: =(M12*0.015) -> 337.5 | P12: =SUM(N12:O12) -> 1587.5
B13: 8th Payment: | C13: 21250 | D13: 1250 | E13: =(C13*0.015) -> 318.75 | F13: =SUM(D13:E13) -> 1568.75 | L13: 8th Payment: | M13: 21250 | N13: 1250 | O13: =(M13*0.015) -> 318.75 | P13: =SUM(N13:O13) -> 1568.75
B14: 9th Payment: | C14: 20000 | D14: 1250 | E14: =(C14*0.015) -> 300 | F14: =SUM(D14:E14) -> 1550 | L14: 9th Payment: | M14: 20000 | N14: 1250 | O14: =(M14*0.015) -> 300 | P14: =SUM(N14:O14) -> 1550
B15: 10th Payment: | C15: 18750 | D15: 1250 | E15: =(C15*0.015) -> 281.25 | F15: =SUM(D15:E15) -> 1531.25 | L15: 10th Payment: | M15: 18750 | N15: 1250 | O15: =(M15*0.015) -> 281.25 | P15: =SUM(N15:O15) -> 1531.25
B16: 11th Payment: | C16: 17500 | D16: 1250 | E16: =(C16*0.015) -> 262.5 | F16: =SUM(D16:E16) -> 1512.5 | L16: 11th Payment: | M16: 17500 | N16: 1250 | O16: =(M16*0.015) -> 262.5 | P16: =SUM(N16:O16) -> 1512.5
B17: 12th Payment: | C17: 16250 | D17: 1250 | E17: =(C17*0.015) -> 243.75 | F17: =SUM(D17:E17) -> 1493.75 | L17: 12th Payment: | M17: 16250 | N17: 1250 | O17: =(M17*0.015) -> 243.75 | P17: =SUM(N17:O17) -> 1493.75
B18: 13th Payment: | C18: 15000 | D18: 1250 | E18: =(C18*0.015) -> 225 | F18: =SUM(D18:E18) -> 1475 | L18: 13th Payment: | M18: 15000 | N18: 1250 | O18: =(M18*0.015) -> 225 | P18: =SUM(N18:O18) -> 1475
... B28: 23rd Payment: | C28: 2500 | D28: 1250 | E28: =(C28*0.015) -> 37.5 | F28: =SUM(D28:E28) -> 1287.5 | L28: 23rd Payment: | M28: 2500 | N28: 1250 | O28: =(M28*0.015) -> 37.5 | P28: =SUM(N28:O28) -> 1287.5
B29: 24th Payment: | C29: 1250 | D29: 1250 | E29: =(C29*0.015) -> 18.75 | F29: =SUM(D29:E29) -> 1268.75 | J29: Fully Paid | L29: 24th Payment: | M29: 1250 | N29: 1250 | O29: =(M29*0.015) -> 18.75 | P29: =SUM(N29:O29) -> 1268.75 | T29: Fully Paid
B32: Member's Name: | C32: Camero, Marilyn | I32: Loan Amount: | J32: 100000 | L32: Member's Name: | M32: Camero, Marilyn | S32: Loan Amount: | T32: 100000
B33: Membership Number: | I33: Date: | J33: 5/19/2025 | L33: Membership Number: | S33: Date: | T33: 5/19/2025
B34: No. of Loan's Made: | I34: Interest Rate: | J34: 0.015 | L34: No. of Loan's Made: | S34: Interest Rate: | T34: 0.015
B35: Mode of Payment: | I35: No. of Months to Pay: | J35: 24 | L35: Mode of Payment: | S35: No. of Months to Pay: | T35: 24
B36: Payment's Made | C36: Present Capital Loan | D36: Constant Payment Deducted to Capital Loan | E36: Interest Amount per Payment | F36: Amount to be Paid | G36: Paid Amount | H36: Date of Payment | I36: Receipt Number | J36: REMARKS | L36: Payment's Made | M36: Present Capital Loan | N36: Constant Payment Deducted to Capital Loan | O36: Interest Amount per Payment | P36: Amount to be Paid | Q36: Paid Amount | R36: Date of Payment | S36: Receipt Number | T36: REMARKS
B37: 1st Payment: | C37: =J32 -> 100000 | D37: =J32/J35 -> 4166.6667 | E37: =(C37*0.015) -> 1500 | F37: =SUM(D37:E37) -> 5666.6667 | L37: 1st Payment: | M37: =T32 -> 100000 | N37: =T32/T35 -> 4166.6667 | O37: =(M37*0.015) -> 1500 | P37: =SUM(N37:O37) -> 5666.6667
B38: 2nd Payment: | C38: 95841 | D38: 4167 | E38: =(C38*0.015) -> 1437.615 | F38: =SUM(D38:E38) -> 5604.615 | L38: 2nd Payment: | M38: 95841 | N38: 4167 | O38: =(M38*0.015) -> 1437.615 | P38: =SUM(N38:O38) -> 5604.615
B39: 3rd Payment: | C39: 91674 | D39: 4167 | E39: =(C39*0.015) -> 1375.11 | F39: =SUM(D39:E39) -> 5542.11 | L39: 3rd Payment: | M39: 91674 | N39: 4167 | O39: =(M39*0.015) -> 1375.11 | P39: =SUM(N39:O39) -> 5542.11
B40: 4th Payment: | C40: 87507 | D40: 4167 | E40: =(C40*0.015) -> 1312.605 | F40: =SUM(D40:E40) -> 5479.605 | L40: 4th Payment: | M40: 87507 | N40: 4167 | O40: =(M40*0.015) -> 1312.605 | P40: =SUM(N40:O40) -> 5479.605
B41: 5th Payment: | C41: 83340 | D41: 4167 | E41: =(C41*0.015) -> 1250.1 | F41: =SUM(D41:E41) -> 5417.1 | L41: 5th Payment: | M41: 83340 | N41: 4167 | O41: =(M41*0.015) -> 1250.1 | P41: =SUM(N41:O41) -> 5417.1
B42: 6th Payment: | C42: 79173 | D42: 4167 | E42: =(C42*0.015) -> 1187.595 | F42: =SUM(D42:E42) -> 5354.595 | L42: 6th Payment: | M42: 79173 | N42: 4167 | O42: =(M42*0.015) -> 1187.595 | P42: =SUM(N42:O42) -> 5354.595
B43: 7th Payment: | C43: 75006 | D43: 4167 | E43: =(C43*0.015) -> 1125.09 | F43: =SUM(D43:E43) -> 5292.09 | L43: 7th Payment: | M43: 75006 | N43: 4167 | O43: =(M43*0.015) -> 1125.09 | P43: =SUM(N43:O43) -> 5292.09
B44: 8th Payment: | C44: 70839 | D44: 4167 | E44: =(C44*0.015) -> 1062.585 | F44: =SUM(D44:E44) -> 5229.585 | L44: 8th Payment: | M44: 70839 | N44: 4167 | O44: =(M44*0.015) -> 1062.585 | P44: =SUM(N44:O44) -> 5229.585
B45: 9th Payment: | C45: 66672 | D45: 4167 | E45: =(C45*0.015) -> 1000.08 | F45: =SUM(D45:E45) -> 5167.08 | L45: 9th Payment: | M45: 66672 | N45: 4167 | O45: =(M45*0.015) -> 1000.08 | P45: =SUM(N45:O45) -> 5167.08
B46: 10th Payment: | C46: 62505 | D46: 4167 | E46: =(C46*0.015) -> 937.575 | F46: =SUM(D46:E46) -> 5104.575 | L46: 10th Payment: | M46: 62505 | N46: 4167 | O46: =(M46*0.015) -> 937.575 | P46: =SUM(N46:O46) -> 5104.575
B47: 11th Payment: | C47: 58338 | D47: 4167 | E47: =(C47*0.015) -> 875.07 | F47: =SUM(D47:E47) -> 5042.07 | L47: 11th Payment: | M47: 58338 | N47: 4167 | O47: =(M47*0.015) -> 875.07 | P47: =SUM(N47:O47) -> 5042.07
B48: 12th Payment: | C48: 54171 | D48: 4167 | E48: =(C48*0.015) -> 812.565 | F48: =SUM(D48:E48) -> 4979.565 | L48: 12th Payment: | M48: 54171 | N48: 4167 | O48: =(M48*0.015) -> 812.565 | P48: =SUM(N48:O48) -> 4979.565
B49: 13th Payment: | C49: 50004 | D49: 4167 | E49: =(C49*0.015) -> 750.06 | F49: =SUM(D49:E49) -> 4917.06 | L49: 13th Payment: | M49: 50004 | N49: 4167 | O49: =(M49*0.015) -> 750.06 | P49: =SUM(N49:O49) -> 4917.06
... B59: 23rd Payment: | C59: 8334 | D59: 4167 | E59: =(C59*0.015) -> 125.01 | F59: =SUM(D59:E59) -> 4292.01 | L59: 23rd Payment: | M59: 8334 | N59: 4167 | O59: =(M59*0.015) -> 125.01 | P59: =SUM(N59:O59) -> 4292.01
B60: 24th Payment: | C60: 4167 | D60: 4167 | E60: =(C60*0.015) -> 62.505 | F60: =SUM(D60:E60) -> 4229.505 | J60: Fully Paid | L60: 24th Payment: | M60: 4167 | N60: 4167 | O60: =(M60*0.015) -> 62.505 | P60: =SUM(N60:O60) -> 4229.505 | T60: Fully Paid
B62: Member's Name: | C62: Aguilar, Alma | I62: Loan Amount: | J62: 35000
B63: Membership Number: | I63: Date:
B64: No. of Loan's Made: | I64: Interest Rate: | J64: 0.015
B65: Mode of Payment: | I65: No. of Months to Pay: | J65: 24
B66: Payment's Made | C66: Present Capital Loan | D66: Constant Payment Deducted to Capital Loan | E66: Interest Amount per Payment | F66: Amount to be Paid | G66: Paid Amount | H66: Date of Payment | I66: Receipt Number | J66: REMARKS
B67: 1st Payment: | C67: =J62 -> 35000 | D67: =J62/J65 -> 1458.3333 | E67: =(C67*0.015) -> 525 | F67: =SUM(D67:E67) -> 1983.3333 | G67: 2700
B68: 2nd Payment: | C68: 33354 | D68: 1458 | E68: =(C68*0.015) -> 500.31 | F68: =SUM(D68:E68) -> 1958.31 | G68: 2700
B69: 3rd Payment: | C69: 32076 | D69: 1458 | E69: =(C69*0.015) -> 481.14 | F69: =SUM(D69:E69) -> 1939.14 | G69: 3000
B70: 4th Payment: | C70: 30618 | D70: 1458 | E70: =(C70*0.015) -> 459.27 | F70: =SUM(D70:E70) -> 1917.27 | G70: 3100
B71: 5th Payment: | C71: 29160 | D71: 1458 | E71: =(C71*0.015) -> 437.4 | F71: =SUM(D71:E71) -> 1895.4 | G71: 3000
B72: 6th Payment: | C72: 27702 | D72: 1458 | E72: =(C72*0.015) -> 415.53 | F72: =SUM(D72:E72) -> 1873.53 | G72: 4600
B73: 7th Payment: | C73: 26244 | D73: 1458 | E73: =(C73*0.015) -> 393.66 | F73: =SUM(D73:E73) -> 1851.66
B74: 8th Payment: | C74: 24786 | D74: 1458 | E74: =(C74*0.015) -> 371.79 | F74: =SUM(D74:E74) -> 1829.79
B75: 9th Payment: | C75: 23328 | D75: 1458 | E75: =(C75*0.015) -> 349.92 | F75: =SUM(D75:E75) -> 1807.92
B76: 10th Payment: | C76: 21870 | D76: 1458 | E76: =(C76*0.015) -> 328.05 | F76: =SUM(D76:E76) -> 1786.05
B77: 11th Payment: | C77: 20412 | D77: 1458 | E77: =(C77*0.015) -> 306.18 | F77: =SUM(D77:E77) -> 1764.18
B78: 12th Payment: | C78: 18954 | D78: 1458 | E78: =(C78*0.015) -> 284.31 | F78: =SUM(D78:E78) -> 1742.31
B79: 13th Payment: | C79: 17496 | D79: 1458 | E79: =(C79*0.015) -> 262.44 | F79: =SUM(D79:E79) -> 1720.44
B80: 14th Payment: | C80: 16038 | D80: 1458 | E80: =(C80*0.015) -> 240.57 | F80: =SUM(D80:E80) -> 1698.57
B81: 15th Payment: | C81: 14580 | D81: 1458 | E81: =(C81*0.015) -> 218.7 | F81: =SUM(D81:E81) -> 1676.7
B82: 16th Payment: | C82: 13122 | D82: 1458 | E82: =(C82*0.015) -> 196.83 | F82: =SUM(D82:E82) -> 1654.83
B83: 17th Payment: | C83: 11664 | D83: 1458 | E83: =(C83*0.015) -> 174.96 | F83: =SUM(D83:E83) -> 1632.96
B84: 18th Payment: | C84: 10206 | D84: 1458 | E84: =(C84*0.015) -> 153.09 | F84: =SUM(D84:E84) -> 1611.09
... B89: 23rd Payment: | C89: 2916 | D89: 1458 | E89: =(C89*0.015) -> 43.74 | F89: =SUM(D89:E89) -> 1501.74
B90: 24th Payment: | C90: 1458 | D90: 1458 | E90: =(C90*0.015) -> 21.87 | F90: =SUM(D90:E90) -> 1479.87 | J90: Fully Paid
D91: =SUM(D67:D90) -> 34992.333 | E91: =SUM(E67:E90) -> 6558.42
B93: Member's Name: | C93: Aguilar, Alma | I93: Loan Amount: | J93: 45000
B94: Membership Number: | I94: Date: | J94: .
B95: No. of Loan's Made: | I95: Interest Rate: | J95: 0.015
B96: Mode of Payment: | I96: No. of Months to Pay: | J96: 24
B97: Payment's Made | C97: Present Capital Loan | D97: Constant Payment Deducted to Capital Loan | E97: Interest Amount per Payment | F97: Amount to be Paid | G97: Paid Amount | H97: Date of Payment | I97: Receipt Number | J97: REMARKS
B98: 1st Payment: | C98: =J93 -> 45000 | D98: =J93/J96 -> 1875 | E98: =(C98*0.015) -> 675 | F98: =SUM(D98:E98) -> 2550 | G98: 3000
B99: 2nd Payment: | C99: 43125 | D99: 1875 | E99: =(C99*0.015) -> 646.875 | F99: =SUM(D99:E99) -> 2521.875 | G99: 5000
B100: 3rd Payment: | C100: 41250 | D100: 1875 | E100: =(C100*0.015) -> 618.75 | F100: =SUM(D100:E100) -> 2493.75 | G100: 3100
B101: 4th Payment: | C101: 39375 | D101: 1875 | E101: =(C101*0.015) -> 590.625 | F101: =SUM(D101:E101) -> 2465.625 | G101: 5000
B102: 5th Payment: | C102: 37500 | D102: 1875 | E102: =(C102*0.015) -> 562.5 | F102: =SUM(D102:E102) -> 2437.5 | G102: 3000
B103: 6th Payment: | C103: 35625 | D103: 1875 | E103: =(C103*0.015) -> 534.375 | F103: =SUM(D103:E103) -> 2409.375 | G103: 4600
B104: 7th Payment: | C104: 33750 | D104: 1875 | E104: =(C104*0.015) -> 506.25 | F104: =SUM(D104:E104) -> 2381.25 | G104: 1600
B105: 8th Payment: | C105: 31875 | D105: 1875 | E105: =(C105*0.015) -> 478.125 | F105: =SUM(D105:E105) -> 2353.125 | G105: 1900
B106: 9th Payment: | C106: 30000 | D106: 1875 | E106: =(C106*0.015) -> 450 | F106: =SUM(D106:E106) -> 2325 | G106: 2000
B107: 10th Payment: | C107: 28125 | D107: 1875 | E107: =(C107*0.015) -> 421.875 | F107: =SUM(D107:E107) -> 2296.875 | G107: 2000
B108: 11th Payment: | C108: 26250 | D108: 1875 | E108: =(C108*0.015) -> 393.75 | F108: =SUM(D108:E108) -> 2268.75 | G108: 5000
B109: 12th Payment: | C109: 24375 | D109: 1875 | E109: =(C109*0.015) -> 365.625 | F109: =SUM(D109:E109) -> 2240.625
B110: 13th Payment: | C110: 22500 | D110: 1875 | E110: =(C110*0.015) -> 337.5 | F110: =SUM(D110:E110) -> 2212.5
B111: 14th Payment: | C111: 20625 | D111: 1875 | E111: =(C111*0.015) -> 309.375 | F111: =SUM(D111:E111) -> 2184.375
B112: 15th Payment: | C112: 18750 | D112: 1875 | E112: =(C112*0.015) -> 281.25 | F112: =SUM(D112:E112) -> 2156.25
B113: 16th Payment: | C113: 16875 | D113: 1875 | E113: =(C113*0.015) -> 253.125 | F113: =SUM(D113:E113) -> 2128.125
B114: 17th Payment: | C114: 15000 | D114: 1875 | E114: =(C114*0.015) -> 225 | F114: =SUM(D114:E114) -> 2100
B115: 18th Payment: | C115: 13125 | D115: 1875 | E115: =(C115*0.015) -> 196.875 | F115: =SUM(D115:E115) -> 2071.875
B116: 19th Payment: | C116: 11250 | D116: 1875 | E116: =(C116*0.015) -> 168.75 | F116: =SUM(D116:E116) -> 2043.75
B117: 20th Payment: | C117: 9375 | D117: 1875 | E117: =(C117*0.015) -> 140.625 | F117: =SUM(D117:E117) -> 2015.625
B118: 21st Payment: | C118: 7500 | D118: 1875 | E118: =(C118*0.015) -> 112.5 | F118: =SUM(D118:E118) -> 1987.5
B119: 22nd Payment: | C119: 5625 | D119: 1875 | E119: =(C119*0.015) -> 84.375 | F119: =SUM(D119:E119) -> 1959.375
B120: 23rd Payment: | C120: 3750 | D120: 1875 | E120: =(C120*0.015) -> 56.25 | F120: =SUM(D120:E120) -> 1931.25
B121: 24th Payment: | C121: 1875 | D121: 1875 | E121: =(C121*0.015) -> 28.125 | F121: =SUM(D121:E121) -> 1903.125 | J121: Fully Paid
D122: =SUM(D98:D121) -> 45000 | E122: =SUM(E98:E121) -> 8437.5 | F122: =SUM(F98:F121) -> 53437.5 | G122: =SUM(G98:G121) -> 36200
B126: Member's Name: | C126: Moyo, Princess Warlin | H126: Loan Amount: | J126: 20000 | L126: Member's Name: | M126: Moyo, Princess Warlin | R126: Loan Amount: | T126: 20000
B127: Membership Number: | I127: Date: | J127: 1/8/2024 | L127: Membership Number: | S127: Date: | T127: 1/8/2024
B128: No. of Loan's Made: | F128: Interest Rate: | J128: 0.015 | L128: No. of Loan's Made: | P128: Interest Rate: | T128: 0.015
B129: Mode of Payment: | E129: No. of Months to Pay: | J129: 24 | L129: Mode of Payment: | O129: No. of Months to Pay: | T129: 24
...

Sheet 36 mos
B1: Member's Name: | C1: Boctot, Maria Rina | I1: Loan Amount: | J1: 60000 | L1: Member's Name: | M1: Boctot, Maria Rina | S1: Loan Amount: | T1: 60000
B2: Membership Number: | I2: Date: | J2: 1/3/2025 | L2: Membership Number: | S2: Date: | T2: 1/3/2025
B3: No. of Loan's Made: | I3: Interest Rate: | J3: 0.015 | L3: No. of Loan's Made: | S3: Interest Rate: | T3: 0.015
B4: Mode of Payment: | I4: No. of Months to Pay: | J4: 36 | L4: Mode of Payment: | S4: No. of Months to Pay: | T4: 36
B5: Payment's Made | C5: Present Capital Loan | D5: Constant Payment Deducted to Capital Loan | E5: Interest Amount per Payment | F5: Amount to be Paid | G5: Paid Amount | H5: Date of Payment | I5: Receipt Number | J5: REMARKS | L5: Payment's Made | M5: Present Capital Loan | N5: Constant Payment Deducted to Capital Loan | O5: Interest Amount per Payment | P5: Amount to be Paid | Q5: Paid Amount | R5: Date of Payment | S5: Receipt Number | T5: REMARKS
B6: 1st Payment: | C6: =J1 -> 60000 | D6: =J1/J4 -> 1666.6667 | E6: =(C6*0.015) -> 900 | F6: =SUM(D6:E6) -> 2566.6667 | L6: 1st Payment: | M6: =T1 -> 60000 | N6: =T1/T4 -> 1666.6667 | O6: =(M6*0.015) -> 900 | P6: =SUM(N6:O6) -> 2566.6667
B7: 2nd Payment: | C7: 58345 | D7: 1667 | E7: =(C7*0.015) -> 875.175 | F7: =SUM(D7:E7) -> 2542.175 | L7: 2nd Payment: | M7: 58345 | N7: 1667 | O7: =(M7*0.015) -> 875.175 | P7: =SUM(N7:O7) -> 2542.175
B8: 3rd Payment: | C8: 56678 | D8: 1667 | E8: =(C8*0.015) -> 850.17 | F8: =SUM(D8:E8) -> 2517.17 | L8: 3rd Payment: | M8: 56678 | N8: 1667 | O8: =(M8*0.015) -> 850.17 | P8: =SUM(N8:O8) -> 2517.17
B9: 4th Payment: | C9: 55011 | D9: 1667 | E9: =(C9*0.015) -> 825.165 | F9: =SUM(D9:E9) -> 2492.165 | L9: 4th Payment: | M9: 55011 | N9: 1667 | O9: =(M9*0.015) -> 825.165 | P9: =SUM(N9:O9) -> 2492.165
B10: 5th Payment: | C10: 53344 | D10: 1667 | E10: =(C10*0.015) -> 800.16 | F10: =SUM(D10:E10) -> 2467.16 | L10: 5th Payment: | M10: 53344 | N10: 1667 | O10: =(M10*0.015) -> 800.16 | P10: =SUM(N10:O10) -> 2467.16
B11: 6th Payment: | C11: 51677 | D11: 1667 | E11: =(C11*0.015) -> 775.155 | F11: =SUM(D11:E11) -> 2442.155 | L11: 6th Payment: | M11: 51677 | N11: 1667 | O11: =(M11*0.015) -> 775.155 | P11: =SUM(N11:O11) -> 2442.155
B12: 7th Payment: | C12: 50010 | D12: 1667 | E12: =(C12*0.015) -> 750.15 | F12: =SUM(D12:E12) -> 2417.15 | L12: 7th Payment: | M12: 50010 | N12: 1667 | O12: =(M12*0.015) -> 750.15 | P12: =SUM(N12:O12) -> 2417.15
B13: 8th Payment: | C13: 48343 | D13: 1667 | E13: =(C13*0.015) -> 725.145 | F13: =SUM(D13:E13) -> 2392.145 | L13: 8th Payment: | M13: 48343 | N13: 1667 | O13: =(M13*0.015) -> 725.145 | P13: =SUM(N13:O13) -> 2392.145
B14: 9th Payment: | C14: 46676 | D14: 1667 | E14: =(C14*0.015) -> 700.14 | F14: =SUM(D14:E14) -> 2367.14 | L14: 9th Payment: | M14: 46676 | N14: 1667 | O14: =(M14*0.015) -> 700.14 | P14: =SUM(N14:O14) -> 2367.14
B15: 10th Payment: | C15: 45009 | D15: 1667 | E15: =(C15*0.015) -> 675.135 | F15: =SUM(D15:E15) -> 2342.135 | L15: 10th Payment: | M15: 45009 | N15: 1667 | O15: =(M15*0.015) -> 675.135 | P15: =SUM(N15:O15) -> 2342.135
B16: 11th Payment: | C16: 43342 | D16: 1667 | E16: =(C16*0.015) -> 650.13 | F16: =SUM(D16:E16) -> 2317.13 | L16: 11th Payment: | M16: 43342 | N16: 1667 | O16: =(M16*0.015) -> 650.13 | P16: =SUM(N16:O16) -> 2317.13
B17: 12th Payment: | C17: 41675 | D17: 1667 | E17: =(C17*0.015) -> 625.125 | F17: =SUM(D17:E17) -> 2292.125 | L17: 12th Payment: | M17: 41675 | N17: 1667 | O17: =(M17*0.015) -> 625.125 | P17: =SUM(N17:O17) -> 2292.125
B18: 13th Payment: | C18: 40008 | D18: 1667 | E18: =(C18*0.015) -> 600.12 | F18: =SUM(D18:E18) -> 2267.12 | L18: 13th Payment: | M18: 40008 | N18: 1667 | O18: =(M18*0.015) -> 600.12 | P18: =SUM(N18:O18) -> 2267.12
... B29: 24th Payment: | C29: 21671 | D29: 1667 | E29: =(C29*0.015) -> 325.065 | F29: =SUM(D29:E29) -> 1992.065 | L29: 24th Payment: | M29: 21671 | N29: 1667 | O29: =(M29*0.015) -> 325.065 | P29: =SUM(N29:O29) -> 1992.065
F30: =SUM(F6:F29) -> 54710.427 | P30: =SUM(P6:P29) -> 54710.427
B35: 25th Payment: | C35: 20004 | D35: 1667 | E35: =(C35*0.015) -> 300.06 | F35: =SUM(D35:E35) -> 1967.06 | L35: 25th Payment: | M35: 20004 | N35: 1667 | O35: =(M35*0.015) -> 300.06 | P35: =SUM(N35:O35) -> 1967.06
B36: 26th Payment: | C36: 18337 | D36: 1667 | E36: =(C36*0.015) -> 275.055 | F36: =SUM(D36:E36) -> 1942.055 | L36: 26th Payment: | M36: 18337 | N36: 1667 | O36: =(M36*0.015) -> 275.055 | P36: =SUM(N36:O36) -> 1942.055
B37: 27th Payment: | C37: 16670 | D37: 1667 | E37: =(C37*0.015) -> 250.05 | F37: =SUM(D37:E37) -> 1917.05 | L37: 27th Payment: | M37: 16670 | N37: 1667 | O37: =(M37*0.015) -> 250.05 | P37: =SUM(N37:O37) -> 1917.05
B38: 28th Payment: | C38: 15003 | D38: 1667 | E38: =(C38*0.015) -> 225.045 | F38: =SUM(D38:E38) -> 1892.045 | L38: 28th Payment: | M38: 15003 | N38: 1667 | O38: =(M38*0.015) -> 225.045 | P38: =SUM(N38:O38) -> 1892.045
B39: 29th Payment: | C39: 13336 | D39: 1667 | E39: =(C39*0.015) -> 200.04 | F39: =SUM(D39:E39) -> 1867.04 | L39: 29th Payment: | M39: 13336 | N39: 1667 | O39: =(M39*0.015) -> 200.04 | P39: =SUM(N39:O39) -> 1867.04
B40: 30th Payment: | C40: 11669 | D40: 1667 | E40: =(C40*0.015) -> 175.035 | F40: =SUM(D40:E40) -> 1842.035 | L40: 30th Payment: | M40: 11669 | N40: 1667 | O40: =(M40*0.015) -> 175.035 | P40: =SUM(N40:O40) -> 1842.035
B41: 31st Payment: | C41: 10002 | D41: 1667 | E41: =(C41*0.015) -> 150.03 | F41: =SUM(D41:E41) -> 1817.03 | L41: 31st Payment: | M41: 10002 | N41: 1667 | O41: =(M41*0.015) -> 150.03 | P41: =SUM(N41:O41) -> 1817.03
B42: 32nd Payment: | C42: 8335 | D42: 1667 | E42: =(C42*0.015) -> 125.025 | F42: =SUM(D42:E42) -> 1792.025 | L42: 32nd Payment: | M42: 8335 | N42: 1667 | O42: =(M42*0.015) -> 125.025 | P42: =SUM(N42:O42) -> 1792.025
B43: 33rd Payment: | C43: 6668 | D43: 1667 | E43: =(C43*0.015) -> 100.02 | F43: =SUM(D43:E43) -> 1767.02 | L43: 33rd Payment: | M43: 6668 | N43: 1667 | O43: =(M43*0.015) -> 100.02 | P43: =SUM(N43:O43) -> 1767.02
B44: 34th Payment: | C44: 5001 | D44: 1667 | E44: =(C44*0.015) -> 75.015 | F44: =SUM(D44:E44) -> 1742.015 | L44: 34th Payment: | M44: 5001 | N44: 1667 | O44: =(M44*0.015) -> 75.015 | P44: =SUM(N44:O44) -> 1742.015
B45: 35th Payment: | C45: 3334 | D45: 1667 | E45: =(C45*0.015) -> 50.01 | F45: =SUM(D45:E45) -> 1717.01 | L45: 35th Payment: | M45: 3334 | N45: 1667 | O45: =(M45*0.015) -> 50.01 | P45: =SUM(N45:O45) -> 1717.01
B46: 36th Payment: | C46: 1667 | D46: 1667 | E46: =(C46*0.015) -> 25.005 | F46: =SUM(D46:E46) -> 1692.005 | J46: Fully Paid | L46: 36th Payment: | M46: 1667 | N46: 1667 | O46: =(M46*0.015) -> 25.005 | P46: =SUM(N46:O46) -> 1692.005 | T46: Fully Paid
E47: =SUM(E6:E46) -> 16653.15
B49: Member's Name: | C49: Salmorin, Arlene | I49: Loan Amount: | J49: 100000 | L49: Member's Name: | M49: Salmorin, Arlene | S49: Loan Amount: | T49: 100000
B50: Membership Number: | I50: Date: | J50: 4/8/2025 | L50: Membership Number: | S50: Date: | T50: 4/8/2025
B51: No. of Loan's Made: | I51: Interest Rate: | J51: 0.015 | L51: No. of Loan's Made: | S51: Interest Rate: | T51: 0.015
B52: Mode of Payment: | I52: No. of Months to Pay: | J52: 36 | L52: Mode of Payment: | S52: No. of Months to Pay: | T52: 36
B53: Payment's Made | C53: Present Capital Loan | D53: Constant Payment Deducted to Capital Loan | E53: Interest Amount per Payment | F53: Amount to be Paid | G53: Paid Amount | H53: Date of Payment | I53: Receipt Number | J53: REMARKS | L53: Payment's Made | M53: Present Capital Loan | N53: Constant Payment Deducted to Capital Loan | O53: Interest Amount per Payment | P53: Amount to be Paid | Q53: Paid Amount | R53: Date of Payment | S53: Receipt Number | T53: REMARKS
B54: 1st Payment: | C54: =J49 -> 100000 | D54: =J49/J52 -> 2777.7778 | E54: =(C54*0.015) -> 1500 | F54: =SUM(D54:E54) -> 4277.7778 | L54: 1st Payment: | M54: =T49 -> 100000 | N54: =T49/T52 -> 2777.7778 | O54: =(M54*0.015) -> 1500 | P54: =SUM(N54:O54) -> 4277.7778
B55: 2nd Payment: | C55: 97230 | D55: 2778 | E55: =(C55*0.015) -> 1458.45 | F55: =SUM(D55:E55) -> 4236.45 | L55: 2nd Payment: | M55: 97230 | N55: 2778 | O55: =(M55*0.015) -> 1458.45 | P55: =SUM(N55:O55) -> 4236.45
B56: 3rd Payment: | C56: 94452 | D56: 2778 | E56: =(C56*0.015) -> 1416.78 | F56: =SUM(D56:E56) -> 4194.78 | L56: 3rd Payment: | M56: 94452 | N56: 2778 | O56: =(M56*0.015) -> 1416.78 | P56: =SUM(N56:O56) -> 4194.78
B57: 4th Payment: | C57: 91674 | D57: 2778 | E57: =(C57*0.015) -> 1375.11 | F57: =SUM(D57:E57) -> 4153.11 | L57: 4th Payment: | M57: 91674 | N57: 2778 | O57: =(M57*0.015) -> 1375.11 | P57: =SUM(N57:O57) -> 4153.11
B58: 5th Payment: | C58: 88896 | D58: 2778 | E58: =(C58*0.015) -> 1333.44 | F58: =SUM(D58:E58) -> 4111.44 | L58: 5th Payment: | M58: 88896 | N58: 2778 | O58: =(M58*0.015) -> 1333.44 | P58: =SUM(N58:O58) -> 4111.44
B59: 6th Payment: | C59: 86118 | D59: 2778 | E59: =(C59*0.015) -> 1291.77 | F59: =SUM(D59:E59) -> 4069.77 | L59: 6th Payment: | M59: 86118 | N59: 2778 | O59: =(M59*0.015) -> 1291.77 | P59: =SUM(N59:O59) -> 4069.77
B60: 7th Payment: | C60: 83340 | D60: 2778 | E60: =(C60*0.015) -> 1250.1 | F60: =SUM(D60:E60) -> 4028.1 | L60: 7th Payment: | M60: 83340 | N60: 2778 | O60: =(M60*0.015) -> 1250.1 | P60: =SUM(N60:O60) -> 4028.1
B61: 8th Payment: | C61: 80562 | D61: 2778 | E61: =(C61*0.015) -> 1208.43 | F61: =SUM(D61:E61) -> 3986.43 | L61: 8th Payment: | M61: 80562 | N61: 2778 | O61: =(M61*0.015) -> 1208.43 | P61: =SUM(N61:O61) -> 3986.43
B62: 9th Payment: | C62: 77784 | D62: 2778 | E62: =(C62*0.015) -> 1166.76 | F62: =SUM(D62:E62) -> 3944.76 | L62: 9th Payment: | M62: 77784 | N62: 2778 | O62: =(M62*0.015) -> 1166.76 | P62: =SUM(N62:O62) -> 3944.76
B63: 10th Payment: | C63: 75006 | D63: 2778 | E63: =(C63*0.015) -> 1125.09 | F63: =SUM(D63:E63) -> 3903.09 | L63: 10th Payment: | M63: 75006 | N63: 2778 | O63: =(M63*0.015) -> 1125.09 | P63: =SUM(N63:O63) -> 3903.09
B64: 11th Payment: | C64: 72228 | D64: 2778 | E64: =(C64*0.015) -> 1083.42 | F64: =SUM(D64:E64) -> 3861.42 | L64: 11th Payment: | M64: 72228 | N64: 2778 | O64: =(M64*0.015) -> 1083.42 | P64: =SUM(N64:O64) -> 3861.42
B65: 12th Payment: | C65: 69450 | D65: 2778 | E65: =(C65*0.015) -> 1041.75 | F65: =SUM(D65:E65) -> 3819.75 | L65: 12th Payment: | M65: 69450 | N65: 2778 | O65: =(M65*0.015) -> 1041.75 | P65: =SUM(N65:O65) -> 3819.75
B66: 13th Payment: | C66: 66672 | D66: 2778 | E66: =(C66*0.015) -> 1000.08 | F66: =SUM(D66:E66) -> 3778.08 | L66: 13th Payment: | M66: 66672 | N66: 2778 | O66: =(M66*0.015) -> 1000.08 | P66: =SUM(N66:O66) -> 3778.08
... B95: 35th Payment: | C95: 5556 | D95: 2778 | E95: =(C95*0.015) -> 83.34 | F95: =SUM(D95:E95) -> 2861.34 | L95: 35th Payment: | M95: 5556 | N95: 2778 | O95: =(M95*0.015) -> 83.34 | P95: =SUM(N95:O95) -> 2861.34
B96: 36th Payment: | C96: 2778 | D96: 2778 | E96: =(C96*0.015) -> 41.67 | F96: =SUM(D96:E96) -> 2819.67 | J96: Fully Paid | L96: 36th Payment: | M96: 2778 | N96: 2778 | O96: =(M96*0.015) -> 41.67 | P96: =SUM(N96:O96) -> 2819.67 | T96: Fully Paid
B100: Member's Name: | C100: Gautani, Ver Louie | I100: Loan Amount: | J100: 40000
B101: Membership Number: | I101: Date:
B102: No. of Loan's Made: | I102: Interest Rate: | J102: 0.015
B103: Mode of Payment: | I103: No. of Months to Pay: | J103: 36
B104: Payment's Made | C104: Present Capital Loan | D104: Constant Payment Deducted to Capital Loan | E104: Interest Amount per Payment | F104: Amount to be Paid | G104: Paid Amount | H104: Date of Payment | I104: Receipt Number | J104: REMARKS
B105: 1st Payment: | C105: =J100 -> 40000 | D105: =J100/J103 -> 1111.1111 | E105: =(C105*0.015) -> 600 | F105: =SUM(D105:E105) -> 1711.1111
B106: 2nd Payment: | C106: 38885 | D106: 1111 | E106: =(C106*0.015) -> 583.275 | F106: =SUM(D106:E106) -> 1694.275
B107: 3rd Payment: | C107: 37774 | D107: 1111 | E107: =(C107*0.015) -> 566.61 | F107: =SUM(D107:E107) -> 1677.61
B108: 4th Payment: | C108: 36663 | D108: 1111 | E108: =(C108*0.015) -> 549.945 | F108: =SUM(D108:E108) -> 1660.945
B109: 5th Payment: | C109: 35552 | D109: 1111 | E109: =(C109*0.015) -> 533.28 | F109: =SUM(D109:E109) -> 1644.28
B110: 6th Payment: | C110: 34441 | D110: 1111 | E110: =(C110*0.015) -> 516.615 | F110: =SUM(D110:E110) -> 1627.615
B111: 7th Payment: | C111: 33330 | D111: 1111 | E111: =(C111*0.015) -> 499.95 | F111: =SUM(D111:E111) -> 1610.95
B112: 8th Payment: | C112: 32219 | D112: 1111 | E112: =(C112*0.015) -> 483.285 | F112: =SUM(D112:E112) -> 1594.285
B113: 9th Payment: | C113: 31108 | D113: 1111 | E113: =(C113*0.015) -> 466.62 | F113: =SUM(D113:E113) -> 1577.62
B114: 10th Payment: | C114: 29997 | D114: 1111 | E114: =(C114*0.015) -> 449.955 | F114: =SUM(D114:E114) -> 1560.955
B115: 11th Payment: | C115: 28886 | D115: 1111 | E115: =(C115*0.015) -> 433.29 | F115: =SUM(D115:E115) -> 1544.29
B116: 12th Payment: | C116: 27775 | D116: 1111 | E116: =(C116*0.015) -> 416.625 | F116: =SUM(D116:E116) -> 1527.625
B117: 13th Payment: | C117: 26664 | D117: 1111 | E117: =(C117*0.015) -> 399.96 | F117: =SUM(D117:E117) -> 1510.96
... B144: 35th Payment: | C144: 2222 | D144: 1111 | E144: =(C144*0.015) -> 33.33 | F144: =SUM(D144:E144) -> 1144.33
B145: 36th Payment: | C145: 1111 | D145: 1111 | E145: =(C145*0.015) -> 16.665 | F145: =SUM(D145:E145) -> 1127.665 | J145: Fully Paid
E146: =SUM(E105:E145) -> 11098.95
B149: Member's Name: | C149: Silang | I149: Loan Amount: | J149: 75000
B150: Membership Number: | I150: Date: | J150: 8/2/2024
B151: No. of Loan's Made: | I151: Interest Rate: | J151: 0.015
B152: Mode of Payment: | I152: No. of Months to Pay: | J152: 36
B153: Payment's Made | C153: Present Capital Loan | D153: Constant Payment Deducted to Capital Loan | E153: Interest Amount per Payment | F153: Amount to be Paid | G153: Paid Amount | H153: Date of Payment | I153: Receipt Number | J153: REMARKS
B154: 1st Payment: | C154: =J149 -> 75000 | D154: =J149/J152 -> 2083.3333 | E154: =(C154*0.015) -> 1125 | F154: =SUM(D154:E154) -> 3208.3333
B155: 2nd Payment: | C155: 72905 | D155: 2083 | E155: =(C155*0.015) -> 1093.575 | F155: =SUM(D155:E155) -> 3176.575
B156: 3rd Payment: | C156: 70822 | D156: 2083 | E156: =(C156*0.015) -> 1062.33 | F156: =SUM(D156:E156) -> 3145.33
B157: 4th Payment: | C157: 68739 | D157: 2083 | E157: =(C157*0.015) -> 1031.085 | F157: =SUM(D157:E157) -> 3114.085
B158: 5th Payment: | C158: 66656 | D158: 2083 | E158: =(C158*0.015) -> 999.84 | F158: =SUM(D158:E158) -> 3082.84
B159: 6th Payment: | C159: 64573 | D159: 2083 | E159: =(C159*0.015) -> 968.595 | F159: =SUM(D159:E159) -> 3051.595
B160: 7th Payment: | C160: 62490 | D160: 2083 | E160: =(C160*0.015) -> 937.35 | F160: =SUM(D160:E160) -> 3020.35
B161: 8th Payment: | C161: 60407 | D161: 2083 | E161: =(C161*0.015) -> 906.105 | F161: =SUM(D161:E161) -> 2989.105
B162: 9th Payment: | C162: 58324 | D162: 2083 | E162: =(C162*0.015) -> 874.86 | F162: =SUM(D162:E162) -> 2957.86
B163: 10th Payment: | C163: 56241 | D163: 2083 | E163: =(C163*0.015) -> 843.615 | F163: =SUM(D163:E163) -> 2926.615
B164: 11th Payment: | C164: 54158 | D164: 2083 | E164: =(C164*0.015) -> 812.37 | F164: =SUM(D164:E164) -> 2895.37
B165: 12th Payment: | C165: 52075 | D165: 2083 | E165: =(C165*0.015) -> 781.125 | F165: =SUM(D165:E165) -> 2864.125
B166: 13th Payment: | C166: 49992 | D166: 2083 | E166: =(C166*0.015) -> 749.88 | F166: =SUM(D166:E166) -> 2832.88
... B181: 26th Payment: | C181: 22913 | D181: 2083 | E181: =(C181*0.015) -> 343.695 | F181: =SUM(D181:E181) -> 2426.695
B182: 27th Payment: | C182: 20830 | D182: 2083 | E182: =(C182*0.015) -> 312.45 | F182: =SUM(D182:E182) -> 2395.45 | L182: Member's Name: | M182: Quintal, Melissa | R182: Loan Amount: | T182: 53000
B183: 28th Payment: | C183: 18747 | D183: 2083 | E183: =(C183*0.015) -> 281.205 | F183: =SUM(D183:E183) -> 2364.205 | L183: Membership Number: | S183: Date: | T183: 1/19/2024
B184: 29th Payment: | C184: 16664 | D184: 2083 | E184: =(C184*0.015) -> 249.96 | F184: =SUM(D184:E184) -> 2332.96 | L184: No. of Loan's Made: | P184: Interest Rate: | T184: 0.015
B185: 30th Payment: | C185: 14581 | D185: 2083 | E185: =(C185*0.015) -> 218.715 | F185: =SUM(D185:E185) -> 2301.715 | L185: Mode of Payment: | O185: No. of Months to Pay: | T185: 24
B186: 31st Payment: | C186: 12498 | D186: 2083 | E186: =(C186*0.015) -> 187.47 | F186: =SUM(D186:E186) -> 2270.47 | L186: Payment's Made | M186: Present Capital Loan | N186: Constant Payment Deducted to Capital Loan | O186: Interest Amount per Payment | P186: Amount to be Paid | Q186: Paid Amount | R186: Date of Payment | S186: Receipt Number | T186: REMARKS
B187: 32nd Payment: | C187: 10415 | D187: 2083 | E187: =(C187*0.015) -> 156.225 | F187: =SUM(D187:E187) -> 2239.225 | L187: 1st Payment: | M187: =T182 -> 53000 | N187: =T182/T185 -> 2208.3333 | O187: =(M187*0.015) -> 795 | P187: =SUM(N187:O187) -> 3003.3333
B188: 33rd Payment: | C188: 8332 | D188: 2083 | E188: =(C188*0.015) -> 124.98 | F188: =SUM(D188:E188) -> 2207.98 | L188: 2nd Payment: | M188: 50784 | N188: 2208 | O188: =(M188*0.015) -> 761.76 | P188: =SUM(N188:O188) -> 2969.76
...

Sheet 4 mos
B1: Member's Name: | C1: Tiama, Ma. Janina | H1: Loan Amount: | J1: 40000 | L1: Member's Name: | M1: Tiama, Ma. Janina | R1: Loan Amount: | T1: 40000
B2: Membership Number: | I2: Date: | J2: 9/10/2024 | L2: Membership Number: | S2: Date: | T2: 9/10/2024
B3: No. of Loan's Made: | F3: Interest Rate: | J3: 0.015 | L3: No. of Loan's Made: | P3: Interest Rate: | T3: 0.015
B4: Mode of Payment: | E4: No. of Months to Pay: | J4: 4 | L4: Mode of Payment: | O4: No. of Months to Pay: | T4: 4
B5: Payment's Made | C5: Present Capital Loan | D5: Constant Payment Deducted to Capital Loan | E5: Interest Amount per Payment | F5: Amount to be Paid | G5: Paid Amount | H5: Date of Payment | I5: Receipt Number | J5: REMARKS | L5: Payment's Made | M5: Present Capital Loan | N5: Constant Payment Deducted to Capital Loan | O5: Interest Amount per Payment | P5: Amount to be Paid | Q5: Paid Amount | R5: Date of Payment | S5: Receipt Number | T5: REMARKS
B6: 1st Payment: | C6: =J1 -> 40000 | D6: =J1/J4 -> 10000 | E6: =(C6*0.015) -> 600 | F6: =SUM(D6:E6) -> 10600 | L6: 1st Payment: | M6: =T1 -> 40000 | N6: =T1/T4 -> 10000 | O6: =(M6*0.015) -> 600 | P6: =SUM(N6:O6) -> 10600
B7: 2nd Payment: | C7: 30000 | D7: 10000 | E7: =(C7*0.015) -> 450 | F7: =SUM(D7:E7) -> 10450 | L7: 2nd Payment: | M7: 30000 | N7: 10000 | O7: =(M7*0.015) -> 450 | P7: =SUM(N7:O7) -> 10450
B8: 3rd Payment: | C8: 20000 | D8: 10000 | E8: =(C8*0.015) -> 300 | F8: =SUM(D8:E8) -> 10300 | L8: 3rd Payment: | M8: 20000 | N8: 10000 | O8: =(M8*0.015) -> 300 | P8: =SUM(N8:O8) -> 10300
B9: 4th Payment: | C9: 10000 | D9: 10000 | E9: =(C9*0.015) -> 150 | F9: =SUM(D9:E9) -> 10150 | J9: Fully Paid | L9: 4th Payment: | M9: 10000 | N9: 10000 | O9: =(M9*0.015) -> 150 | P9: =SUM(N9:O9) -> 10150 | T9: Fully Paid
B12: Member's Name: | C12: Acala. Aimee | H12: Loan Amount: | J12: 50000 | L12: Member's Name: | M12: Acala. Aimee | R12: Loan Amount: | T12: 50000
B13: Membership Number: | I13: Date: | J13: 3/19/2025 | L13: Membership Number: | S13: Date: | T13: 3/19/2025
B14: No. of Loan's Made: | F14: Interest Rate: | J14: 0.015 | L14: No. of Loan's Made: | P14: Interest Rate: | T14: 0.015
B15: Mode of Payment: | E15: No. of Months to Pay: | J15: 4 | L15: Mode of Payment: | O15: No. of Months to Pay: | T15: 4
B16: Payment's Made | C16: Present Capital Loan | D16: Constant Payment Deducted to Capital Loan | E16: Interest Amount per Payment | F16: Amount to be Paid | G16: Paid Amount | H16: Date of Payment | I16: Receipt Number | J16: REMARKS | L16: Payment's Made | M16: Present Capital Loan | N16: Constant Payment Deducted to Capital Loan | O16: Interest Amount per Payment | P16: Amount to be Paid | Q16: Paid Amount | R16: Date of Payment | S16: Receipt Number | T16: REMARKS
B17: 1st Payment: | C17: =J12 -> 50000 | D17: =J12/J15 -> 12500 | E17: =(C17*0.015) -> 750 | F17: =SUM(D17:E17) -> 13250 | G17: 45000 | L17: 1st Payment: | M17: =T12 -> 50000 | N17: =T12/T15 -> 12500 | O17: =(M17*0.015) -> 750 | P17: =SUM(N17:O17) -> 13250
B18: 2nd Payment: | C18: 37500 | D18: 12500 | E18: =(C18*0.015) -> 562.5 | F18: =SUM(D18:E18) -> 13062.5 | L18: 2nd Payment: | M18: 37500 | N18: 12500 | O18: =(M18*0.015) -> 562.5 | P18: =SUM(N18:O18) -> 13062.5
B19: 3rd Payment: | C19: 25000 | D19: 12500 | E19: =(C19*0.015) -> 375 | F19: =SUM(D19:E19) -> 12875 | L19: 3rd Payment: | M19: 25000 | N19: 12500 | O19: =(M19*0.015) -> 375 | P19: =SUM(N19:O19) -> 12875
B20: 4th Payment: | C20: 12500 | D20: 12500 | E20: =(C20*0.015) -> 187.5 | F20: =SUM(D20:E20) -> 12687.5 | J20: Fully Paid | L20: 4th Payment: | M20: 12500 | N20: 12500 | O20: =(M20*0.015) -> 187.5 | P20: =SUM(N20:O20) -> 12687.5 | T20: Fully Paid
F21: =SUM(F17:F20) -> 51875
B23: Member's Name: | C23: Navarro, Marivic | H23: Loan Amount: | J23: 10000 | L23: Member's Name: | M23: Navarro, Marivic | R23: Loan Amount: | T23: 10000
B24: Membership Number: | I24: Date: | J24: 3/17/2025 | L24: Membership Number: | S24: Date: | T24: 3/17/2025
B25: No. of Loan's Made: | F25: Interest Rate: | J25: 0.015 | L25: No. of Loan's Made: | P25: Interest Rate: | T25: 0.015
B26: Mode of Payment: | E26: No. of Months to Pay: | J26: 4 | L26: Mode of Payment: | O26: No. of Months to Pay: | T26: 4
B27: Payment's Made | C27: Present Capital Loan | D27: Constant Payment Deducted to Capital Loan | E27: Interest Amount per Payment | F27: Amount to be Paid | G27: Paid Amount | H27: Date of Payment | I27: Receipt Number | J27: REMARKS | L27: Payment's Made | M27: Present Capital Loan | N27: Constant Payment Deducted to Capital Loan | O27: Interest Amount per Payment | P27: Amount to be Paid | Q27: Paid Amount | R27: Date of Payment | S27: Receipt Number | T27: REMARKS
B28: 1st Payment: | C28: =J23 -> 10000 | D28: =J23/J26 -> 2500 | E28: =(C28*0.015) -> 150 | F28: =SUM(D28:E28) -> 2650 | L28: 1st Payment: | M28: =T23 -> 10000 | N28: =T23/T26 -> 2500 | O28: =(M28*0.015) -> 150 | P28: =SUM(N28:O28) -> 2650
B29: 2nd Payment: | C29: 7500 | D29: 2500 | E29: =(C29*0.015) -> 112.5 | F29: =SUM(D29:E29) -> 2612.5 | L29: 2nd Payment: | M29: 7500 | N29: 2500 | O29: =(M29*0.015) -> 112.5 | P29: =SUM(N29:O29) -> 2612.5
B30: 3rd Payment: | C30: 5000 | D30: 2500 | E30: =(C30*0.015) -> 75 | F30: =SUM(D30:E30) -> 2575 | L30: 3rd Payment: | M30: 5000 | N30: 2500 | O30: =(M30*0.015) -> 75 | P30: =SUM(N30:O30) -> 2575
B31: 4th Payment: | C31: 2500 | D31: 2500 | E31: =(C31*0.015) -> 37.5 | F31: =SUM(D31:E31) -> 2537.5 | J31: Fully Paid | L31: 4th Payment: | M31: 2500 | N31: 2500 | O31: =(M31*0.015) -> 37.5 | P31: =SUM(N31:O31) -> 2537.5 | T31: Fully Paid
B34: Member's Name: | C34: Dela Cruz, Myla | H34: Loan Amount: | J34: 10000 | L34: Member's Name: | M34: Dela Cruz, Myla | R34: Loan Amount: | T34: 10000
B35: Membership Number: | I35: Date: | J35: 2/6/2025 | L35: Membership Number: | S35: Date: | T35: 2/6/2025
B36: No. of Loan's Made: | F36: Interest Rate: | J36: 0.015 | L36: No. of Loan's Made: | P36: Interest Rate: | T36: 0.015
B37: Mode of Payment: | E37: No. of Months to Pay: | J37: 4 | L37: Mode of Payment: | O37: No. of Months to Pay: | T37: 4
B38: Payment's Made | C38: Present Capital Loan | D38: Constant Payment Deducted to Capital Loan | E38: Interest Amount per Payment | F38: Amount to be Paid | G38: Paid Amount | H38: Date of Payment | I38: Receipt Number | J38: REMARKS | L38: Payment's Made | M38: Present Capital Loan | N38: Constant Payment Deducted to Capital Loan | O38: Interest Amount per Payment | P38: Amount to be Paid | Q38: Paid Amount | R38: Date of Payment | S38: Receipt Number | T38: REMARKS
B39: 1st Payment: | C39: =J34 -> 10000 | D39: =J34/J37 -> 2500 | E39: =(C39*0.015) -> 150 | F39: =SUM(D39:E39) -> 2650 | L39: 1st Payment: | M39: =T34 -> 10000 | N39: =T34/T37 -> 2500 | O39: =(M39*0.015) -> 150 | P39: =SUM(N39:O39) -> 2650
B40: 2nd Payment: | C40: 7500 | D40: 2500 | E40: =(C40*0.015) -> 112.5 | F40: =SUM(D40:E40) -> 2612.5 | L40: 2nd Payment: | M40: 7500 | N40: 2500 | O40: =(M40*0.015) -> 112.5 | P40: =SUM(N40:O40) -> 2612.5
B41: 3rd Payment: | C41: 5000 | D41: 2500 | E41: =(C41*0.015) -> 75 | F41: =SUM(D41:E41) -> 2575 | L41: 3rd Payment: | M41: 5000 | N41: 2500 | O41: =(M41*0.015) -> 75 | P41: =SUM(N41:O41) -> 2575
B42: 4th Payment: | C42: 2500 | D42: 2500 | E42: =(C42*0.015) -> 37.5 | F42: =SUM(D42:E42) -> 2537.5 | J42: Fully Paid | L42: 4th Payment: | M42: 2500 | N42: 2500 | O42: =(M42*0.015) -> 37.5 | P42: =SUM(N42:O42) -> 2537.5 | T42: Fully Paid

Sheet 60-12
B3: Member's Name: | C3: Aguilar, Alma | I3: Loan Amount: | J3: 20000 | L3: Member's Name: | M3: Moyo, Princess Warlin | R3: Loan Amount: | T3: 20000
B4: Membership Number: | I4: Date: | J4: 5/18/23 | L4: Membership Number: | S4: Date: | T4: 4/17/23
B5: No. of Loan's Made: | I5: Interest Rate: | J5: 0.015 | L5: No. of Loan's Made: | S5: Interest Rate: | T5: 0.015
B6: Mode of Payment: | I6: No. of Months to Pay: | J6: 24 | L6: Mode of Payment: | S6: No. of Months to Pay: | T6: 24
B7: Payment's Made | C7: Present Capital Loan | D7: Constant Payment Deducted to Capital Loan | E7: Interest Amount per Payment | F7: Amount to be Paid | G7: Paid Amount | H7: Date of Payment | I7: Receipt Number | J7: REMARKS | L7: Payment's Made | M7: Present Capital Loan | N7: Constant Payment Deducted to Capital Loan | O7: Interest Amount per Payment | P7: Amount to be Paid | Q7: Paid Amount | R7: Date of Payment | S7: Receipt Number | T7: REMARKS
B8: 1st Payment: | C8: =J3 -> 20000 | D8: =J3/J6 -> 833.33333 | E8: =(C8*0.015) -> 300 | F8: =$C$6+E8 -> 300 | L8: 1st Payment: | M8: =T3 -> 20000 | N8: =T3/T6 -> 833.33333 | O8: =(M8*0.015) -> 300 | P8: =$C$7+'60-12'!#REF! -> #VALUE!
B9: 2nd Payment: | C9: 19159 | D9: =$C$6 -> 0 | E9: =(C9*0.015) -> 287.385 | F9: =$C$6+E9 -> 287.385 | L9: 2nd Payment: | M9: 19159 | N9: =$C$7 -> Present Capital Loan | O9: =(M9*0.015) -> 287.385 | P9: =$C$7+O9 -> #VALUE!
B10: 3rd Payment: | C10: 18326 | D10: =$C$6 -> 0 | E10: =(C10*0.015) -> 274.89 | F10: =$C$6+E10 -> 274.89 | L10: 3rd Payment: | M10: 18326 | N10: =$C$7 -> Present Capital Loan | O10: =(M10*0.015) -> 274.89 | P10: =$C$7+O10 -> #VALUE!
B11: 4th Payment: | C11: 17493 | D11: =$C$6 -> 0 | E11: =(C11*0.015) -> 262.395 | F11: =$C$6+E11 -> 262.395 | L11: 4th Payment: | M11: 17493 | N11: =$C$7 -> Present Capital Loan | O11: =(M11*0.015) -> 262.395 | P11: =$C$7+O11 -> #VALUE!
B12: 5th Payment: | C12: 16660 | D12: =$C$6 -> 0 | E12: =(C12*0.015) -> 249.9 | F12: =$C$6+E12 -> 249.9 | L12: 5th Payment: | M12: 16660 | N12: =$C$7 -> Present Capital Loan | O12: =(M12*0.015) -> 249.9 | P12: =$C$7+O12 -> #VALUE!
B13: 6th Payment: | C13: 15827 | D13: =$C$6 -> 0 | E13: =(C13*0.015) -> 237.405 | F13: =$C$6+E13 -> 237.405 | L13: 6th Payment: | M13: 15827 | N13: =$C$7 -> Present Capital Loan | O13: =(M13*0.015) -> 237.405 | P13: =$C$7+O13 -> #VALUE!
B14: 7th Payment: | C14: 14994 | D14: =$C$6 -> 0 | E14: =(C14*0.015) -> 224.91 | F14: =$C$6+E14 -> 224.91 | L14: 7th Payment: | M14: 14994 | N14: =$C$7 -> Present Capital Loan | O14: =(M14*0.015) -> 224.91 | P14: =$C$7+O14 -> #VALUE!
B15: 8th Payment: | C15: 14161 | D15: =$C$6 -> 0 | E15: =(C15*0.015) -> 212.415 | F15: =$C$6+E15 -> 212.415 | L15: 8th Payment: | M15: 14161 | N15: =$C$7 -> Present Capital Loan | O15: =(M15*0.015) -> 212.415 | P15: =$C$7+O15 -> #VALUE!
B16: 9th Payment: | C16: 13328 | D16: =$C$6 -> 0 | E16: =(C16*0.015) -> 199.92 | F16: =$C$6+E16 -> 199.92 | L16: 9th Payment: | M16: 13328 | N16: =$C$7 -> Present Capital Loan | O16: =(M16*0.015) -> 199.92 | P16: =$C$7+O16 -> #VALUE!
B17: 10th Payment: | C17: 12495 | D17: =$C$6 -> 0 | E17: =(C17*0.015) -> 187.425 | F17: =$C$6+E17 -> 187.425 | L17: 10th Payment: | M17: 12495 | N17: =$C$7 -> Present Capital Loan | O17: =(M17*0.015) -> 187.425 | P17: =$C$7+O17 -> #VALUE!
B18: 11th Payment: | C18: 11662 | D18: =$C$6 -> 0 | E18: =(C18*0.015) -> 174.93 | F18: =$C$6+E18 -> 174.93 | L18: 11th Payment: | M18: 11662 | N18: =$C$7 -> Present Capital Loan | O18: =(M18*0.015) -> 174.93 | P18: =$C$7+O18 -> #VALUE!
B19: 12th Payment: | C19: 10829 | D19: =$C$6 -> 0 | E19: =(C19*0.015) -> 162.435 | F19: =$C$6+E19 -> 162.435 | L19: 12th Payment: | M19: 10829 | N19: =$C$7 -> Present Capital Loan | O19: =(M19*0.015) -> 162.435 | P19: =$C$7+O19 -> #VALUE!
B20: 13th Payment: | C20: 9996 | D20: =$C$6 -> 0 | E20: =(C20*0.015) -> 149.94 | F20: =$C$6+E20 -> 149.94 | L20: 13th Payment: | M20: 9996 | N20: =$C$7 -> Present Capital Loan | O20: =(M20*0.015) -> 149.94 | P20: =$C$7+O20 -> #VALUE!
... B30: 23rd Payment: | C30: 1666 | D30: =$C$6 -> 0 | E30: =(C30*0.015) -> 24.99 | F30: =$C$6+E30 -> 24.99 | L30: 23rd Payment: | M30: 1666 | N30: =$C$7 -> Present Capital Loan | O30: =(M30*0.015) -> 24.99 | P30: =$C$7+O30 -> #VALUE!
B31: 24th Payment: | C31: 833 | D31: =$C$6 -> 0 | E31: =(C31*0.015) -> 12.495 | F31: =$C$6+E31 -> 12.495 | J31: Fully Paid | L31: 24th Payment: | M31: 833 | N31: =$C$7 -> Present Capital Loan | O31: =(M31*0.015) -> 12.495 | P31: =$C$7+O31 -> #VALUE! | T31: Fully Paid
B37: Member's Name: | C37: Escoto, Ronalyn | H37: Loan Amount: | J37: 20000 | L37: Member's Name: | M37: Mayores, Jenelyn | S37: Loan Amount: | T37: 35000
B38: Membership Number: | I38: Date: | J38: 11/13/23 | L38: Membership Number: | S38: Date: | T38: 10/13/23
B39: No. of Loan's Made: | F39: Interest Rate: | J39: 0.015 | L39: No. of Loan's Made: | S39: Interest Rate: | T39: 0.015
B40: Mode of Payment: | E40: No. of Months to Pay: | J40: 24 | L40: Mode of Payment: | S40: No. of Months to Pay: | T40: 24
B41: Payment's Made | C41: Present Capital Loan | D41: Constant Payment Deducted to Capital Loan | E41: Interest Amount per Payment | F41: Amount to be Paid | G41: Paid Amount | H41: Date of Payment | I41: Receipt Number | J41: REMARKS | L41: Payment's Made | M41: Present Capital Loan | N41: Constant Payment Deducted to Capital Loan | O41: Interest Amount per Payment | P41: Amount to be Paid | Q41: Paid Amount | R41: Date of Payment | S41: Receipt Number | T41: REMARKS
B42: 1st Payment: | C42: =J37 -> 20000 | D42: =J37/J40 -> 833.33333 | E42: =(C42*0.015) -> 300 | F42: =$C$7+E42 -> #VALUE! | L42: 1st Payment: | M42: =T37 -> 35000 | N42: =T37/T40 -> 1458.3333 | O42: =(M42*0.015) -> 525 | P42: =$C$7+O42 -> #VALUE!
B43: 2nd Payment: | C43: 19159 | D43: =$C$7 -> Present Capital Loan | E43: =(C43*0.015) -> 287.385 | F43: =$C$7+E43 -> #VALUE! | L43: 2nd Payment: | M43: 33534 | N43: 1458 | O43: =(M43*0.015) -> 503.01 | P43: =SUM(N43:O43) -> 1961.01
B44: 3rd Payment: | C44: 18326 | D44: =$C$7 -> Present Capital Loan | E44: =(C44*0.015) -> 274.89 | F44: =$C$7+E44 -> #VALUE! | L44: 3rd Payment: | M44: 32076 | N44: 1458 | O44: =(M44*0.015) -> 481.14 | P44: =SUM(N44:O44) -> 1939.14
B45: 4th Payment: | C45: 17493 | D45: =$C$7 -> Present Capital Loan | E45: =(C45*0.015) -> 262.395 | F45: =$C$7+E45 -> #VALUE! | L45: 4th Payment: | M45: 30618 | N45: 1458 | O45: =(M45*0.015) -> 459.27 | P45: =SUM(N45:O45) -> 1917.27
B46: 5th Payment: | C46: 16660 | D46: =$C$7 -> Present Capital Loan | E46: =(C46*0.015) -> 249.9 | F46: =$C$7+E46 -> #VALUE! | L46: 5th Payment: | M46: 29160 | N46: 1458 | O46: =(M46*0.015) -> 437.4 | P46: =SUM(N46:O46) -> 1895.4
B47: 6th Payment: | C47: 15827 | D47: =$C$7 -> Present Capital Loan | E47: =(C47*0.015) -> 237.405 | F47: =$C$7+E47 -> #VALUE! | L47: 6th Payment: | M47: 27702 | N47: 1458 | O47: =(M47*0.015) -> 415.53 | P47: =SUM(N47:O47) -> 1873.53
B48: 7th Payment: | C48: 14994 | D48: =$C$7 -> Present Capital Loan | E48: =(C48*0.015) -> 224.91 | F48: =$C$7+E48 -> #VALUE! | L48: 7th Payment: | M48: 26244 | N48: 1458 | O48: =(M48*0.015) -> 393.66 | P48: =SUM(N48:O48) -> 1851.66
B49: 8th Payment: | C49: 14161 | D49: =$C$7 -> Present Capital Loan | E49: =(C49*0.015) -> 212.415 | F49: =$C$7+E49 -> #VALUE! | L49: 8th Payment: | M49: 24786 | N49: 1458 | O49: =(M49*0.015) -> 371.79 | P49: =SUM(N49:O49) -> 1829.79
B50: 9th Payment: | C50: 13328 | D50: =$C$7 -> Present Capital Loan | E50: =(C50*0.015) -> 199.92 | F50: =$C$7+E50 -> #VALUE! | L50: 9th Payment: | M50: 23328 | N50: 1458 | O50: =(M50*0.015) -> 349.92 | P50: =SUM(N50:O50) -> 1807.92
B51: 10th Payment: | C51: 12495 | D51: =$C$7 -> Present Capital Loan | E51: =(C51*0.015) -> 187.425 | F51: =$C$7+E51 -> #VALUE! | L51: 10th Payment: | M51: 21870 | N51: 1458 | O51: =(M51*0.015) -> 328.05 | P51: =SUM(N51:O51) -> 1786.05
B52: 11th Payment: | C52: 11662 | D52: =$C$7 -> Present Capital Loan | E52: =(C52*0.015) -> 174.93 | F52: =$C$7+E52 -> #VALUE! | L52: 11th Payment: | M52: 20412 | N52: 1458 | O52: =(M52*0.015) -> 306.18 | P52: =SUM(N52:O52) -> 1764.18
B53: 12th Payment: | C53: 10829 | D53: =$C$7 -> Present Capital Loan | E53: =(C53*0.015) -> 162.435 | F53: =$C$7+E53 -> #VALUE! | L53: 12th Payment: | M53: 18954 | N53: 1458 | O53: =(M53*0.015) -> 284.31 | P53: =SUM(N53:O53) -> 1742.31
B54: 13th Payment: | C54: 9996 | D54: =$C$7 -> Present Capital Loan | E54: =(C54*0.015) -> 149.94 | F54: =$C$7+E54 -> #VALUE! | L54: 13th Payment: | M54: 17496 | N54: 1458 | O54: =(M54*0.015) -> 262.44 | P54: =SUM(N54:O54) -> 1720.44
... B64: 23rd Payment: | C64: 1666 | D64: =$C$7 -> Present Capital Loan | E64: =(C64*0.015) -> 24.99 | F64: =$C$7+E64 -> #VALUE! | L64: 23rd Payment: | M64: 2916 | N64: 1458 | O64: =(M64*0.015) -> 43.74 | P64: =SUM(N64:O64) -> 1501.74
B65: 24th Payment: | C65: 833 | D65: =$C$7 -> Present Capital Loan | E65: =(C65*0.015) -> 12.495 | F65: =$C$7+E65 -> #VALUE! | J65: Fully Paid | L65: 24th Payment: | M65: 1458 | N65: 1458 | O65: =(M65*0.015) -> 21.87 | P65: =SUM(N65:O65) -> 1479.87 | T65: Fully Paid

Sheet 50-12
A26: Member's Name: | B26: Peñarubia, Sheila | G26: Loan Amount: | I26: 50000
A27: Membership Number: | H27: Date: | I27: 7/18/23
A28: No. of Loan's Made: | E28: Interest Rate: | I28: 0.015
A29: Mode of Payment: | D29: No. of Months to Pay: | I29: 12
A30: Payment's Made | B30: Present Capital Loan | C30: Constant Payment Deducted to Capital Loan | D30: Interest Amount per Payment | E30: Amount to be Paid | F30: Paid Amount | G30: Date of Payment | H30: Receipt Number | I30: REMARKS
A31: 1st Payment: | B31: =I26 -> 50000 | C31: =I26/I29 -> 4166.6667 | D31: =(B31*0.015) -> 750 | E31: =#REF!+D31 -> #REF!
A32: 2nd Payment: | B32: 55000 | C32: =#REF! -> #REF! | D32: =(B32*0.015) -> 825 | E32: =#REF!+D32 -> #REF!
A33: 3rd Payment: | B33: 50000 | C33: =#REF! -> #REF! | D33: =(B33*0.015) -> 750 | E33: =#REF!+D33 -> #REF!
A34: 4th Payment: | B34: 45000 | C34: =#REF! -> #REF! | D34: =(B34*0.015) -> 675 | E34: =#REF!+D34 -> #REF!
A35: 5th Payment: | B35: 40000 | C35: =#REF! -> #REF! | D35: =(B35*0.015) -> 600 | E35: =#REF!+D35 -> #REF!
A36: 6th Payment: | B36: 35000 | C36: =#REF! -> #REF! | D36: =(B36*0.015) -> 525 | E36: =#REF!+D36 -> #REF!
A37: 7th Payment: | B37: 30000 | C37: =#REF! -> #REF! | D37: =(B37*0.015) -> 450 | E37: =#REF!+D37 -> #REF!
A38: 8th Payment: | B38: 25000 | C38: =#REF! -> #REF! | D38: =(B38*0.015) -> 375 | E38: =#REF!+D38 -> #REF!
A39: 9th Payment: | B39: 20000 | C39: =#REF! -> #REF! | D39: =(B39*0.015) -> 300 | E39: =#REF!+D39 -> #REF!
A40: 10th Payment: | B40: 15000 | C40: =#REF! -> #REF! | D40: =(B40*0.015) -> 225 | E40: =#REF!+D40 -> #REF!
A41: 11th Payment: | B41: 10000 | C41: =#REF! -> #REF! | D41: =(B41*0.015) -> 150 | E41: =#REF!+D41 -> #REF!
A42: 12th Payment: | B42: 5000 | C42: =#REF! -> #REF! | D42: =(B42*0.015) -> 75 | E42: =#REF!+D42 -> #REF! | I42: Fully Paid
A48: Member's Name: | B48: De Mesa, Danilo | G48: Loan Amount: | I48: 50000
A49: Membership Number: | H49: Date: | I49: 7/28/23
A50: No. of Loan's Made: | E50: Interest Rate: | I50: 0.015
A51: Mode of Payment: | D51: No. of Months to Pay: | I51: 12
A52: Payment's Made | B52: Present Capital Loan | C52: Constant Payment Deducted to Capital Loan | D52: Interest Amount per Payment | E52: Amount to be Paid | F52: Paid Amount | G52: Date of Payment | H52: Receipt Number | I52: REMARKS
A53: 1st Payment: | B53: =I48 -> 50000 | C53: =I48/I51 -> 4166.6667 | D53: =(B53*0.015) -> 750 | E53: =#REF!+D53 -> #REF!
A54: 2nd Payment: | B54: 55000 | C54: =#REF! -> #REF! | D54: =(B54*0.015) -> 825 | E54: =#REF!+D54 -> #REF!
A55: 3rd Payment: | B55: 50000 | C55: =#REF! -> #REF! | D55: =(B55*0.015) -> 750 | E55: =#REF!+D55 -> #REF!
A56: 4th Payment: | B56: 45000 | C56: =#REF! -> #REF! | D56: =(B56*0.015) -> 675 | E56: =#REF!+D56 -> #REF!
A57: 5th Payment: | B57: 40000 | C57: =#REF! -> #REF! | D57: =(B57*0.015) -> 600 | E57: =#REF!+D57 -> #REF!
A58: 6th Payment: | B58: 35000 | C58: =#REF! -> #REF! | D58: =(B58*0.015) -> 525 | E58: =#REF!+D58 -> #REF!
A59: 7th Payment: | B59: 30000 | C59: =#REF! -> #REF! | D59: =(B59*0.015) -> 450 | E59: =#REF!+D59 -> #REF!
A60: 8th Payment: | B60: 25000 | C60: =#REF! -> #REF! | D60: =(B60*0.015) -> 375 | E60: =#REF!+D60 -> #REF!
A61: 9th Payment: | B61: 20000 | C61: =#REF! -> #REF! | D61: =(B61*0.015) -> 300 | E61: =#REF!+D61 -> #REF!
A62: 10th Payment: | B62: 15000 | C62: =#REF! -> #REF! | D62: =(B62*0.015) -> 225 | E62: =#REF!+D62 -> #REF!
A63: 11th Payment: | B63: 10000 | C63: =#REF! -> #REF! | D63: =(B63*0.015) -> 150 | E63: =#REF!+D63 -> #REF!
A64: 12th Payment: | B64: 5000 | C64: =#REF! -> #REF! | D64: =(B64*0.015) -> 75 | E64: =#REF!+D64 -> #REF! | I64: Fully Paid
A72: Member's Name: | B72: De Mesa, Juczvil | G72: Loan Amount: | I72: 50000
A73: Membership Number: | H73: Date: | I73: 7/28/23
A74: No. of Loan's Made: | E74: Interest Rate: | I74: 0.015
A75: Mode of Payment: | D75: No. of Months to Pay: | I75: 12
A76: Payment's Made | B76: Present Capital Loan | C76: Constant Payment Deducted to Capital Loan | D76: Interest Amount per Payment | E76: Amount to be Paid | F76: Paid Amount | G76: Date of Payment | H76: Receipt Number | I76: REMARKS
A77: 1st Payment: | B77: =I72 -> 50000 | C77: =I72/I75 -> 4166.6667 | D77: =(B77*0.015) -> 750 | E77: =#REF!+D77 -> #REF!
A78: 2nd Payment: | B78: 55000 | C78: =#REF! -> #REF! | D78: =(B78*0.015) -> 825 | E78: =#REF!+D78 -> #REF!
A79: 3rd Payment: | B79: 50000 | C79: =#REF! -> #REF! | D79: =(B79*0.015) -> 750 | E79: =#REF!+D79 -> #REF!
A80: 4th Payment: | B80: 45000 | C80: =#REF! -> #REF! | D80: =(B80*0.015) -> 675 | E80: =#REF!+D80 -> #REF!
A81: 5th Payment: | B81: 40000 | C81: =#REF! -> #REF! | D81: =(B81*0.015) -> 600 | E81: =#REF!+D81 -> #REF!
A82: 6th Payment: | B82: 35000 | C82: =#REF! -> #REF! | D82: =(B82*0.015) -> 525 | E82: =#REF!+D82 -> #REF!
A83: 7th Payment: | B83: 30000 | C83: =#REF! -> #REF! | D83: =(B83*0.015) -> 450 | E83: =#REF!+D83 -> #REF!
A84: 8th Payment: | B84: 25000 | C84: =#REF! -> #REF! | D84: =(B84*0.015) -> 375 | E84: =#REF!+D84 -> #REF!
A85: 9th Payment: | B85: 20000 | C85: =#REF! -> #REF! | D85: =(B85*0.015) -> 300 | E85: =#REF!+D85 -> #REF!
A86: 10th Payment: | B86: 15000 | C86: =#REF! -> #REF! | D86: =(B86*0.015) -> 225 | E86: =#REF!+D86 -> #REF!
A87: 11th Payment: | B87: 10000 | C87: =#REF! -> #REF! | D87: =(B87*0.015) -> 150 | E87: =#REF!+D87 -> #REF!
A88: 12th Payment: | B88: 5000 | C88: =#REF! -> #REF! | D88: =(B88*0.015) -> 75 | E88: =#REF!+D88 -> #REF! | I88: Fully Paid
A93: Member's Name: | B93: Asuncion, Marites | G93: Loan Amount: | I93: 50000
A94: Membership Number: | H94: Date: | I94: 8/14/23
A95: No. of Loan's Made: | E95: Interest Rate: | I95: 0.015
A96: Mode of Payment: | D96: No. of Months to Pay: | I96: 12
A97: Payment's Made | B97: Present Capital Loan | C97: Constant Payment Deducted to Capital Loan | D97: Interest Amount per Payment | E97: Amount to be Paid | F97: Paid Amount | G97: Date of Payment | H97: Receipt Number | I97: REMARKS
A98: 1st Payment: | B98: =I93 -> 50000 | C98: =I93/I96 -> 4166.6667 | D98: =(B98*0.015) -> 750 | E98: {=#REF!+'50-12'!P8D98} -> #REF!
A99: 2nd Payment: | B99: 55000 | C99: =#REF! -> #REF! | D99: =(B99*0.015) -> 825 | E99: =#REF!+D99 -> #REF!
A100: 3rd Payment: | B100: 50000 | C100: =#REF! -> #REF! | D100: =(B100*0.015) -> 750 | E100: =#REF!+D100 -> #REF!
A101: 4th Payment: | B101: 45000 | C101: =#REF! -> #REF! | D101: =(B101*0.015) -> 675 | E101: =#REF!+D101 -> #REF!
A102: 5th Payment: | B102: 40000 | C102: =#REF! -> #REF! | D102: =(B102*0.015) -> 600 | E102: =#REF!+D102 -> #REF!
A103: 6th Payment: | B103: 35000 | C103: =#REF! -> #REF! | D103: =(B103*0.015) -> 525 | E103: =#REF!+D103 -> #REF!
A104: 7th Payment: | B104: 30000 | C104: =#REF! -> #REF! | D104: =(B104*0.015) -> 450 | E104: =#REF!+D104 -> #REF!
A105: 8th Payment: | B105: 25000 | C105: =#REF! -> #REF! | D105: =(B105*0.015) -> 375 | E105: =#REF!+D105 -> #REF!
A106: 9th Payment: | B106: 20000 | C106: =#REF! -> #REF! | D106: =(B106*0.015) -> 300 | E106: =#REF!+D106 -> #REF!
A107: 10th Payment: | B107: 15000 | C107: =#REF! -> #REF! | D107: =(B107*0.015) -> 225 | E107: =#REF!+D107 -> #REF!
A108: 11th Payment: | B108: 10000 | C108: =#REF! -> #REF! | D108: =(B108*0.015) -> 150 | E108: =#REF!+D108 -> #REF!
A109: 12th Payment: | B109: 5000 | C109: =#REF! -> #REF! | D109: =(B109*0.015) -> 75 | E109: =#REF!+D109 -> #REF! | I109: Fully Paid

Sheet 30-12
A1: Member's Name: | B1: Bautista, Jonah | G1: Loan Amount: | I1: 30000
A2: Membership Number: | G2: Date: | I2: 2/22/23
A3: No. of Loan's Made: | G3: Interest Rate: | I3: 0.015
A4: Mode of Payment: | G4: No. of Months to Pay: | I4: 12
A5: Payment's Made | B5: Present Capital Loan | C5: Constant Payment Deducted to Capital Loan | D5: Interest Amount per Payment | E5: Amount to be Paid | F5: Paid Amount | G5: Date of Payment | H5: Receipt Number | I5: REMARKS
A6: 1st Payment: | B6: =I1 -> 30000 | C6: =I1/I4 -> 2500 | D6: =(B6*0.015) -> 450 | E6: =$C$6+D6 -> 2950
A7: 2nd Payment: | B7: 27500 | C7: =$C$6 -> 2500 | D7: =(B7*0.015) -> 412.5 | E7: =$C$6+D7 -> 2912.5
A8: 3rd Payment: | B8: 2500 | C8: =$C$6 -> 2500 | D8: =(B8*0.015) -> 37.5 | E8: =$C$6+D8 -> 2537.5
A9: 4th Payment: | B9: 22500 | C9: =$C$6 -> 2500 | D9: =(B9*0.015) -> 337.5 | E9: =$C$6+D9 -> 2837.5
A10: 5th Payment: | B10: 20000 | C10: =$C$6 -> 2500 | D10: =(B10*0.015) -> 300 | E10: =$C$6+D10 -> 2800
A11: 6th Payment: | B11: 17500 | C11: =$C$6 -> 2500 | D11: =(B11*0.015) -> 262.5 | E11: =$C$6+D11 -> 2762.5
A12: 7th Payment: | B12: 15000 | C12: =$C$6 -> 2500 | D12: =(B12*0.015) -> 225 | E12: =$C$6+D12 -> 2725
A13: 8th Payment: | B13: 12500 | C13: =$C$6 -> 2500 | D13: =(B13*0.015) -> 187.5 | E13: =$C$6+D13 -> 2687.5
A14: 9th Payment: | B14: 10000 | C14: =$C$6 -> 2500 | D14: =(B14*0.015) -> 150 | E14: =$C$6+D14 -> 2650
A15: 10th Payment: | B15: 7500 | C15: =$C$6 -> 2500 | D15: =(B15*0.015) -> 112.5 | E15: =$C$6+D15 -> 2612.5
A16: 11th Payment: | B16: 5000 | C16: =$C$6 -> 2500 | D16: =(B16*0.015) -> 75 | E16: =$C$6+D16 -> 2575
A17: 12th Payment: | B17: 2500 | C17: =$C$6 -> 2500 | D17: =(B17*0.015) -> 37.5 | E17: =$C$6+D17 -> 2537.5 | I17: Fully Paid
A22: Member's Name: | B22: Recaña, Ma. Liza | G22: Loan Amount: | I22: 30000
A23: Membership Number: | G23: Date: | I23: 4/20/23
A24: No. of Loan's Made: | G24: Interest Rate: | I24: 0.015
A25: Mode of Payment: | G25: No. of Months to Pay: | I25: 12
A26: Payment's Made | B26: Present Capital Loan | C26: Constant Payment Deducted to Capital Loan | D26: Interest Amount per Payment | E26: Amount to be Paid | F26: Paid Amount | G26: Date of Payment | H26: Receipt Number | I26: REMARKS
A27: 1st Payment: | B27: =I22 -> 30000 | C27: =I22/I25 -> 2500 | D27: =(B27*0.015) -> 450 | E27: =$C$6+D27 -> 2950
A28: 2nd Payment: | B28: 27500 | C28: =$C$6 -> 2500 | D28: =(B28*0.015) -> 412.5 | E28: =$C$6+D28 -> 2912.5
A29: 3rd Payment: | B29: 2500 | C29: =$C$6 -> 2500 | D29: =(B29*0.015) -> 37.5 | E29: =$C$6+D29 -> 2537.5
A30: 4th Payment: | B30: 22500 | C30: =$C$6 -> 2500 | D30: =(B30*0.015) -> 337.5 | E30: =$C$6+D30 -> 2837.5
A31: 5th Payment: | B31: 20000 | C31: =$C$6 -> 2500 | D31: =(B31*0.015) -> 300 | E31: =$C$6+D31 -> 2800
A32: 6th Payment: | B32: 17500 | C32: =$C$6 -> 2500 | D32: =(B32*0.015) -> 262.5 | E32: =$C$6+D32 -> 2762.5
A33: 7th Payment: | B33: 15000 | C33: =$C$6 -> 2500 | D33: =(B33*0.015) -> 225 | E33: =$C$6+D33 -> 2725
A34: 8th Payment: | B34: 12500 | C34: =$C$6 -> 2500 | D34: =(B34*0.015) -> 187.5 | E34: =$C$6+D34 -> 2687.5
A35: 9th Payment: | B35: 10000 | C35: =$C$6 -> 2500 | D35: =(B35*0.015) -> 150 | E35: =$C$6+D35 -> 2650
A36: 10th Payment: | B36: 7500 | C36: =$C$6 -> 2500 | D36: =(B36*0.015) -> 112.5 | E36: =$C$6+D36 -> 2612.5
A37: 11th Payment: | B37: 5000 | C37: =$C$6 -> 2500 | D37: =(B37*0.015) -> 75 | E37: =$C$6+D37 -> 2575
A38: 12th Payment: | B38: 2500 | C38: =$C$6 -> 2500 | D38: =(B38*0.015) -> 37.5 | E38: =$C$6+D38 -> 2537.5
A39: 11th Payment: | B39: 5000 | C39: =$C$6 -> 2500 | D39: =(B39*0.015) -> 75 | E39: =$C$6+D39 -> 2575
A40: 12th Payment: | B40: 2500 | C40: =$C$6 -> 2500 | D40: =(B40*0.015) -> 37.5 | E40: =$C$6+D40 -> 2537.5 | I40: Fully Paid

Sheet 10-3
A2: Member's Name: | B2: Generala, Julieta | G2: Loan Amount: | I2: 10000
A3: Membership Number: | H3: Date: | I3: 9/8/2023
A4: No. of Loan's Made: | E4: Interest Rate: | I4: 0.015
A5: Mode of Payment: | D5: No. of Months to Pay: | I5: 3
A6: Payment's Made | B6: Present Capital Loan | C6: Constant Payment Deducted to Capital Loan | D6: Interest Amount per Payment | E6: Amount to be Paid | F6: Paid Amount | G6: Date of Payment | H6: Receipt Number | I6: REMARKS
A7: 1st Payment: | B7: =I2 -> 10000 | C7: =I2/I5 -> 3333.3333 | D7: =(B7*0.015) -> 150 | E7: =$C$7+D7 -> 3483.3333
A8: 2nd Payment: | B8: 6667 | C8: =$C$7 -> 3333.3333 | D8: =(B8*0.015) -> 100.005 | E8: =$C$7+D8 -> 3433.3383
A9: 3rd Payment: | B9: 3333 | C9: =$C$7 -> 3333.3333 | D9: =(B9*0.015) -> 49.995 | E9: =$C$7+D9 -> 3383.3283 | I9: Fully Paid
A15: Member's Name: | B15: Bautitsa, Jonah | F15: (EL) | G15: Loan Amount: | I15: 10000
A16: Membership Number: | H16: Date: | I16: 8/24/2023
A17: No. of Loan's Made: | E17: Interest Rate: | I17: 0.015
A18: Mode of Payment: | D18: No. of Months to Pay: | I18: 3
A19: Payment's Made | B19: Present Capital Loan | C19: Constant Payment Deducted to Capital Loan | D19: Interest Amount per Payment | E19: Amount to be Paid | F19: Paid Amount | G19: Date of Payment | H19: Receipt Number | I19: REMARKS
A20: 1st Payment: | B20: =I15 -> 10000 | C20: =I15/I18 -> 3333.3333 | D20: =(B20*0.015) -> 150 | E20: =$C$7+D20 -> 3483.3333
A21: 2nd Payment: | B21: 6667 | C21: =$C$7 -> 3333.3333 | D21: =(B21*0.015) -> 100.005 | E21: =$C$7+D21 -> 3433.3383
A22: 3rd Payment: | B22: 3333 | C22: =$C$7 -> 3333.3333 | D22: =(B22*0.015) -> 49.995 | E22: =$C$7+D22 -> 3383.3283 | I22: Fully Paid
A28: Member's Name: | B28: Dela Cruz, Myla | F28: (EL) | G28: Loan Amount: | I28: 10000
A29: Membership Number: | H29: Date: | I29: 2/3/23
A30: No. of Loan's Made: | E30: Interest Rate: | I30: 0.015
A31: Mode of Payment: | D31: No. of Months to Pay: | I31: 3
A32: Payment's Made | B32: Present Capital Loan | C32: Constant Payment Deducted to Capital Loan | D32: Interest Amount per Payment | E32: Amount to be Paid | F32: Paid Amount | G32: Date of Payment | H32: Receipt Number | I32: REMARKS
A33: 1st Payment: | B33: =I28 -> 10000 | C33: =I28/I31 -> 3333.3333 | D33: =(B33*0.015) -> 150 | E33: =$C$7+D33 -> 3483.3333
A34: 2nd Payment: | B34: 6667 | C34: =$C$7 -> 3333.3333 | D34: =(B34*0.015) -> 100.005 | E34: =$C$7+D34 -> 3433.3383
A35: 3rd Payment: | B35: 3333 | C35: =$C$7 -> 3333.3333 | D35: =(B35*0.015) -> 49.995 | E35: =$C$7+D35 -> 3383.3283 | I35: Fully Paid
A45: Member's Name: | B45: Tangtang, Neddie | F45: (EL) | G45: Loan Amount: | I45: 10000
A46: Membership Number: | H46: Date: | I46: 7/18/23
A47: No. of Loan's Made: | E47: Interest Rate: | I47: 0.015
A48: Mode of Payment: | D48: No. of Months to Pay: | I48: 3
A49: Payment's Made | B49: Present Capital Loan | C49: Constant Payment Deducted to Capital Loan | D49: Interest Amount per Payment | E49: Amount to be Paid | F49: Paid Amount | G49: Date of Payment | H49: Receipt Number | I49: REMARKS
A50: 1st Payment: | B50: =I45 -> 10000 | C50: =I45/I48 -> 3333.3333 | D50: =(B50*0.015) -> 150 | E50: =$C$7+D50 -> 3483.3333
A51: 2nd Payment: | B51: 6667 | C51: =$C$7 -> 3333.3333 | D51: =(B51*0.015) -> 100.005 | E51: =$C$7+D51 -> 3433.3383
A52: 3rd Payment: | B52: 3333 | C52: =$C$7 -> 3333.3333 | D52: =(B52*0.015) -> 49.995 | E52: =$C$7+D52 -> 3383.3283 | I52: Fully Paid
A57: Member's Name: | B57: Golingay, Cristina | G57: Loan Amount: | I57: 10000
A58: Membership Number: | H58: Date: | I58: 10/24/23
A59: No. of Loan's Made: | E59: Interest Rate: | I59: 0.015
A60: Mode of Payment: | D60: No. of Months to Pay: | I60: 3
A61: Payment's Made | B61: Present Capital Loan | C61: Constant Payment Deducted to Capital Loan | D61: Interest Amount per Payment | E61: Amount to be Paid | F61: Paid Amount | G61: Date of Payment | H61: Receipt Number | I61: REMARKS
A62: 1st Payment: | B62: =I57 -> 10000 | C62: =I57/I60 -> 3333.3333 | D62: =(B62*0.015) -> 150 | E62: =$C$7+D62 -> 3483.3333
A63: 2nd Payment: | B63: 6667 | C63: =$C$7 -> 3333.3333 | D63: =(B63*0.015) -> 100.005 | E63: =$C$7+D63 -> 3433.3383
A64: 3rd Payment: | B64: 3333 | C64: =$C$7 -> 3333.3333 | D64: =(B64*0.015) -> 49.995 | E64: =$C$7+D64 -> 3383.3283 | I64: Fully Paid
A69: Member's Name: | B69: Mayores, Jenelyn | G69: Loan Amount: | I69: 5000
A70: Membership Number: | H70: Date: | I70: 1/17/23
A71: No. of Loan's Made: | E71: Interest Rate: | I71: 0.015
A72: Mode of Payment: | D72: No. of Months to Pay: | I72: 3
A73: Payment's Made | B73: Present Capital Loan | C73: Constant Payment Deducted to Capital Loan | D73: Interest Amount per Payment | E73: Amount to be Paid | F73: Paid Amount | G73: Date of Payment | H73: Receipt Number | I73: REMARKS
A74: 1st Payment: | B74: =I69 -> 5000 | C74: =I69/I72 -> 1666.6667 | D74: =(B74*0.015) -> 75 | E74: =SUM(C74:D74) -> 1741.6667
A75: 2nd Payment: | B75: 3333 | C75: 1667 | D75: =(B75*0.015) -> 49.995 | E75: =SUM(C75:D75) -> 1716.995
A76: 3rd Payment: | B76: 1667 | C76: 1667 | D76: =(B76*0.015) -> 25.005 | E76: =SUM(C76:D76) -> 1692.005 | I76: Fully Paid
A91: Member's Name: | B91: Golingay, Cristina | G91: Loan Amount: | I91: 5000
A92: Membership Number: | H92: Date: | I92: 3/29/23
A93: No. of Loan's Made: | E93: Interest Rate: | I93: 0.015
A94: Mode of Payment: | D94: No. of Months to Pay: | I94: 3
A95: Payment's Made | B95: Present Capital Loan | C95: Constant Payment Deducted to Capital Loan | D95: Interest Amount per Payment | E95: Amount to be Paid | F95: Paid Amount | G95: Date of Payment | H95: Receipt Number | I95: REMARKS
A96: 1st Payment: | B96: =I91 -> 5000 | C96: =I91/I94 -> 1666.6667 | D96: =(B96*0.015) -> 75 | E96: =SUM(C96:D96) -> 1741.6667
A97: 2nd Payment: | B97: 3333 | C97: 1667 | D97: =(B97*0.015) -> 49.995 | E97: =SUM(C97:D97) -> 1716.995
A98: 3rd Payment: | B98: 1667 | C98: 1667 | D98: =(B98*0.015) -> 25.005 | E98: =SUM(C98:D98) -> 1692.005 | I98: Fully Paid
A104: Member's Name: | B104: Gunda, Ma. Jomelyn | G104: Loan Amount: | I104: 5000
A105: Membership Number: | H105: Date: | I105: 4/20/23
A106: No. of Loan's Made: | E106: Interest Rate: | I106: 0.015
A107: Mode of Payment: | G107: No. of Months to Pay: | I107: 3
A108: Payment's Made | B108: Present Capital Loan | C108: Constant Payment Deducted to Capital Loan | D108: Interest Amount per Payment | E108: Amount to be Paid | F108: Paid Amount | G108: Date of Payment | H108: Receipt Number | I108: REMARKS
A109: 1st Payment: | B109: =I104 -> 5000 | C109: =I104/I107 -> 1666.6667 | D109: =(B109*0.015) -> 75 | E109: =SUM(C109:D109) -> 1741.6667
A110: 2nd Payment: | B110: 3334 | C110: 1667 | D110: =(B110*0.015) -> 50.01 | E110: =SUM(C110:D110) -> 1717.01
A111: 3rd Payment: | B111: 1667 | C111: 1667 | D111: =(B111*0.015) -> 25.005 | E111: =SUM(C111:D111) -> 1692.005 | I111: Fully Paid

Sheet 20-24
A2: Member's Name: | B2: Aguilar, Alma | G2: Loan Amount: | I2: 20000
A3: Membership Number: | H3: Date: | I3: 5/18/23
A4: No. of Loan's Made: | E4: Interest Rate: | I4: 0.015
A5: Mode of Payment: | D5: No. of Months to Pay: | I5: 24
A6: Payment's Made | B6: Present Capital Loan | C6: Constant Payment Deducted to Capital Loan | D6: Interest Amount per Payment | E6: Amount to be Paid | F6: Paid Amount | G6: Date of Payment | H6: Receipt Number | I6: REMARKS
A7: 1st Payment: | B7: =I2 -> 20000 | C7: =I2/I5 -> 833.33333 | D7: =(B7*0.015) -> 300 | E7: =$C$7+D7 -> 1133.3333
A8: 2nd Payment: | B8: 19159 | C8: =$C$7 -> 833.33333 | D8: =(B8*0.015) -> 287.385 | E8: =$C$7+D8 -> 1120.7183
A9: 3rd Payment: | B9: 18326 | C9: =$C$7 -> 833.33333 | D9: =(B9*0.015) -> 274.89 | E9: =$C$7+D9 -> 1108.2233
A10: 4th Payment: | B10: 17493 | C10: =$C$7 -> 833.33333 | D10: =(B10*0.015) -> 262.395 | E10: =$C$7+D10 -> 1095.7283
A11: 5th Payment: | B11: 16660 | C11: =$C$7 -> 833.33333 | D11: =(B11*0.015) -> 249.9 | E11: =$C$7+D11 -> 1083.2333
A12: 6th Payment: | B12: 15827 | C12: =$C$7 -> 833.33333 | D12: =(B12*0.015) -> 237.405 | E12: =$C$7+D12 -> 1070.7383
A13: 7th Payment: | B13: 14994 | C13: =$C$7 -> 833.33333 | D13: =(B13*0.015) -> 224.91 | E13: =$C$7+D13 -> 1058.2433
A14: 8th Payment: | B14: 14161 | C14: =$C$7 -> 833.33333 | D14: =(B14*0.015) -> 212.415 | E14: =$C$7+D14 -> 1045.7483
A15: 9th Payment: | B15: 13328 | C15: =$C$7 -> 833.33333 | D15: =(B15*0.015) -> 199.92 | E15: =$C$7+D15 -> 1033.2533
A16: 10th Payment: | B16: 12495 | C16: =$C$7 -> 833.33333 | D16: =(B16*0.015) -> 187.425 | E16: =$C$7+D16 -> 1020.7583
A17: 11th Payment: | B17: 11662 | C17: =$C$7 -> 833.33333 | D17: =(B17*0.015) -> 174.93 | E17: =$C$7+D17 -> 1008.2633
A18: 12th Payment: | B18: 10829 | C18: =$C$7 -> 833.33333 | D18: =(B18*0.015) -> 162.435 | E18: =$C$7+D18 -> 995.76833
A19: 13th Payment: | B19: 9996 | C19: =$C$7 -> 833.33333 | D19: =(B19*0.015) -> 149.94 | E19: =$C$7+D19 -> 983.27333
... A29: 23rd Payment: | B29: 1666 | C29: =$C$7 -> 833.33333 | D29: =(B29*0.015) -> 24.99 | E29: =$C$7+D29 -> 858.32333
A30: 24th Payment: | B30: 833 | C30: =$C$7 -> 833.33333 | D30: =(B30*0.015) -> 12.495 | E30: =$C$7+D30 -> 845.82833 | I30: Fully Paid
A52: Member's Name: | B52: Moyo, Princess Warlin | G52: Loan Amount: | I52: 20000
A53: Membership Number: | H53: Date: | I53: 4/17/23
A54: No. of Loan's Made: | E54: Interest Rate: | I54: 0.015
A55: Mode of Payment: | D55: No. of Months to Pay: | I55: 24
A56: Payment's Made | B56: Present Capital Loan | C56: Constant Payment Deducted to Capital Loan | D56: Interest Amount per Payment | E56: Amount to be Paid | F56: Paid Amount | G56: Date of Payment | H56: Receipt Number | I56: REMARKS
A57: 1st Payment: | B57: =I52 -> 20000 | C57: =I52/I55 -> 833.33333 | D57: =(B57*0.015) -> 300 | E57: =$C$7+'60-12'!O8 -> 1133.3333
A58: 2nd Payment: | B58: 19159 | C58: =$C$7 -> 833.33333 | D58: =(B58*0.015) -> 287.385 | E58: =$C$7+D58 -> 1120.7183
A59: 3rd Payment: | B59: 18326 | C59: =$C$7 -> 833.33333 | D59: =(B59*0.015) -> 274.89 | E59: =$C$7+D59 -> 1108.2233
A60: 4th Payment: | B60: 17493 | C60: =$C$7 -> 833.33333 | D60: =(B60*0.015) -> 262.395 | E60: =$C$7+D60 -> 1095.7283
A61: 5th Payment: | B61: 16660 | C61: =$C$7 -> 833.33333 | D61: =(B61*0.015) -> 249.9 | E61: =$C$7+D61 -> 1083.2333
A62: 6th Payment: | B62: 15827 | C62: =$C$7 -> 833.33333 | D62: =(B62*0.015) -> 237.405 | E62: =$C$7+D62 -> 1070.7383
A63: 7th Payment: | B63: 14994 | C63: =$C$7 -> 833.33333 | D63: =(B63*0.015) -> 224.91 | E63: =$C$7+D63 -> 1058.2433
A64: 8th Payment: | B64: 14161 | C64: =$C$7 -> 833.33333 | D64: =(B64*0.015) -> 212.415 | E64: =$C$7+D64 -> 1045.7483
A65: 9th Payment: | B65: 13328 | C65: =$C$7 -> 833.33333 | D65: =(B65*0.015) -> 199.92 | E65: =$C$7+D65 -> 1033.2533
A66: 10th Payment: | B66: 12495 | C66: =$C$7 -> 833.33333 | D66: =(B66*0.015) -> 187.425 | E66: =$C$7+D66 -> 1020.7583
A67: 11th Payment: | B67: 11662 | C67: =$C$7 -> 833.33333 | D67: =(B67*0.015) -> 174.93 | E67: =$C$7+D67 -> 1008.2633
A68: 12th Payment: | B68: 10829 | C68: =$C$7 -> 833.33333 | D68: =(B68*0.015) -> 162.435 | E68: =$C$7+D68 -> 995.76833
A69: 13th Payment: | B69: 9996 | C69: =$C$7 -> 833.33333 | D69: =(B69*0.015) -> 149.94 | E69: =$C$7+D69 -> 983.27333
... A79: 23rd Payment: | B79: 1666 | C79: =$C$7 -> 833.33333 | D79: =(B79*0.015) -> 24.99 | E79: =$C$7+D79 -> 858.32333
A80: 24th Payment: | B80: 833 | C80: =$C$7 -> 833.33333 | D80: =(B80*0.015) -> 12.495 | E80: =$C$7+D80 -> 845.82833 | I80: Fully Paid
A104: Member's Name: | B104: Escoto, Ronalyn | G104: Loan Amount: | I104: 20000
A105: Membership Number: | H105: Date: | I105: 11/13/23
A106: No. of Loan's Made: | E106: Interest Rate: | I106: 0.015
A107: Mode of Payment: | D107: No. of Months to Pay: | I107: 24
A108: Payment's Made | B108: Present Capital Loan | C108: Constant Payment Deducted to Capital Loan | D108: Interest Amount per Payment | E108: Amount to be Paid | F108: Paid Amount | G108: Date of Payment | H108: Receipt Number | I108: REMARKS
A109: 1st Payment: | B109: =I104 -> 20000 | C109: =I104/I107 -> 833.33333 | D109: =(B109*0.015) -> 300 | E109: =$C$7+D109 -> 1133.3333
A110: 2nd Payment: | B110: 19159 | C110: =$C$7 -> 833.33333 | D110: =(B110*0.015) -> 287.385 | E110: =$C$7+D110 -> 1120.7183
A111: 3rd Payment: | B111: 18326 | C111: =$C$7 -> 833.33333 | D111: =(B111*0.015) -> 274.89 | E111: =$C$7+D111 -> 1108.2233
A112: 4th Payment: | B112: 17493 | C112: =$C$7 -> 833.33333 | D112: =(B112*0.015) -> 262.395 | E112: =$C$7+D112 -> 1095.7283
A113: 5th Payment: | B113: 16660 | C113: =$C$7 -> 833.33333 | D113: =(B113*0.015) -> 249.9 | E113: =$C$7+D113 -> 1083.2333
A114: 6th Payment: | B114: 15827 | C114: =$C$7 -> 833.33333 | D114: =(B114*0.015) -> 237.405 | E114: =$C$7+D114 -> 1070.7383
A115: 7th Payment: | B115: 14994 | C115: =$C$7 -> 833.33333 | D115: =(B115*0.015) -> 224.91 | E115: =$C$7+D115 -> 1058.2433
A116: 8th Payment: | B116: 14161 | C116: =$C$7 -> 833.33333 | D116: =(B116*0.015) -> 212.415 | E116: =$C$7+D116 -> 1045.7483
A117: 9th Payment: | B117: 13328 | C117: =$C$7 -> 833.33333 | D117: =(B117*0.015) -> 199.92 | E117: =$C$7+D117 -> 1033.2533
A118: 10th Payment: | B118: 12495 | C118: =$C$7 -> 833.33333 | D118: =(B118*0.015) -> 187.425 | E118: =$C$7+D118 -> 1020.7583
A119: 11th Payment: | B119: 11662 | C119: =$C$7 -> 833.33333 | D119: =(B119*0.015) -> 174.93 | E119: =$C$7+D119 -> 1008.2633
A120: 12th Payment: | B120: 10829 | C120: =$C$7 -> 833.33333 | D120: =(B120*0.015) -> 162.435 | E120: =$C$7+D120 -> 995.76833
A121: 13th Payment: | B121: 9996 | C121: =$C$7 -> 833.33333 | D121: =(B121*0.015) -> 149.94 | E121: =$C$7+D121 -> 983.27333
... A131: 23rd Payment: | B131: 1666 | C131: =$C$7 -> 833.33333 | D131: =(B131*0.015) -> 24.99 | E131: =$C$7+D131 -> 858.32333
A132: 24th Payment: | B132: 833 | C132: =$C$7 -> 833.33333 | D132: =(B132*0.015) -> 12.495 | E132: =$C$7+D132 -> 845.82833 | I132: Fully Paid
A154: Member's Name: | C154: Mayores, Jenelyn | G154: Loan Amount: | I154: 35000
A155: Membership Number: | H155: Date: | I155: 10/13/23
A156: No. of Loan's Made: | E156: Interest Rate: | I156: 0.015
A157: Mode of Payment: | D157: No. of Months to Pay: | I157: 24
A158: Payment's Made | B158: Present Capital Loan | C158: Constant Payment Deducted to Capital Loan | D158: Interest Amount per Payment | E158: Amount to be Paid | F158: Paid Amount | G158: Date of Payment | H158: Receipt Number | I158: REMARKS
A159: 1st Payment: | B159: =I154 -> 35000 | C159: =I154/I157 -> 1458.3333 | D159: =(B159*0.015) -> 525 | E159: =$C$7+D159 -> 1358.3333
A160: 2nd Payment: | B160: 33534 | C160: 1458 | D160: =(B160*0.015) -> 503.01 | E160: =SUM(C160:D160) -> 1961.01
A161: 3rd Payment: | B161: 32076 | C161: 1458 | D161: =(B161*0.015) -> 481.14 | E161: =SUM(C161:D161) -> 1939.14
A162: 4th Payment: | B162: 30618 | C162: 1458 | D162: =(B162*0.015) -> 459.27 | E162: =SUM(C162:D162) -> 1917.27
